[
  {
    "id_ours": "385c44c555a5a77dcab4e4e76f0dc0ba5bed996a",
    "id_search_engine": "7652130458",
    "url": "https://farm9.staticflickr.com/8162/7652130458_556f11af54_o.jpg",
    "url_type": "url_o",
    "wnid": "n02102973",
    "search_key": "irish water spaniel",
    "search_engine": "flickr",
    "uploader": "becca",
    "date_upload_our_db": "2018-09-23 20:09:14",
    "date_taken": "2012-07-25 20:35:30",
    "date_upload_search_engine": "2012-07-25 12:35:30",
    "width": null,
    "height": null,
    "max_taken_date": "2015-07-11",
    "max_uploaded_date": "2015-07-11",
    "min_taken_date": "2012-07-11",
    "min_uploaded_date": "2012-07-11",
    "search_sort": "date-posted-asc",
    "max_images": 200
  },
  {
    "id_ours": "0d632a427d9867b1e0247bf8561a5f22e78fa59f",
    "id_search_engine": "7775340172",
    "url": "https://farm9.staticflickr.com/8288/7775340172_e972aa9371_k.jpg",
    "url_type": "url_k",
    "wnid": "n02102973",
    "search_key": "irish water spaniel",
    "search_engine": "flickr",
    "uploader": "becca",
    "date_upload_our_db": "2018-09-23 20:09:14",
    "date_taken": "2012-08-13 20:11:47",
    "date_upload_search_engine": "2012-08-13 11:22:43",
    "width": null,
    "height": null,
    "max_taken_date": "2015-07-11",
    "max_uploaded_date": "2015-07-11",
    "min_taken_date": "2012-07-11",
    "min_uploaded_date": "2012-07-11",
    "search_sort": "date-posted-asc",
    "max_images": 200
  },
  {
    "id_ours": "18a79dfcfccca180ac68c2850b587aa29af349a1",
    "id_search_engine": "7812369208",
    "url": "https://farm8.staticflickr.com/7132/7812369208_05e98ed65e_o.jpg",
    "url_type": "url_o",
    "wnid": "n02102973",
    "search_key": "irish water spaniel",
    "search_engine": "flickr",
    "uploader": "becca",
    "date_upload_our_db": "2018-09-23 20:09:14",
    "date_taken": "2012-08-19 07:36:10",
    "date_upload_search_engine": "2012-08-18 20:16:47",
    "width": "2000",
    "height": "3008",
    "max_taken_date": "2015-07-11",
    "max_uploaded_date": "2015-07-11",
    "min_taken_date": "2012-07-11",
    "min_uploaded_date": "2012-07-11",
    "search_sort": "date-posted-asc",
    "max_images": 200
  },
  {
    "id_ours": "106aaa8a6998165fc2bc62a19466b7ad7707a982",
    "id_search_engine": "7812363146",
    "url": "https://farm9.staticflickr.com/8296/7812363146_b27952a6f5_o.jpg",
    "url_type": "url_o",
    "wnid": "n02102973",
    "search_key": "irish water spaniel",
    "search_engine": "flickr",
    "uploader": "becca",
    "date_upload_our_db": "2018-09-23 20:09:14",
    "date_taken": "2012-08-19 07:34:30",
    "date_upload_search_engine": "2012-08-18 20:15:25",
    "width": "2000",
    "height": "3008",
    "max_taken_date": "2015-07-11",
    "max_uploaded_date": "2015-07-11",
    "min_taken_date": "2012-07-11",
    "min_uploaded_date": "2012-07-11",
    "search_sort": "date-posted-asc",
    "max_images": 200
  },
  {
    "id_ours": "61c6f9955494dac437bd300f5efbab949663cc66",
    "id_search_engine": "7812357006",
    "url": "https://farm8.staticflickr.com/7116/7812357006_0d42a89f5a_o.jpg",
    "url_type": "url_o",
    "wnid": "n02102973",
    "search_key": "irish water spaniel",
    "search_engine": "flickr",
    "uploader": "becca",
    "date_upload_our_db": "2018-09-23 20:09:14",
    "date_taken": "2012-08-19 07:33:09",
    "date_upload_search_engine": "2012-08-18 20:14:01",
    "width": "3008",
    "height": "2000",
    "max_taken_date": "2015-07-11",
    "max_uploaded_date": "2015-07-11",
    "min_taken_date": "2012-07-11",
    "min_uploaded_date": "2012-07-11",
    "search_sort": "date-posted-asc",
    "max_images": 200
  },
  {
    "id_ours": "3654460411cb280a5499d6c9e1c1c0903f97a27f",
    "id_search_engine": "7824750860",
    "url": "https://farm9.staticflickr.com/8141/7824750860_4dbac115df_o.jpg",
    "url_type": "url_o",
    "wnid": "n02102973",
    "search_key": "irish water spaniel",
    "search_engine": "flickr",
    "uploader": "becca",
    "date_upload_our_db": "2018-09-23 20:09:14",
    "date_taken": "2012-08-18 12:50:17",
    "date_upload_search_engine": "2012-08-20 10:03:20",
    "width": null,
    "height": null,
    "max_taken_date": "2015-07-11",
    "max_uploaded_date": "2015-07-11",
    "min_taken_date": "2012-07-11",
    "min_uploaded_date": "2012-07-11",
    "search_sort": "date-posted-asc",
    "max_images": 200
  },
  {
    "id_ours": "3432e98f45afe3bbc479a3da906419e4e02df7ab",
    "id_search_engine": "7841950684",
    "url": "https://farm9.staticflickr.com/8434/7841950684_bdf556067e_o.jpg",
    "url_type": "url_o",
    "wnid": "n02102973",
    "search_key": "irish water spaniel",
    "search_engine": "flickr",
    "uploader": "becca",
    "date_upload_our_db": "2018-09-23 20:09:14",
    "date_taken": "2012-08-23 09:16:49",
    "date_upload_search_engine": "2012-08-22 18:50:57",
    "width": "3000",
    "height": "4000",
    "max_taken_date": "2015-07-11",
    "max_uploaded_date": "2015-07-11",
    "min_taken_date": "2012-07-11",
    "min_uploaded_date": "2012-07-11",
    "search_sort": "date-posted-asc",
    "max_images": 200
  },
  {
    "id_ours": "893d63d3e4adb1b53a47f478309ac5dfe697a38c",
    "id_search_engine": "7842103064",
    "url": "https://farm9.staticflickr.com/8292/7842103064_fe2c81b766_o.jpg",
    "url_type": "url_o",
    "wnid": "n02102973",
    "search_key": "irish water spaniel",
    "search_engine": "flickr",
    "uploader": "becca",
    "date_upload_our_db": "2018-09-23 20:09:14",
    "date_taken": "2012-08-23 09:18:49",
    "date_upload_search_engine": "2012-08-22 19:25:11",
    "width": "3591",
    "height": "2693",
    "max_taken_date": "2015-07-11",
    "max_uploaded_date": "2015-07-11",
    "min_taken_date": "2012-07-11",
    "min_uploaded_date": "2012-07-11",
    "search_sort": "date-posted-asc",
    "max_images": 200
  },
  {
    "id_ours": "6b5d5be24f336941dae1fd14c6e96de2bacbb0db",
    "id_search_engine": "7849059936",
    "url": "https://farm9.staticflickr.com/8436/7849059936_63bdcdfd95_k.jpg",
    "url_type": "url_k",
    "wnid": "n02102973",
    "search_key": "irish water spaniel",
    "search_engine": "flickr",
    "uploader": "becca",
    "date_upload_our_db": "2018-09-23 20:09:14",
    "date_taken": "2012-08-14 14:28:52",
    "date_upload_search_engine": "2012-08-23 22:33:29",
    "width": null,
    "height": null,
    "max_taken_date": "2015-07-11",
    "max_uploaded_date": "2015-07-11",
    "min_taken_date": "2012-07-11",
    "min_uploaded_date": "2012-07-11",
    "search_sort": "date-posted-asc",
    "max_images": 200
  },
  {
    "id_ours": "976f234852954feddb007117230ad9bcd194dbec",
    "id_search_engine": "7849066476",
    "url": "https://farm8.staticflickr.com/7261/7849066476_5ea86cc955_k.jpg",
    "url_type": "url_k",
    "wnid": "n02102973",
    "search_key": "irish water spaniel",
    "search_engine": "flickr",
    "uploader": "becca",
    "date_upload_our_db": "2018-09-23 20:09:14",
    "date_taken": "2012-08-14 14:31:30",
    "date_upload_search_engine": "2012-08-23 22:35:25",
    "width": null,
    "height": null,
    "max_taken_date": "2015-07-11",
    "max_uploaded_date": "2015-07-11",
    "min_taken_date": "2012-07-11",
    "min_uploaded_date": "2012-07-11",
    "search_sort": "date-posted-asc",
    "max_images": 200
  },
  {
    "id_ours": "f82ce37080ecc5f74029e2687f79e97fc21fc640",
    "id_search_engine": "7855489442",
    "url": "https://farm9.staticflickr.com/8425/7855489442_bdcb9ff9ee_k.jpg",
    "url_type": "url_k",
    "wnid": "n02102973",
    "search_key": "irish water spaniel",
    "search_engine": "flickr",
    "uploader": "becca",
    "date_upload_our_db": "2018-09-23 20:09:14",
    "date_taken": "2012-08-14 14:49:59",
    "date_upload_search_engine": "2012-08-25 00:23:50",
    "width": null,
    "height": null,
    "max_taken_date": "2015-07-11",
    "max_uploaded_date": "2015-07-11",
    "min_taken_date": "2012-07-11",
    "min_uploaded_date": "2012-07-11",
    "search_sort": "date-posted-asc",
    "max_images": 200
  },
  {
    "id_ours": "00585a83610fad09d5ebe1136438f6293717bca6",
    "id_search_engine": "7855504686",
    "url": "https://farm8.staticflickr.com/7140/7855504686_4737cc3019_k.jpg",
    "url_type": "url_k",
    "wnid": "n02102973",
    "search_key": "irish water spaniel",
    "search_engine": "flickr",
    "uploader": "becca",
    "date_upload_our_db": "2018-09-23 20:09:14",
    "date_taken": "2012-08-14 14:57:23",
    "date_upload_search_engine": "2012-08-25 00:28:49",
    "width": null,
    "height": null,
    "max_taken_date": "2015-07-11",
    "max_uploaded_date": "2015-07-11",
    "min_taken_date": "2012-07-11",
    "min_uploaded_date": "2012-07-11",
    "search_sort": "date-posted-asc",
    "max_images": 200
  },
  {
    "id_ours": "fc0ec552c2f01fd4a39cec623a83a24a9d43c63c",
    "id_search_engine": "7855501630",
    "url": "https://farm8.staticflickr.com/7109/7855501630_e164cb01d5_k.jpg",
    "url_type": "url_k",
    "wnid": "n02102973",
    "search_key": "irish water spaniel",
    "search_engine": "flickr",
    "uploader": "becca",
    "date_upload_our_db": "2018-09-23 20:09:14",
    "date_taken": "2012-08-14 14:57:22",
    "date_upload_search_engine": "2012-08-25 00:27:48",
    "width": null,
    "height": null,
    "max_taken_date": "2015-07-11",
    "max_uploaded_date": "2015-07-11",
    "min_taken_date": "2012-07-11",
    "min_uploaded_date": "2012-07-11",
    "search_sort": "date-posted-asc",
    "max_images": 200
  },
  {
    "id_ours": "8b47ec7394b2a5bea8a83a67de6406ea7adeaab0",
    "id_search_engine": "7855485756",
    "url": "https://farm8.staticflickr.com/7278/7855485756_4d2b69f980_k.jpg",
    "url_type": "url_k",
    "wnid": "n02102973",
    "search_key": "irish water spaniel",
    "search_engine": "flickr",
    "uploader": "becca",
    "date_upload_our_db": "2018-09-23 20:09:14",
    "date_taken": "2012-08-14 14:49:57",
    "date_upload_search_engine": "2012-08-25 00:22:39",
    "width": null,
    "height": null,
    "max_taken_date": "2015-07-11",
    "max_uploaded_date": "2015-07-11",
    "min_taken_date": "2012-07-11",
    "min_uploaded_date": "2012-07-11",
    "search_sort": "date-posted-asc",
    "max_images": 200
  },
  {
    "id_ours": "382c7be00e7f56d0174d1739e52b99475baa822a",
    "id_search_engine": "7855481232",
    "url": "https://farm9.staticflickr.com/8297/7855481232_85eccdb1a4_k.jpg",
    "url_type": "url_k",
    "wnid": "n02102973",
    "search_key": "irish water spaniel",
    "search_engine": "flickr",
    "uploader": "becca",
    "date_upload_our_db": "2018-09-23 20:09:14",
    "date_taken": "2012-08-14 14:49:04",
    "date_upload_search_engine": "2012-08-25 00:21:18",
    "width": null,
    "height": null,
    "max_taken_date": "2015-07-11",
    "max_uploaded_date": "2015-07-11",
    "min_taken_date": "2012-07-11",
    "min_uploaded_date": "2012-07-11",
    "search_sort": "date-posted-asc",
    "max_images": 200
  },
  {
    "id_ours": "dd319bc835cece1381f640310117d3dbd9e32857",
    "id_search_engine": "7867074446",
    "url": "https://farm9.staticflickr.com/8286/7867074446_8169a69975_o.jpg",
    "url_type": "url_o",
    "wnid": "n02102973",
    "search_key": "irish water spaniel",
    "search_engine": "flickr",
    "uploader": "becca",
    "date_upload_our_db": "2018-09-23 20:09:14",
    "date_taken": "2012-08-26 11:14:02",
    "date_upload_search_engine": "2012-08-26 13:50:44",
    "width": "4592",
    "height": "2576",
    "max_taken_date": "2015-07-11",
    "max_uploaded_date": "2015-07-11",
    "min_taken_date": "2012-07-11",
    "min_uploaded_date": "2012-07-11",
    "search_sort": "date-posted-asc",
    "max_images": 200
  },
  {
    "id_ours": "16e2bff48f963eec5573bb817b16350ace875058",
    "id_search_engine": "7885326506",
    "url": "https://farm9.staticflickr.com/8030/7885326506_7533e784b7_o.jpg",
    "url_type": "url_o",
    "wnid": "n02102973",
    "search_key": "irish water spaniel",
    "search_engine": "flickr",
    "uploader": "becca",
    "date_upload_our_db": "2018-09-23 20:09:14",
    "date_taken": "2012-08-28 21:28:07",
    "date_upload_search_engine": "2012-08-28 22:04:18",
    "width": "2506",
    "height": "3129",
    "max_taken_date": "2015-07-11",
    "max_uploaded_date": "2015-07-11",
    "min_taken_date": "2012-07-11",
    "min_uploaded_date": "2012-07-11",
    "search_sort": "date-posted-asc",
    "max_images": 200
  },
  {
    "id_ours": "0c4a0303cb78ad472c3cd8e82795bb2fde5f3637",
    "id_search_engine": "7890186894",
    "url": "https://farm9.staticflickr.com/8170/7890186894_7ac9be664a_o.jpg",
    "url_type": "url_o",
    "wnid": "n02102973",
    "search_key": "irish water spaniel",
    "search_engine": "flickr",
    "uploader": "becca",
    "date_upload_our_db": "2018-09-23 20:09:14",
    "date_taken": "2012-08-16 15:52:27",
    "date_upload_search_engine": "2012-08-29 14:57:54",
    "width": "3264",
    "height": "2448",
    "max_taken_date": "2015-07-11",
    "max_uploaded_date": "2015-07-11",
    "min_taken_date": "2012-07-11",
    "min_uploaded_date": "2012-07-11",
    "search_sort": "date-posted-asc",
    "max_images": 200
  },
  {
    "id_ours": "f8d73753a5001849d1a32eef8a8ea96d465b08f1",
    "id_search_engine": "8134973781",
    "url": "https://farm9.staticflickr.com/8193/8134973781_19450d82b8_o.jpg",
    "url_type": "url_o",
    "wnid": "n02102973",
    "search_key": "irish water spaniel",
    "search_engine": "flickr",
    "uploader": "becca",
    "date_upload_our_db": "2018-09-23 20:09:14",
    "date_taken": "2012-10-29 14:14:03",
    "date_upload_search_engine": "2012-10-29 07:24:54",
    "width": null,
    "height": null,
    "max_taken_date": "2015-07-11",
    "max_uploaded_date": "2015-07-11",
    "min_taken_date": "2012-07-11",
    "min_uploaded_date": "2012-07-11",
    "search_sort": "date-posted-asc",
    "max_images": 200
  },
  {
    "id_ours": "e6b408ce1560c0db9797e9673fc6b2663ec28102",
    "id_search_engine": "8337767948",
    "url": "https://farm9.staticflickr.com/8071/8337767948_c505f004bc_c.jpg",
    "url_type": "url_c",
    "wnid": "n02102973",
    "search_key": "irish water spaniel",
    "search_engine": "flickr",
    "uploader": "becca",
    "date_upload_our_db": "2018-09-23 20:09:14",
    "date_taken": "2013-01-02 10:46:36",
    "date_upload_search_engine": "2013-01-02 02:46:36",
    "width": null,
    "height": null,
    "max_taken_date": "2015-07-11",
    "max_uploaded_date": "2015-07-11",
    "min_taken_date": "2012-07-11",
    "min_uploaded_date": "2012-07-11",
    "search_sort": "date-posted-asc",
    "max_images": 200
  },
  {
    "id_ours": "5312fe2c239af60d2400f467e931e07c665a36b0",
    "id_search_engine": "8581464824",
    "url": "https://farm9.staticflickr.com/8250/8581464824_a1fc1b8254_o.jpg",
    "url_type": "url_o",
    "wnid": "n02102973",
    "search_key": "irish water spaniel",
    "search_engine": "flickr",
    "uploader": "becca",
    "date_upload_our_db": "2018-09-23 20:09:14",
    "date_taken": "2013-03-23 07:59:22",
    "date_upload_search_engine": "2013-03-22 15:18:41",
    "width": "1349",
    "height": "1429",
    "max_taken_date": "2015-07-11",
    "max_uploaded_date": "2015-07-11",
    "min_taken_date": "2012-07-11",
    "min_uploaded_date": "2012-07-11",
    "search_sort": "date-posted-asc",
    "max_images": 200
  },
  {
    "id_ours": "417c774927adb9636c6d313ff8c629bc8cabfa66",
    "id_search_engine": "8598585812",
    "url": "https://farm9.staticflickr.com/8108/8598585812_f56a265c42_k.jpg",
    "url_type": "url_k",
    "wnid": "n02102973",
    "search_key": "irish water spaniel",
    "search_engine": "flickr",
    "uploader": "becca",
    "date_upload_our_db": "2018-09-23 20:09:14",
    "date_taken": "2013-03-16 13:31:11",
    "date_upload_search_engine": "2013-03-28 10:52:36",
    "width": null,
    "height": null,
    "max_taken_date": "2015-07-11",
    "max_uploaded_date": "2015-07-11",
    "min_taken_date": "2012-07-11",
    "min_uploaded_date": "2012-07-11",
    "search_sort": "date-posted-asc",
    "max_images": 200
  },
  {
    "id_ours": "6b26e1b11bc62ea519c096890f4804154b74f7a7",
    "id_search_engine": "8999851602",
    "url": "https://farm8.staticflickr.com/7438/8999851602_575f7b7bd4_o.jpg",
    "url_type": "url_o",
    "wnid": "n02102973",
    "search_key": "irish water spaniel",
    "search_engine": "flickr",
    "uploader": "becca",
    "date_upload_our_db": "2018-09-23 20:09:14",
    "date_taken": "2013-06-09 10:27:41",
    "date_upload_search_engine": "2013-06-09 12:43:43",
    "width": "2592",
    "height": "3888",
    "max_taken_date": "2015-07-11",
    "max_uploaded_date": "2015-07-11",
    "min_taken_date": "2012-07-11",
    "min_uploaded_date": "2012-07-11",
    "search_sort": "date-posted-asc",
    "max_images": 200
  },
  {
    "id_ours": "e5966804444c36ca1b7b5b66ea065ee549ab4f5a",
    "id_search_engine": "9027368779",
    "url": "https://farm3.staticflickr.com/2878/9027368779_bf7153cb8c_o.jpg",
    "url_type": "url_o",
    "wnid": "n02102973",
    "search_key": "irish water spaniel",
    "search_engine": "flickr",
    "uploader": "becca",
    "date_upload_our_db": "2018-09-23 20:09:14",
    "date_taken": "2013-06-09 01:19:34",
    "date_upload_search_engine": "2013-06-12 15:33:49",
    "width": "2136",
    "height": "1424",
    "max_taken_date": "2015-07-11",
    "max_uploaded_date": "2015-07-11",
    "min_taken_date": "2012-07-11",
    "min_uploaded_date": "2012-07-11",
    "search_sort": "date-posted-asc",
    "max_images": 200
  },
  {
    "id_ours": "024242bdfd6ecfff1a07cc001d9f3483e82ea250",
    "id_search_engine": "9848677864",
    "url": "https://farm4.staticflickr.com/3694/9848677864_7055ae975c_o.jpg",
    "url_type": "url_o",
    "wnid": "n02102973",
    "search_key": "irish water spaniel",
    "search_engine": "flickr",
    "uploader": "becca",
    "date_upload_our_db": "2018-09-23 20:09:14",
    "date_taken": "2013-09-20 04:27:08",
    "date_upload_search_engine": "2013-09-20 22:44:43",
    "width": null,
    "height": null,
    "max_taken_date": "2015-07-11",
    "max_uploaded_date": "2015-07-11",
    "min_taken_date": "2012-07-11",
    "min_uploaded_date": "2012-07-11",
    "search_sort": "date-posted-asc",
    "max_images": 200
  },
  {
    "id_ours": "ba5a138ec50e4e7b5e8bd9cb372a9bc079e6937a",
    "id_search_engine": "10065625246",
    "url": "https://farm6.staticflickr.com/5446/10065625246_dc639a5d72_o.jpg",
    "url_type": "url_o",
    "wnid": "n02102973",
    "search_key": "irish water spaniel",
    "search_engine": "flickr",
    "uploader": "becca",
    "date_upload_our_db": "2018-09-23 20:09:14",
    "date_taken": "2013-10-03 09:55:43",
    "date_upload_search_engine": "2013-10-03 01:03:32",
    "width": null,
    "height": null,
    "max_taken_date": "2015-07-11",
    "max_uploaded_date": "2015-07-11",
    "min_taken_date": "2012-07-11",
    "min_uploaded_date": "2012-07-11",
    "search_sort": "date-posted-asc",
    "max_images": 200
  },
  {
    "id_ours": "4a6bed5ebf1744bbe486f627b129efddbfc93f99",
    "id_search_engine": "10615025175",
    "url": "https://farm8.staticflickr.com/7344/10615025175_034a340d3b_o.jpg",
    "url_type": "url_o",
    "wnid": "n02102973",
    "search_key": "irish water spaniel",
    "search_engine": "flickr",
    "uploader": "becca",
    "date_upload_our_db": "2018-09-23 20:09:14",
    "date_taken": "2013-10-28 14:32:38",
    "date_upload_search_engine": "2013-11-01 13:34:40",
    "width": null,
    "height": null,
    "max_taken_date": "2015-07-11",
    "max_uploaded_date": "2015-07-11",
    "min_taken_date": "2012-07-11",
    "min_uploaded_date": "2012-07-11",
    "search_sort": "date-posted-asc",
    "max_images": 200
  },
  {
    "id_ours": "3924433109c0b31fce7db4385e0a191aa0d3667d",
    "id_search_engine": "10986087863",
    "url": "https://farm4.staticflickr.com/3712/10986087863_16fd62f64e_o.jpg",
    "url_type": "url_o",
    "wnid": "n02102973",
    "search_key": "irish water spaniel",
    "search_engine": "flickr",
    "uploader": "becca",
    "date_upload_our_db": "2018-09-23 20:09:14",
    "date_taken": "2013-11-22 08:12:21",
    "date_upload_search_engine": "2013-11-21 16:04:57",
    "width": null,
    "height": null,
    "max_taken_date": "2015-07-11",
    "max_uploaded_date": "2015-07-11",
    "min_taken_date": "2012-07-11",
    "min_uploaded_date": "2012-07-11",
    "search_sort": "date-posted-asc",
    "max_images": 200
  },
  {
    "id_ours": "d19e5128aa720bc072288d0e39061a113178d0ad",
    "id_search_engine": "11221191265",
    "url": "https://farm6.staticflickr.com/5482/11221191265_72d63cd764_o.jpg",
    "url_type": "url_o",
    "wnid": "n02102973",
    "search_key": "irish water spaniel",
    "search_engine": "flickr",
    "uploader": "becca",
    "date_upload_our_db": "2018-09-23 20:09:14",
    "date_taken": "2013-12-05 05:41:05",
    "date_upload_search_engine": "2013-12-05 05:41:05",
    "width": null,
    "height": null,
    "max_taken_date": "2015-07-11",
    "max_uploaded_date": "2015-07-11",
    "min_taken_date": "2012-07-11",
    "min_uploaded_date": "2012-07-11",
    "search_sort": "date-posted-asc",
    "max_images": 200
  },
  {
    "id_ours": "f51cff9e0b2b81d356c602acafdb02dd561ec5be",
    "id_search_engine": "11685052605",
    "url": "https://farm4.staticflickr.com/3751/11685052605_b2d5fdab1c_c.jpg",
    "url_type": "url_c",
    "wnid": "n02102973",
    "search_key": "irish water spaniel",
    "search_engine": "flickr",
    "uploader": "becca",
    "date_upload_our_db": "2018-09-23 20:09:14",
    "date_taken": "2014-01-01 07:57:21",
    "date_upload_search_engine": "2014-01-01 05:36:32",
    "width": null,
    "height": null,
    "max_taken_date": "2015-07-11",
    "max_uploaded_date": "2015-07-11",
    "min_taken_date": "2012-07-11",
    "min_uploaded_date": "2012-07-11",
    "search_sort": "date-posted-asc",
    "max_images": 200
  },
  {
    "id_ours": "feb88b5b2559707dd3a1cb56a4bf5d6412da143b",
    "id_search_engine": "11685834246",
    "url": "https://farm8.staticflickr.com/7399/11685834246_b6d87e9e16_c.jpg",
    "url_type": "url_c",
    "wnid": "n02102973",
    "search_key": "irish water spaniel",
    "search_engine": "flickr",
    "uploader": "becca",
    "date_upload_our_db": "2018-09-23 20:09:14",
    "date_taken": "2014-01-01 07:57:50",
    "date_upload_search_engine": "2014-01-01 05:36:31",
    "width": null,
    "height": null,
    "max_taken_date": "2015-07-11",
    "max_uploaded_date": "2015-07-11",
    "min_taken_date": "2012-07-11",
    "min_uploaded_date": "2012-07-11",
    "search_sort": "date-posted-asc",
    "max_images": 200
  },
  {
    "id_ours": "eed40e1f407d9f878e675ea770799bf449e304cc",
    "id_search_engine": "11685318833",
    "url": "https://farm8.staticflickr.com/7396/11685318833_e2d514ee4d_c.jpg",
    "url_type": "url_c",
    "wnid": "n02102973",
    "search_key": "irish water spaniel",
    "search_engine": "flickr",
    "uploader": "becca",
    "date_upload_our_db": "2018-09-23 20:09:14",
    "date_taken": "2014-01-01 07:58:22",
    "date_upload_search_engine": "2014-01-01 05:36:31",
    "width": null,
    "height": null,
    "max_taken_date": "2015-07-11",
    "max_uploaded_date": "2015-07-11",
    "min_taken_date": "2012-07-11",
    "min_uploaded_date": "2012-07-11",
    "search_sort": "date-posted-asc",
    "max_images": 200
  },
  {
    "id_ours": "6e6ebe95dc8855836e3794b7f05dd498e07b1963",
    "id_search_engine": "12226415864",
    "url": "https://farm8.staticflickr.com/7339/12226415864_70038351be_o.jpg",
    "url_type": "url_o",
    "wnid": "n02102973",
    "search_key": "irish water spaniel",
    "search_engine": "flickr",
    "uploader": "becca",
    "date_upload_our_db": "2018-09-23 20:09:14",
    "date_taken": "2014-01-30 14:49:12",
    "date_upload_search_engine": "2014-01-30 13:35:01",
    "width": null,
    "height": null,
    "max_taken_date": "2015-07-11",
    "max_uploaded_date": "2015-07-11",
    "min_taken_date": "2012-07-11",
    "min_uploaded_date": "2012-07-11",
    "search_sort": "date-posted-asc",
    "max_images": 200
  },
  {
    "id_ours": "535852dd5b27db02c47f800e0d626e332c011cb2",
    "id_search_engine": "12976467525",
    "url": "https://farm3.staticflickr.com/2476/12976467525_5a56f4ba52_o.jpg",
    "url_type": "url_o",
    "wnid": "n02102973",
    "search_key": "irish water spaniel",
    "search_engine": "flickr",
    "uploader": "becca",
    "date_upload_our_db": "2018-09-23 20:09:14",
    "date_taken": "2014-03-06 13:19:16",
    "date_upload_search_engine": "2014-03-06 13:03:47",
    "width": "1024",
    "height": "680",
    "max_taken_date": "2015-07-11",
    "max_uploaded_date": "2015-07-11",
    "min_taken_date": "2012-07-11",
    "min_uploaded_date": "2012-07-11",
    "search_sort": "date-posted-asc",
    "max_images": 200
  },
  {
    "id_ours": "7b6adca860ac9bbd1b9086515f436f9117a129c9",
    "id_search_engine": "12996839115",
    "url": "https://farm3.staticflickr.com/2321/12996839115_3992851d96_o.jpg",
    "url_type": "url_o",
    "wnid": "n02102973",
    "search_key": "irish water spaniel",
    "search_engine": "flickr",
    "uploader": "becca",
    "date_upload_our_db": "2018-09-23 20:09:14",
    "date_taken": "2014-03-07 17:21:10",
    "date_upload_search_engine": "2014-03-07 13:26:37",
    "width": null,
    "height": null,
    "max_taken_date": "2015-07-11",
    "max_uploaded_date": "2015-07-11",
    "min_taken_date": "2012-07-11",
    "min_uploaded_date": "2012-07-11",
    "search_sort": "date-posted-asc",
    "max_images": 200
  },
  {
    "id_ours": "d1a12c15893873111663fdbbfcd94bfa170440e0",
    "id_search_engine": "12996843675",
    "url": "https://farm3.staticflickr.com/2835/12996843675_eae2f1d510_o.jpg",
    "url_type": "url_o",
    "wnid": "n02102973",
    "search_key": "irish water spaniel",
    "search_engine": "flickr",
    "uploader": "becca",
    "date_upload_our_db": "2018-09-23 20:09:14",
    "date_taken": "2014-03-07 17:18:01",
    "date_upload_search_engine": "2014-03-07 13:26:34",
    "width": null,
    "height": null,
    "max_taken_date": "2015-07-11",
    "max_uploaded_date": "2015-07-11",
    "min_taken_date": "2012-07-11",
    "min_uploaded_date": "2012-07-11",
    "search_sort": "date-posted-asc",
    "max_images": 200
  },
  {
    "id_ours": "faf40992ab0d4dfc682b8a81aa2fdfc9fd5a9b2e",
    "id_search_engine": "12996997313",
    "url": "https://farm3.staticflickr.com/2064/12996997313_03f299f44f_o.jpg",
    "url_type": "url_o",
    "wnid": "n02102973",
    "search_key": "irish water spaniel",
    "search_engine": "flickr",
    "uploader": "becca",
    "date_upload_our_db": "2018-09-23 20:09:14",
    "date_taken": "2014-03-07 17:08:10",
    "date_upload_search_engine": "2014-03-07 13:26:24",
    "width": null,
    "height": null,
    "max_taken_date": "2015-07-11",
    "max_uploaded_date": "2015-07-11",
    "min_taken_date": "2012-07-11",
    "min_uploaded_date": "2012-07-11",
    "search_sort": "date-posted-asc",
    "max_images": 200
  },
  {
    "id_ours": "7e14e37516da6db8b658507f3a1045811d5f8c36",
    "id_search_engine": "12997082433",
    "url": "https://farm4.staticflickr.com/3090/12997082433_122fe16fa2_o.jpg",
    "url_type": "url_o",
    "wnid": "n02102973",
    "search_key": "irish water spaniel",
    "search_engine": "flickr",
    "uploader": "becca",
    "date_upload_our_db": "2018-09-23 20:09:14",
    "date_taken": "2014-03-07 16:26:17",
    "date_upload_search_engine": "2014-03-07 13:25:55",
    "width": null,
    "height": null,
    "max_taken_date": "2015-07-11",
    "max_uploaded_date": "2015-07-11",
    "min_taken_date": "2012-07-11",
    "min_uploaded_date": "2012-07-11",
    "search_sort": "date-posted-asc",
    "max_images": 200
  },
  {
    "id_ours": "1c10059c7c4dfd2d605ca743cdec0a888291b518",
    "id_search_engine": "12996903175",
    "url": "https://farm4.staticflickr.com/3059/12996903175_e7afc60ab8_o.jpg",
    "url_type": "url_o",
    "wnid": "n02102973",
    "search_key": "irish water spaniel",
    "search_engine": "flickr",
    "uploader": "becca",
    "date_upload_our_db": "2018-09-23 20:09:14",
    "date_taken": "2014-03-07 16:59:52",
    "date_upload_search_engine": "2014-03-07 13:26:13",
    "width": null,
    "height": null,
    "max_taken_date": "2015-07-11",
    "max_uploaded_date": "2015-07-11",
    "min_taken_date": "2012-07-11",
    "min_uploaded_date": "2012-07-11",
    "search_sort": "date-posted-asc",
    "max_images": 200
  },
  {
    "id_ours": "3d024d2171fa191da3c4ef93554a94f82c18405a",
    "id_search_engine": "12997266004",
    "url": "https://farm4.staticflickr.com/3234/12997266004_2f9decd704_o.jpg",
    "url_type": "url_o",
    "wnid": "n02102973",
    "search_key": "irish water spaniel",
    "search_engine": "flickr",
    "uploader": "becca",
    "date_upload_our_db": "2018-09-23 20:09:14",
    "date_taken": "2014-03-07 17:08:06",
    "date_upload_search_engine": "2014-03-07 13:26:23",
    "width": null,
    "height": null,
    "max_taken_date": "2015-07-11",
    "max_uploaded_date": "2015-07-11",
    "min_taken_date": "2012-07-11",
    "min_uploaded_date": "2012-07-11",
    "search_sort": "date-posted-asc",
    "max_images": 200
  },
  {
    "id_ours": "5fa67a68b7e145c46419985aa37b4d9a1073ca4c",
    "id_search_engine": "12997083843",
    "url": "https://farm8.staticflickr.com/7436/12997083843_13b36599b0_o.jpg",
    "url_type": "url_o",
    "wnid": "n02102973",
    "search_key": "irish water spaniel",
    "search_engine": "flickr",
    "uploader": "becca",
    "date_upload_our_db": "2018-09-23 20:09:14",
    "date_taken": "2014-03-07 16:24:56",
    "date_upload_search_engine": "2014-03-07 13:25:54",
    "width": null,
    "height": null,
    "max_taken_date": "2015-07-11",
    "max_uploaded_date": "2015-07-11",
    "min_taken_date": "2012-07-11",
    "min_uploaded_date": "2012-07-11",
    "search_sort": "date-posted-asc",
    "max_images": 200
  },
  {
    "id_ours": "b2aa14d7acfa142418ae88149669516f7554f523",
    "id_search_engine": "12997234374",
    "url": "https://farm8.staticflickr.com/7307/12997234374_503ba074b5_o.jpg",
    "url_type": "url_o",
    "wnid": "n02102973",
    "search_key": "irish water spaniel",
    "search_engine": "flickr",
    "uploader": "becca",
    "date_upload_our_db": "2018-09-23 20:09:14",
    "date_taken": "2014-03-07 16:24:00",
    "date_upload_search_engine": "2014-03-07 13:25:53",
    "width": null,
    "height": null,
    "max_taken_date": "2015-07-11",
    "max_uploaded_date": "2015-07-11",
    "min_taken_date": "2012-07-11",
    "min_uploaded_date": "2012-07-11",
    "search_sort": "date-posted-asc",
    "max_images": 200
  },
  {
    "id_ours": "1c7116164f5ec5610e37794b26e3a2a96e70a3e0",
    "id_search_engine": "12997335444",
    "url": "https://farm8.staticflickr.com/7409/12997335444_b81276bd7e_o.jpg",
    "url_type": "url_o",
    "wnid": "n02102973",
    "search_key": "irish water spaniel",
    "search_engine": "flickr",
    "uploader": "becca",
    "date_upload_our_db": "2018-09-23 20:09:14",
    "date_taken": "2014-03-07 16:37:24",
    "date_upload_search_engine": "2014-03-07 13:26:01",
    "width": null,
    "height": null,
    "max_taken_date": "2015-07-11",
    "max_uploaded_date": "2015-07-11",
    "min_taken_date": "2012-07-11",
    "min_uploaded_date": "2012-07-11",
    "search_sort": "date-posted-asc",
    "max_images": 200
  },
  {
    "id_ours": "0f0b45eea371fc2d03d559406a7c36f1ba172918",
    "id_search_engine": "12997068763",
    "url": "https://farm8.staticflickr.com/7428/12997068763_45177459cb_o.jpg",
    "url_type": "url_o",
    "wnid": "n02102973",
    "search_key": "irish water spaniel",
    "search_engine": "flickr",
    "uploader": "becca",
    "date_upload_our_db": "2018-09-23 20:09:14",
    "date_taken": "2014-03-07 16:37:23",
    "date_upload_search_engine": "2014-03-07 13:26:01",
    "width": null,
    "height": null,
    "max_taken_date": "2015-07-11",
    "max_uploaded_date": "2015-07-11",
    "min_taken_date": "2012-07-11",
    "min_uploaded_date": "2012-07-11",
    "search_sort": "date-posted-asc",
    "max_images": 200
  },
  {
    "id_ours": "d8fbcf81cbaa456f4e4c62086cecb0607532978f",
    "id_search_engine": "12996881445",
    "url": "https://farm8.staticflickr.com/7338/12996881445_3127d07c58_o.jpg",
    "url_type": "url_o",
    "wnid": "n02102973",
    "search_key": "irish water spaniel",
    "search_engine": "flickr",
    "uploader": "becca",
    "date_upload_our_db": "2018-09-23 20:09:14",
    "date_taken": "2014-03-07 17:02:18",
    "date_upload_search_engine": "2014-03-07 13:26:20",
    "width": null,
    "height": null,
    "max_taken_date": "2015-07-11",
    "max_uploaded_date": "2015-07-11",
    "min_taken_date": "2012-07-11",
    "min_uploaded_date": "2012-07-11",
    "search_sort": "date-posted-asc",
    "max_images": 200
  },
  {
    "id_ours": "b8137b0bb79d41c082885d970f5d395674a708d1",
    "id_search_engine": "12997358234",
    "url": "https://farm8.staticflickr.com/7303/12997358234_b4ec1ba6b0_o.jpg",
    "url_type": "url_o",
    "wnid": "n02102973",
    "search_key": "irish water spaniel",
    "search_engine": "flickr",
    "uploader": "becca",
    "date_upload_our_db": "2018-09-23 20:09:14",
    "date_taken": "2014-03-07 16:22:12",
    "date_upload_search_engine": "2014-03-07 13:25:52",
    "width": null,
    "height": null,
    "max_taken_date": "2015-07-11",
    "max_uploaded_date": "2015-07-11",
    "min_taken_date": "2012-07-11",
    "min_uploaded_date": "2012-07-11",
    "search_sort": "date-posted-asc",
    "max_images": 200
  },
  {
    "id_ours": "acfa6328027c05f97ca449388115424ad90f17b3",
    "id_search_engine": "12997096643",
    "url": "https://farm4.staticflickr.com/3024/12997096643_b44e37896a_o.jpg",
    "url_type": "url_o",
    "wnid": "n02102973",
    "search_key": "irish water spaniel",
    "search_engine": "flickr",
    "uploader": "becca",
    "date_upload_our_db": "2018-09-23 20:09:14",
    "date_taken": "2014-03-07 16:21:22",
    "date_upload_search_engine": "2014-03-07 13:25:50",
    "width": null,
    "height": null,
    "max_taken_date": "2015-07-11",
    "max_uploaded_date": "2015-07-11",
    "min_taken_date": "2012-07-11",
    "min_uploaded_date": "2012-07-11",
    "search_sort": "date-posted-asc",
    "max_images": 200
  },
  {
    "id_ours": "e7ff63119c9022fcb34e5a71731ae0a24a5b3f1a",
    "id_search_engine": "12997252954",
    "url": "https://farm8.staticflickr.com/7416/12997252954_f4eea37fde_o.jpg",
    "url_type": "url_o",
    "wnid": "n02102973",
    "search_key": "irish water spaniel",
    "search_engine": "flickr",
    "uploader": "becca",
    "date_upload_our_db": "2018-09-23 20:09:14",
    "date_taken": "2014-03-07 17:12:20",
    "date_upload_search_engine": "2014-03-07 13:26:28",
    "width": null,
    "height": null,
    "max_taken_date": "2015-07-11",
    "max_uploaded_date": "2015-07-11",
    "min_taken_date": "2012-07-11",
    "min_uploaded_date": "2012-07-11",
    "search_sort": "date-posted-asc",
    "max_images": 200
  },
  {
    "id_ours": "18550e57e03b54e2e8b0971f977bdc13b56d7216",
    "id_search_engine": "12997245584",
    "url": "https://farm3.staticflickr.com/2659/12997245584_2bb5988f8a_o.jpg",
    "url_type": "url_o",
    "wnid": "n02102973",
    "search_key": "irish water spaniel",
    "search_engine": "flickr",
    "uploader": "becca",
    "date_upload_our_db": "2018-09-23 20:09:14",
    "date_taken": "2014-03-07 17:16:43",
    "date_upload_search_engine": "2014-03-07 13:26:32",
    "width": null,
    "height": null,
    "max_taken_date": "2015-07-11",
    "max_uploaded_date": "2015-07-11",
    "min_taken_date": "2012-07-11",
    "min_uploaded_date": "2012-07-11",
    "search_sort": "date-posted-asc",
    "max_images": 200
  },
  {
    "id_ours": "2ec2c9abb86b267a00c9f6436942d749e6893177",
    "id_search_engine": "12996886575",
    "url": "https://farm8.staticflickr.com/7446/12996886575_30f0492d0f_o.jpg",
    "url_type": "url_o",
    "wnid": "n02102973",
    "search_key": "irish water spaniel",
    "search_engine": "flickr",
    "uploader": "becca",
    "date_upload_our_db": "2018-09-23 20:09:14",
    "date_taken": "2014-03-07 17:01:29",
    "date_upload_search_engine": "2014-03-07 13:26:18",
    "width": null,
    "height": null,
    "max_taken_date": "2015-07-11",
    "max_uploaded_date": "2015-07-11",
    "min_taken_date": "2012-07-11",
    "min_uploaded_date": "2012-07-11",
    "search_sort": "date-posted-asc",
    "max_images": 200
  },
  {
    "id_ours": "738845e8557dda2ddf9e6b7ea70306f768627d85",
    "id_search_engine": "12997071843",
    "url": "https://farm3.staticflickr.com/2425/12997071843_f2462faa9a_o.jpg",
    "url_type": "url_o",
    "wnid": "n02102973",
    "search_key": "irish water spaniel",
    "search_engine": "flickr",
    "uploader": "becca",
    "date_upload_our_db": "2018-09-23 20:09:14",
    "date_taken": "2014-03-07 16:33:25",
    "date_upload_search_engine": "2014-03-07 13:25:59",
    "width": null,
    "height": null,
    "max_taken_date": "2015-07-11",
    "max_uploaded_date": "2015-07-11",
    "min_taken_date": "2012-07-11",
    "min_uploaded_date": "2012-07-11",
    "search_sort": "date-posted-asc",
    "max_images": 200
  },
  {
    "id_ours": "570c83e67291203f2693cb960a9c6fd0ff841961",
    "id_search_engine": "12996846455",
    "url": "https://farm8.staticflickr.com/7383/12996846455_7bcede3f51_o.jpg",
    "url_type": "url_o",
    "wnid": "n02102973",
    "search_key": "irish water spaniel",
    "search_engine": "flickr",
    "uploader": "becca",
    "date_upload_our_db": "2018-09-23 20:09:14",
    "date_taken": "2014-03-07 17:17:36",
    "date_upload_search_engine": "2014-03-07 13:26:33",
    "width": null,
    "height": null,
    "max_taken_date": "2015-07-11",
    "max_uploaded_date": "2015-07-11",
    "min_taken_date": "2012-07-11",
    "min_uploaded_date": "2012-07-11",
    "search_sort": "date-posted-asc",
    "max_images": 200
  },
  {
    "id_ours": "5147ede2dfe4abe245d234af1208fd5ab5aff9d3",
    "id_search_engine": "12997248554",
    "url": "https://farm4.staticflickr.com/3259/12997248554_7b317af68f_o.jpg",
    "url_type": "url_o",
    "wnid": "n02102973",
    "search_key": "irish water spaniel",
    "search_engine": "flickr",
    "uploader": "becca",
    "date_upload_our_db": "2018-09-23 20:09:14",
    "date_taken": "2014-03-07 17:14:43",
    "date_upload_search_engine": "2014-03-07 13:26:31",
    "width": null,
    "height": null,
    "max_taken_date": "2015-07-11",
    "max_uploaded_date": "2015-07-11",
    "min_taken_date": "2012-07-11",
    "min_uploaded_date": "2012-07-11",
    "search_sort": "date-posted-asc",
    "max_images": 200
  },
  {
    "id_ours": "20519396cae2ccd817be6881665e1f385f89e8c2",
    "id_search_engine": "12997103293",
    "url": "https://farm3.staticflickr.com/2509/12997103293_9fb528e8c1_o.jpg",
    "url_type": "url_o",
    "wnid": "n02102973",
    "search_key": "irish water spaniel",
    "search_engine": "flickr",
    "uploader": "becca",
    "date_upload_our_db": "2018-09-23 20:09:14",
    "date_taken": "2014-03-07 16:20:37",
    "date_upload_search_engine": "2014-03-07 13:25:48",
    "width": null,
    "height": null,
    "max_taken_date": "2015-07-11",
    "max_uploaded_date": "2015-07-11",
    "min_taken_date": "2012-07-11",
    "min_uploaded_date": "2012-07-11",
    "search_sort": "date-posted-asc",
    "max_images": 200
  },
  {
    "id_ours": "6cd28b5ccb7e6d4d22a6cc477ca983c3af0da6fc",
    "id_search_engine": "13179262004",
    "url": "https://farm4.staticflickr.com/3665/13179262004_c762e85203_o.jpg",
    "url_type": "url_o",
    "wnid": "n02102973",
    "search_key": "irish water spaniel",
    "search_engine": "flickr",
    "uploader": "becca",
    "date_upload_our_db": "2018-09-23 20:09:14",
    "date_taken": "2014-03-15 13:55:17",
    "date_upload_search_engine": "2014-03-15 17:40:37",
    "width": null,
    "height": null,
    "max_taken_date": "2015-07-11",
    "max_uploaded_date": "2015-07-11",
    "min_taken_date": "2012-07-11",
    "min_uploaded_date": "2012-07-11",
    "search_sort": "date-posted-asc",
    "max_images": 200
  },
  {
    "id_ours": "1dc6d29be3b61d260cc65e17fcfa7f5cf432f2f0",
    "id_search_engine": "13901330353",
    "url": "https://farm4.staticflickr.com/3706/13901330353_6ede613907_o.jpg",
    "url_type": "url_o",
    "wnid": "n02102973",
    "search_key": "irish water spaniel",
    "search_engine": "flickr",
    "uploader": "becca",
    "date_upload_our_db": "2018-09-23 20:09:14",
    "date_taken": "2014-02-06 18:50:55",
    "date_upload_search_engine": "2014-04-16 12:58:29",
    "width": null,
    "height": null,
    "max_taken_date": "2015-07-11",
    "max_uploaded_date": "2015-07-11",
    "min_taken_date": "2012-07-11",
    "min_uploaded_date": "2012-07-11",
    "search_sort": "date-posted-asc",
    "max_images": 200
  },
  {
    "id_ours": "d5a25041bd2d1770a46468d6d3e318fe72e5e2b7",
    "id_search_engine": "13901275325",
    "url": "https://farm8.staticflickr.com/7144/13901275325_f5a8e05620_o.jpg",
    "url_type": "url_o",
    "wnid": "n02102973",
    "search_key": "irish water spaniel",
    "search_engine": "flickr",
    "uploader": "becca",
    "date_upload_our_db": "2018-09-23 20:09:14",
    "date_taken": "2014-01-10 15:52:44",
    "date_upload_search_engine": "2014-04-16 12:58:37",
    "width": null,
    "height": null,
    "max_taken_date": "2015-07-11",
    "max_uploaded_date": "2015-07-11",
    "min_taken_date": "2012-07-11",
    "min_uploaded_date": "2012-07-11",
    "search_sort": "date-posted-asc",
    "max_images": 200
  },
  {
    "id_ours": "da24e2c00579d2fec2ccd7779bb4ba6f3afa4198",
    "id_search_engine": "13901280325",
    "url": "https://farm8.staticflickr.com/7062/13901280325_ab5a23b056_o.jpg",
    "url_type": "url_o",
    "wnid": "n02102973",
    "search_key": "irish water spaniel",
    "search_engine": "flickr",
    "uploader": "becca",
    "date_upload_our_db": "2018-09-23 20:09:14",
    "date_taken": "2014-01-03 11:47:50",
    "date_upload_search_engine": "2014-04-16 12:58:53",
    "width": null,
    "height": null,
    "max_taken_date": "2015-07-11",
    "max_uploaded_date": "2015-07-11",
    "min_taken_date": "2012-07-11",
    "min_uploaded_date": "2012-07-11",
    "search_sort": "date-posted-asc",
    "max_images": 200
  },
  {
    "id_ours": "7a4b07ba86f087e68b2509299d964eeac7b37e87",
    "id_search_engine": "13901742514",
    "url": "https://farm4.staticflickr.com/3793/13901742514_e43d04377a_o.jpg",
    "url_type": "url_o",
    "wnid": "n02102973",
    "search_key": "irish water spaniel",
    "search_engine": "flickr",
    "uploader": "becca",
    "date_upload_our_db": "2018-09-23 20:09:14",
    "date_taken": "2013-11-18 08:14:14",
    "date_upload_search_engine": "2014-04-16 13:01:27",
    "width": null,
    "height": null,
    "max_taken_date": "2015-07-11",
    "max_uploaded_date": "2015-07-11",
    "min_taken_date": "2012-07-11",
    "min_uploaded_date": "2012-07-11",
    "search_sort": "date-posted-asc",
    "max_images": 200
  },
  {
    "id_ours": "8bd092ee8be4c35eb36651ec46817ff9ca5925b5",
    "id_search_engine": "13901376893",
    "url": "https://farm8.staticflickr.com/7261/13901376893_44a835042f_o.jpg",
    "url_type": "url_o",
    "wnid": "n02102973",
    "search_key": "irish water spaniel",
    "search_engine": "flickr",
    "uploader": "becca",
    "date_upload_our_db": "2018-09-23 20:09:14",
    "date_taken": "2014-03-10 16:07:45",
    "date_upload_search_engine": "2014-04-16 13:00:55",
    "width": null,
    "height": null,
    "max_taken_date": "2015-07-11",
    "max_uploaded_date": "2015-07-11",
    "min_taken_date": "2012-07-11",
    "min_uploaded_date": "2012-07-11",
    "search_sort": "date-posted-asc",
    "max_images": 200
  },
  {
    "id_ours": "0a814924320288ce3905d2644ab46f00eb79196c",
    "id_search_engine": "14770260620",
    "url": "https://farm6.staticflickr.com/5562/14770260620_a83fb816d1_o.jpg",
    "url_type": "url_o",
    "wnid": "n02102973",
    "search_key": "irish water spaniel",
    "search_engine": "flickr",
    "uploader": "becca",
    "date_upload_our_db": "2018-09-23 20:09:14",
    "date_taken": "2013-12-25 17:05:32",
    "date_upload_search_engine": "2014-08-18 03:20:26",
    "width": null,
    "height": null,
    "max_taken_date": "2015-07-11",
    "max_uploaded_date": "2015-07-11",
    "min_taken_date": "2012-07-11",
    "min_uploaded_date": "2012-07-11",
    "search_sort": "date-posted-asc",
    "max_images": 200
  },
  {
    "id_ours": "1b861d1f1baff93b2de744300a3fb0e41e62eaf4",
    "id_search_engine": "15154511391",
    "url": "https://farm6.staticflickr.com/5581/15154511391_e7a9621790_k.jpg",
    "url_type": "url_k",
    "wnid": "n02102973",
    "search_key": "irish water spaniel",
    "search_engine": "flickr",
    "uploader": "becca",
    "date_upload_our_db": "2018-09-23 20:09:14",
    "date_taken": "2014-09-06 15:17:23",
    "date_upload_search_engine": "2014-09-06 09:12:46",
    "width": 1661,
    "height": 2048,
    "max_taken_date": "2015-07-11",
    "max_uploaded_date": "2015-07-11",
    "min_taken_date": "2012-07-11",
    "min_uploaded_date": "2012-07-11",
    "search_sort": "date-posted-asc",
    "max_images": 200
  },
  {
    "id_ours": "43b60191f9e12eb7575f96cafcb0bea521f86727",
    "id_search_engine": "15187783056",
    "url": "https://farm4.staticflickr.com/3891/15187783056_626205f8a2_o.jpg",
    "url_type": "url_o",
    "wnid": "n02102973",
    "search_key": "irish water spaniel",
    "search_engine": "flickr",
    "uploader": "becca",
    "date_upload_our_db": "2018-09-23 20:09:14",
    "date_taken": "2014-08-16 15:20:18",
    "date_upload_search_engine": "2014-09-11 14:02:33",
    "width": 4608,
    "height": 3456,
    "max_taken_date": "2015-07-11",
    "max_uploaded_date": "2015-07-11",
    "min_taken_date": "2012-07-11",
    "min_uploaded_date": "2012-07-11",
    "search_sort": "date-posted-asc",
    "max_images": 200
  },
  {
    "id_ours": "614d997656f62219c1f8aff61451066ce00703c9",
    "id_search_engine": "15187782586",
    "url": "https://farm6.staticflickr.com/5553/15187782586_9923eee242_o.jpg",
    "url_type": "url_o",
    "wnid": "n02102973",
    "search_key": "irish water spaniel",
    "search_engine": "flickr",
    "uploader": "becca",
    "date_upload_our_db": "2018-09-23 20:09:14",
    "date_taken": "2014-08-16 15:20:47",
    "date_upload_search_engine": "2014-09-11 14:02:34",
    "width": 4608,
    "height": 3456,
    "max_taken_date": "2015-07-11",
    "max_uploaded_date": "2015-07-11",
    "min_taken_date": "2012-07-11",
    "min_uploaded_date": "2012-07-11",
    "search_sort": "date-posted-asc",
    "max_images": 200
  },
  {
    "id_ours": "38d1345a8c87d1d229310cd806e4399c58dd1c71",
    "id_search_engine": "15820797698",
    "url": "https://farm9.staticflickr.com/8605/15820797698_fdc82c111f_k.jpg",
    "url_type": "url_k",
    "wnid": "n02102973",
    "search_key": "irish water spaniel",
    "search_engine": "flickr",
    "uploader": "becca",
    "date_upload_our_db": "2018-09-23 20:09:14",
    "date_taken": "2012-08-14 14:28:52",
    "date_upload_search_engine": "2014-12-12 17:49:00",
    "width": null,
    "height": null,
    "max_taken_date": "2015-07-11",
    "max_uploaded_date": "2015-07-11",
    "min_taken_date": "2012-07-11",
    "min_uploaded_date": "2012-07-11",
    "search_sort": "date-posted-asc",
    "max_images": 200
  },
  {
    "id_ours": "d5582ad1a1595521d82769cdb72b35e7a0fc1dcc",
    "id_search_engine": "15966227280",
    "url": "https://farm8.staticflickr.com/7469/15966227280_f54a922183_k.jpg",
    "url_type": "url_k",
    "wnid": "n02102973",
    "search_key": "irish water spaniel",
    "search_engine": "flickr",
    "uploader": "becca",
    "date_upload_our_db": "2018-09-23 20:09:14",
    "date_taken": "2012-08-14 15:03:13",
    "date_upload_search_engine": "2014-12-30 22:14:19",
    "width": null,
    "height": null,
    "max_taken_date": "2015-07-11",
    "max_uploaded_date": "2015-07-11",
    "min_taken_date": "2012-07-11",
    "min_uploaded_date": "2012-07-11",
    "search_sort": "date-posted-asc",
    "max_images": 200
  },
  {
    "id_ours": "84e462c99af020fbf016903c360a536e7c6a0dd6",
    "id_search_engine": "15965050803",
    "url": "https://farm8.staticflickr.com/7382/15965050803_4ba2ae6272_o.jpg",
    "url_type": "url_o",
    "wnid": "n02102973",
    "search_key": "irish water spaniel",
    "search_engine": "flickr",
    "uploader": "becca",
    "date_upload_our_db": "2018-09-23 20:09:14",
    "date_taken": "2015-02-17 09:01:26",
    "date_upload_search_engine": "2015-02-19 15:40:06",
    "width": 2000,
    "height": 3008,
    "max_taken_date": "2015-07-11",
    "max_uploaded_date": "2015-07-11",
    "min_taken_date": "2012-07-11",
    "min_uploaded_date": "2012-07-11",
    "search_sort": "date-posted-asc",
    "max_images": 200
  },
  {
    "id_ours": "a590b4c35c0db64a872510f080e8a5141c028295",
    "id_search_engine": "16584139232",
    "url": "https://farm9.staticflickr.com/8594/16584139232_51484c8566_o.jpg",
    "url_type": "url_o",
    "wnid": "n02102973",
    "search_key": "irish water spaniel",
    "search_engine": "flickr",
    "uploader": "becca",
    "date_upload_our_db": "2018-09-23 20:09:14",
    "date_taken": "2015-02-17 09:01:35",
    "date_upload_search_engine": "2015-02-19 15:40:06",
    "width": 2000,
    "height": 3008,
    "max_taken_date": "2015-07-11",
    "max_uploaded_date": "2015-07-11",
    "min_taken_date": "2012-07-11",
    "min_uploaded_date": "2012-07-11",
    "search_sort": "date-posted-asc",
    "max_images": 200
  },
  {
    "id_ours": "e677d8223f3f02722a7c5a3b7fcc319db2c8397f",
    "id_search_engine": "16583608481",
    "url": "https://farm8.staticflickr.com/7437/16583608481_dc079788e8_o.jpg",
    "url_type": "url_o",
    "wnid": "n02102973",
    "search_key": "irish water spaniel",
    "search_engine": "flickr",
    "uploader": "becca",
    "date_upload_our_db": "2018-09-23 20:09:14",
    "date_taken": "2015-02-17 09:01:28",
    "date_upload_search_engine": "2015-02-19 15:40:06",
    "width": 2000,
    "height": 3008,
    "max_taken_date": "2015-07-11",
    "max_uploaded_date": "2015-07-11",
    "min_taken_date": "2012-07-11",
    "min_uploaded_date": "2012-07-11",
    "search_sort": "date-posted-asc",
    "max_images": 200
  },
  {
    "id_ours": "0dbc2fae37ebdc8eb008d2d59c6cda35f9517128",
    "id_search_engine": "18213801985",
    "url": "https://farm9.staticflickr.com/8885/18213801985_0652649582_o.jpg",
    "url_type": "url_o",
    "wnid": "n02102973",
    "search_key": "irish water spaniel",
    "search_engine": "flickr",
    "uploader": "becca",
    "date_upload_our_db": "2018-09-23 20:09:14",
    "date_taken": "2015-05-28 19:10:09",
    "date_upload_search_engine": "2015-05-28 17:44:26",
    "width": 3264,
    "height": 2448,
    "max_taken_date": "2015-07-11",
    "max_uploaded_date": "2015-07-11",
    "min_taken_date": "2012-07-11",
    "min_uploaded_date": "2012-07-11",
    "search_sort": "date-posted-asc",
    "max_images": 200
  },
  {
    "id_ours": "912067e831f22089d2221685fe2f34bfb9f858be",
    "id_search_engine": "18025959638",
    "url": "https://farm8.staticflickr.com/7737/18025959638_98098476c1_o.jpg",
    "url_type": "url_o",
    "wnid": "n02102973",
    "search_key": "irish water spaniel",
    "search_engine": "flickr",
    "uploader": "becca",
    "date_upload_our_db": "2018-09-23 20:09:14",
    "date_taken": "2015-05-28 19:23:42",
    "date_upload_search_engine": "2015-05-28 17:44:39",
    "width": 1463,
    "height": 1219,
    "max_taken_date": "2015-07-11",
    "max_uploaded_date": "2015-07-11",
    "min_taken_date": "2012-07-11",
    "min_uploaded_date": "2012-07-11",
    "search_sort": "date-posted-asc",
    "max_images": 200
  },
  {
    "id_ours": "36862dcbb548a589ac77a3ee68dd0e830c114a2a",
    "id_search_engine": "18025952308",
    "url": "https://farm8.staticflickr.com/7739/18025952308_f96c18251e_o.jpg",
    "url_type": "url_o",
    "wnid": "n02102973",
    "search_key": "irish water spaniel",
    "search_engine": "flickr",
    "uploader": "becca",
    "date_upload_our_db": "2018-09-23 20:09:14",
    "date_taken": "2015-05-28 19:09:56",
    "date_upload_search_engine": "2015-05-28 17:44:19",
    "width": 3264,
    "height": 2448,
    "max_taken_date": "2015-07-11",
    "max_uploaded_date": "2015-07-11",
    "min_taken_date": "2012-07-11",
    "min_uploaded_date": "2012-07-11",
    "search_sort": "date-posted-asc",
    "max_images": 200
  },
  {
    "id_ours": "4a3fed92edc75ea9dc5fe3b66acb2ee574a0737b",
    "id_search_engine": "18025961668",
    "url": "https://farm8.staticflickr.com/7779/18025961668_6792551468_o.jpg",
    "url_type": "url_o",
    "wnid": "n02102973",
    "search_key": "irish water spaniel",
    "search_engine": "flickr",
    "uploader": "becca",
    "date_upload_our_db": "2018-09-23 20:09:14",
    "date_taken": "2015-05-28 19:30:48",
    "date_upload_search_engine": "2015-05-28 17:44:45",
    "width": 3264,
    "height": 2448,
    "max_taken_date": "2015-07-11",
    "max_uploaded_date": "2015-07-11",
    "min_taken_date": "2012-07-11",
    "min_uploaded_date": "2012-07-11",
    "search_sort": "date-posted-asc",
    "max_images": 200
  },
  {
    "id_ours": "88b1352ab703334b0706ca98f929dba6fcb08b9b",
    "id_search_engine": "18215013971",
    "url": "https://farm9.staticflickr.com/8856/18215013971_1f297e78bf_o.jpg",
    "url_type": "url_o",
    "wnid": "n02102973",
    "search_key": "irish water spaniel",
    "search_engine": "flickr",
    "uploader": "becca",
    "date_upload_our_db": "2018-09-23 20:09:14",
    "date_taken": "2015-05-28 19:01:33",
    "date_upload_search_engine": "2015-05-28 17:44:09",
    "width": 3264,
    "height": 2448,
    "max_taken_date": "2015-07-11",
    "max_uploaded_date": "2015-07-11",
    "min_taken_date": "2012-07-11",
    "min_uploaded_date": "2012-07-11",
    "search_sort": "date-posted-asc",
    "max_images": 200
  },
  {
    "id_ours": "da8a98447aaf4d49e5ba634669815255b0f35597",
    "id_search_engine": "18213794875",
    "url": "https://farm8.staticflickr.com/7787/18213794875_9111c7a953_o.jpg",
    "url_type": "url_o",
    "wnid": "n02102973",
    "search_key": "irish water spaniel",
    "search_engine": "flickr",
    "uploader": "becca",
    "date_upload_our_db": "2018-09-23 20:09:14",
    "date_taken": "2015-05-28 18:55:53",
    "date_upload_search_engine": "2015-05-28 17:44:07",
    "width": 2448,
    "height": 3264,
    "max_taken_date": "2015-07-11",
    "max_uploaded_date": "2015-07-11",
    "min_taken_date": "2012-07-11",
    "min_uploaded_date": "2012-07-11",
    "search_sort": "date-posted-asc",
    "max_images": 200
  },
  {
    "id_ours": "bf4d660718b521cfb027a4f2e67ad2d171fb6eac",
    "id_search_engine": "18210133972",
    "url": "https://farm9.staticflickr.com/8855/18210133972_806a807e68_o.jpg",
    "url_type": "url_o",
    "wnid": "n02102973",
    "search_key": "irish water spaniel",
    "search_engine": "flickr",
    "uploader": "becca",
    "date_upload_our_db": "2018-09-23 20:09:14",
    "date_taken": "2015-05-28 19:09:48",
    "date_upload_search_engine": "2015-05-28 17:44:18",
    "width": 3264,
    "height": 2448,
    "max_taken_date": "2015-07-11",
    "max_uploaded_date": "2015-07-11",
    "min_taken_date": "2012-07-11",
    "min_uploaded_date": "2012-07-11",
    "search_sort": "date-posted-asc",
    "max_images": 200
  },
  {
    "id_ours": "598fbc9487c28f302c0a3d4ea361771ff620f33c",
    "id_search_engine": "18213804505",
    "url": "https://farm8.staticflickr.com/7744/18213804505_61a9a8c29d_o.jpg",
    "url_type": "url_o",
    "wnid": "n02102973",
    "search_key": "irish water spaniel",
    "search_engine": "flickr",
    "uploader": "becca",
    "date_upload_our_db": "2018-09-23 20:09:14",
    "date_taken": "2015-05-28 19:18:23",
    "date_upload_search_engine": "2015-05-28 17:44:33",
    "width": 3264,
    "height": 2448,
    "max_taken_date": "2015-07-11",
    "max_uploaded_date": "2015-07-11",
    "min_taken_date": "2012-07-11",
    "min_uploaded_date": "2012-07-11",
    "search_sort": "date-posted-asc",
    "max_images": 200
  },
  {
    "id_ours": "29825724a5f68ee571072748e3e917a8e56ab0ea",
    "id_search_engine": "18026078270",
    "url": "https://farm9.staticflickr.com/8843/18026078270_3f926792d9_o.jpg",
    "url_type": "url_o",
    "wnid": "n02102973",
    "search_key": "irish water spaniel",
    "search_engine": "flickr",
    "uploader": "becca",
    "date_upload_our_db": "2018-09-23 20:09:14",
    "date_taken": "2015-05-28 19:30:49",
    "date_upload_search_engine": "2015-05-28 17:44:51",
    "width": 3264,
    "height": 2448,
    "max_taken_date": "2015-07-11",
    "max_uploaded_date": "2015-07-11",
    "min_taken_date": "2012-07-11",
    "min_uploaded_date": "2012-07-11",
    "search_sort": "date-posted-asc",
    "max_images": 200
  },
  {
    "id_ours": "8f7288f88bd1b8ef762e426631634811d3108141",
    "id_search_engine": "18026059260",
    "url": "https://farm8.staticflickr.com/7772/18026059260_e2d8f5208b_o.jpg",
    "url_type": "url_o",
    "wnid": "n02102973",
    "search_key": "irish water spaniel",
    "search_engine": "flickr",
    "uploader": "becca",
    "date_upload_our_db": "2018-09-23 20:09:14",
    "date_taken": "2015-05-28 19:05:58",
    "date_upload_search_engine": "2015-05-28 17:44:00",
    "width": 3264,
    "height": 2448,
    "max_taken_date": "2015-07-11",
    "max_uploaded_date": "2015-07-11",
    "min_taken_date": "2012-07-11",
    "min_uploaded_date": "2012-07-11",
    "search_sort": "date-posted-asc",
    "max_images": 200
  },
  {
    "id_ours": "09cec90f5b5927bbc7031992d5fc154f97a42cec",
    "id_search_engine": "17591185774",
    "url": "https://farm9.staticflickr.com/8772/17591185774_d82233b1cf_o.jpg",
    "url_type": "url_o",
    "wnid": "n02102973",
    "search_key": "irish water spaniel",
    "search_engine": "flickr",
    "uploader": "becca",
    "date_upload_our_db": "2018-09-23 20:09:14",
    "date_taken": "2015-05-28 19:29:32",
    "date_upload_search_engine": "2015-05-28 17:44:41",
    "width": 3264,
    "height": 2448,
    "max_taken_date": "2015-07-11",
    "max_uploaded_date": "2015-07-11",
    "min_taken_date": "2012-07-11",
    "min_uploaded_date": "2012-07-11",
    "search_sort": "date-posted-asc",
    "max_images": 200
  },
  {
    "id_ours": "5d609e3f172e8fe4e90480eed29b0acbba969461",
    "id_search_engine": "18213799345",
    "url": "https://farm9.staticflickr.com/8856/18213799345_c124f2c0a4_o.jpg",
    "url_type": "url_o",
    "wnid": "n02102973",
    "search_key": "irish water spaniel",
    "search_engine": "flickr",
    "uploader": "becca",
    "date_upload_our_db": "2018-09-23 20:09:14",
    "date_taken": "2015-05-28 19:09:52",
    "date_upload_search_engine": "2015-05-28 17:44:19",
    "width": 3264,
    "height": 2448,
    "max_taken_date": "2015-07-11",
    "max_uploaded_date": "2015-07-11",
    "min_taken_date": "2012-07-11",
    "min_uploaded_date": "2012-07-11",
    "search_sort": "date-posted-asc",
    "max_images": 200
  },
  {
    "id_ours": "cad79491f7ad64f537ad31c188f5c65be1486910",
    "id_search_engine": "18215035761",
    "url": "https://farm8.staticflickr.com/7762/18215035761_63dceb75b4_o.jpg",
    "url_type": "url_o",
    "wnid": "n02102973",
    "search_key": "irish water spaniel",
    "search_engine": "flickr",
    "uploader": "becca",
    "date_upload_our_db": "2018-09-23 20:09:14",
    "date_taken": "2015-05-28 19:30:52",
    "date_upload_search_engine": "2015-05-28 17:45:06",
    "width": 3264,
    "height": 2448,
    "max_taken_date": "2015-07-11",
    "max_uploaded_date": "2015-07-11",
    "min_taken_date": "2012-07-11",
    "min_uploaded_date": "2012-07-11",
    "search_sort": "date-posted-asc",
    "max_images": 200
  },
  {
    "id_ours": "b68ad7510ee71fec77b500183978b97bd47fec19",
    "id_search_engine": "18213807555",
    "url": "https://farm8.staticflickr.com/7737/18213807555_c1ba60bd57_o.jpg",
    "url_type": "url_o",
    "wnid": "n02102973",
    "search_key": "irish water spaniel",
    "search_engine": "flickr",
    "uploader": "becca",
    "date_upload_our_db": "2018-09-23 20:09:14",
    "date_taken": "2015-05-28 19:29:33",
    "date_upload_search_engine": "2015-05-28 17:44:41",
    "width": 3264,
    "height": 2448,
    "max_taken_date": "2015-07-11",
    "max_uploaded_date": "2015-07-11",
    "min_taken_date": "2012-07-11",
    "min_uploaded_date": "2012-07-11",
    "search_sort": "date-posted-asc",
    "max_images": 200
  },
  {
    "id_ours": "ef4fad5681345b3d26c8ee275bb66c46341c280b",
    "id_search_engine": "18767077646",
    "url": "https://farm1.staticflickr.com/519/18767077646_91bb7be290_k.jpg",
    "url_type": "url_k",
    "wnid": "n02102973",
    "search_key": "irish water spaniel",
    "search_engine": "flickr",
    "uploader": "becca",
    "date_upload_our_db": "2018-09-23 20:09:14",
    "date_taken": "2012-08-14 15:12:25",
    "date_upload_search_engine": "2015-06-14 00:14:49",
    "width": null,
    "height": null,
    "max_taken_date": "2015-07-11",
    "max_uploaded_date": "2015-07-11",
    "min_taken_date": "2012-07-11",
    "min_uploaded_date": "2012-07-11",
    "search_sort": "date-posted-asc",
    "max_images": 200
  },
  {
    "id_ours": "a8142a5f6d665e8c56698b02fcfd2e6932f4a528",
    "id_search_engine": "19008385501",
    "url": "https://farm1.staticflickr.com/479/19008385501_ccf2ae128c_o.jpg",
    "url_type": "url_o",
    "wnid": "n02102973",
    "search_key": "irish water spaniel",
    "search_engine": "flickr",
    "uploader": "becca",
    "date_upload_our_db": "2018-09-23 20:09:14",
    "date_taken": "2015-06-06 12:29:42",
    "date_upload_search_engine": "2015-06-20 20:03:17",
    "width": 5184,
    "height": 3456,
    "max_taken_date": "2015-07-11",
    "max_uploaded_date": "2015-07-11",
    "min_taken_date": "2012-07-11",
    "min_uploaded_date": "2012-07-11",
    "search_sort": "date-posted-asc",
    "max_images": 200
  },
  {
    "id_ours": "566c02182cc912c9532fec6020ba67cbe0b8d8fd",
    "id_search_engine": "18382757444",
    "url": "https://farm1.staticflickr.com/465/18382757444_a33515bd42_o.jpg",
    "url_type": "url_o",
    "wnid": "n02102973",
    "search_key": "irish water spaniel",
    "search_engine": "flickr",
    "uploader": "becca",
    "date_upload_our_db": "2018-09-23 20:09:14",
    "date_taken": "2015-06-07 11:44:06",
    "date_upload_search_engine": "2015-06-20 20:03:19",
    "width": 3629,
    "height": 2420,
    "max_taken_date": "2015-07-11",
    "max_uploaded_date": "2015-07-11",
    "min_taken_date": "2012-07-11",
    "min_uploaded_date": "2012-07-11",
    "search_sort": "date-posted-asc",
    "max_images": 200
  },
  {
    "id_ours": "3cb61544f6f8523b1aed19fd72d66896b162a3fc",
    "id_search_engine": "19618736522",
    "url": "https://farm1.staticflickr.com/559/19618736522_6027efe9d7_o.jpg",
    "url_type": "url_o",
    "wnid": "n02102973",
    "search_key": "irish water spaniel",
    "search_engine": "flickr",
    "uploader": "becca",
    "date_upload_our_db": "2018-09-23 20:09:14",
    "date_taken": "2015-07-09 13:46:24",
    "date_upload_search_engine": "2015-07-12 01:28:13",
    "width": 3120,
    "height": 4160,
    "max_taken_date": "2015-07-11",
    "max_uploaded_date": "2015-07-11",
    "min_taken_date": "2012-07-11",
    "min_uploaded_date": "2012-07-11",
    "search_sort": "date-posted-asc",
    "max_images": 200
  },
  {
    "id_ours": "abd224754ea084b714ae542198db7d7c17e77d85",
    "id_search_engine": "23853903213",
    "url": "https://farm2.staticflickr.com/1594/23853903213_a828159e5b_k.jpg",
    "url_type": "url_k",
    "wnid": "n02102973",
    "search_key": "irish water spaniel",
    "search_engine": "flickr",
    "uploader": "becca",
    "date_upload_our_db": "2018-09-23 20:09:14",
    "date_taken": "2015-05-10 12:58:08",
    "date_upload_search_engine": "2016-01-19 05:39:31",
    "width": 1365,
    "height": 2048,
    "max_taken_date": "2015-07-11",
    "max_uploaded_date": "2015-07-11",
    "min_taken_date": "2012-07-11",
    "min_uploaded_date": "2012-07-11",
    "search_sort": "date-posted-asc",
    "max_images": 200
  },
  {
    "id_ours": "63fc2d2c6552a006a8eff4971e9c6498271dcc26",
    "id_search_engine": "24398285901",
    "url": "https://farm2.staticflickr.com/1614/24398285901_080d371960_k.jpg",
    "url_type": "url_k",
    "wnid": "n02102973",
    "search_key": "irish water spaniel",
    "search_engine": "flickr",
    "uploader": "becca",
    "date_upload_our_db": "2018-09-23 20:09:14",
    "date_taken": "2015-05-10 13:00:14",
    "date_upload_search_engine": "2016-01-19 05:39:31",
    "width": 2048,
    "height": 1365,
    "max_taken_date": "2015-07-11",
    "max_uploaded_date": "2015-07-11",
    "min_taken_date": "2012-07-11",
    "min_uploaded_date": "2012-07-11",
    "search_sort": "date-posted-asc",
    "max_images": 200
  },
  {
    "id_ours": "cf97f255580f2ad53765f8d312f00ad9cc0385ed",
    "id_search_engine": "24480738015",
    "url": "https://farm2.staticflickr.com/1707/24480738015_1403f6d5cd_k.jpg",
    "url_type": "url_k",
    "wnid": "n02102973",
    "search_key": "irish water spaniel",
    "search_engine": "flickr",
    "uploader": "becca",
    "date_upload_our_db": "2018-09-23 20:09:14",
    "date_taken": "2015-05-10 12:25:59",
    "date_upload_search_engine": "2016-01-19 05:39:25",
    "width": 2048,
    "height": 1365,
    "max_taken_date": "2015-07-11",
    "max_uploaded_date": "2015-07-11",
    "min_taken_date": "2012-07-11",
    "min_uploaded_date": "2012-07-11",
    "search_sort": "date-posted-asc",
    "max_images": 200
  },
  {
    "id_ours": "2e9b652714ce14625ab2a029123124e41fe01a84",
    "id_search_engine": "24112924939",
    "url": "https://farm2.staticflickr.com/1500/24112924939_1abcac362b_k.jpg",
    "url_type": "url_k",
    "wnid": "n02102973",
    "search_key": "irish water spaniel",
    "search_engine": "flickr",
    "uploader": "becca",
    "date_upload_our_db": "2018-09-23 20:09:14",
    "date_taken": "2015-05-10 13:22:34",
    "date_upload_search_engine": "2016-01-19 05:39:33",
    "width": 2048,
    "height": 1365,
    "max_taken_date": "2015-07-11",
    "max_uploaded_date": "2015-07-11",
    "min_taken_date": "2012-07-11",
    "min_uploaded_date": "2012-07-11",
    "search_sort": "date-posted-asc",
    "max_images": 200
  },
  {
    "id_ours": "2c1283ac377e9418a7daf35d3729617924e5e2d7",
    "id_search_engine": "24454485126",
    "url": "https://farm2.staticflickr.com/1598/24454485126_0ff5b5f1b4_k.jpg",
    "url_type": "url_k",
    "wnid": "n02102973",
    "search_key": "irish water spaniel",
    "search_engine": "flickr",
    "uploader": "becca",
    "date_upload_our_db": "2018-09-23 20:09:14",
    "date_taken": "2015-05-10 13:14:25",
    "date_upload_search_engine": "2016-01-19 05:39:32",
    "width": 2048,
    "height": 1365,
    "max_taken_date": "2015-07-11",
    "max_uploaded_date": "2015-07-11",
    "min_taken_date": "2012-07-11",
    "min_uploaded_date": "2012-07-11",
    "search_sort": "date-posted-asc",
    "max_images": 200
  },
  {
    "id_ours": "7c59605855e0ee3acc013bcc90fa7537204f6d18",
    "id_search_engine": "24112984839",
    "url": "https://farm2.staticflickr.com/1652/24112984839_2790d006b5_k.jpg",
    "url_type": "url_k",
    "wnid": "n02102973",
    "search_key": "irish water spaniel",
    "search_engine": "flickr",
    "uploader": "becca",
    "date_upload_our_db": "2018-09-23 20:09:14",
    "date_taken": "2015-05-10 12:34:56",
    "date_upload_search_engine": "2016-01-19 05:39:27",
    "width": 2048,
    "height": 1365,
    "max_taken_date": "2015-07-11",
    "max_uploaded_date": "2015-07-11",
    "min_taken_date": "2012-07-11",
    "min_uploaded_date": "2012-07-11",
    "search_sort": "date-posted-asc",
    "max_images": 200
  },
  {
    "id_ours": "467664c8ba12175b88286f5f6f05eb3bd7072dd1",
    "id_search_engine": "23852571064",
    "url": "https://farm2.staticflickr.com/1459/23852571064_5e616224b2_k.jpg",
    "url_type": "url_k",
    "wnid": "n02102973",
    "search_key": "irish water spaniel",
    "search_engine": "flickr",
    "uploader": "becca",
    "date_upload_our_db": "2018-09-23 20:09:14",
    "date_taken": "2015-05-10 12:25:13",
    "date_upload_search_engine": "2016-01-19 05:39:25",
    "width": 2048,
    "height": 1365,
    "max_taken_date": "2015-07-11",
    "max_uploaded_date": "2015-07-11",
    "min_taken_date": "2012-07-11",
    "min_uploaded_date": "2012-07-11",
    "search_sort": "date-posted-asc",
    "max_images": 200
  },
  {
    "id_ours": "22637a0cbda728d5bcc294b3f6ef81794e048ecb",
    "id_search_engine": "24372459172",
    "url": "https://farm2.staticflickr.com/1469/24372459172_776e99947f_k.jpg",
    "url_type": "url_k",
    "wnid": "n02102973",
    "search_key": "irish water spaniel",
    "search_engine": "flickr",
    "uploader": "becca",
    "date_upload_our_db": "2018-09-23 20:09:14",
    "date_taken": "2015-05-10 12:25:15",
    "date_upload_search_engine": "2016-01-19 05:39:25",
    "width": 2048,
    "height": 1365,
    "max_taken_date": "2015-07-11",
    "max_uploaded_date": "2015-07-11",
    "min_taken_date": "2012-07-11",
    "min_uploaded_date": "2012-07-11",
    "search_sort": "date-posted-asc",
    "max_images": 200
  },
  {
    "id_ours": "0b491eaa9636b4f3ada26195fa918147a708d1ea",
    "id_search_engine": "24185145670",
    "url": "https://farm2.staticflickr.com/1709/24185145670_e1135a9e3e_k.jpg",
    "url_type": "url_k",
    "wnid": "n02102973",
    "search_key": "irish water spaniel",
    "search_engine": "flickr",
    "uploader": "becca",
    "date_upload_our_db": "2018-09-23 20:09:14",
    "date_taken": "2015-05-10 12:55:16",
    "date_upload_search_engine": "2016-01-19 05:39:30",
    "width": 2048,
    "height": 1365,
    "max_taken_date": "2015-07-11",
    "max_uploaded_date": "2015-07-11",
    "min_taken_date": "2012-07-11",
    "min_uploaded_date": "2012-07-11",
    "search_sort": "date-posted-asc",
    "max_images": 200
  }
]