[
  {
    "id_ours": "83cbd9b8b07c2411640cb02af2a5a06f91bb9bed",
    "id_search_engine": "558427792",
    "url": "https://farm2.staticflickr.com/1072/558427792_6d259b018a_z.jpg",
    "url_type": "url_z",
    "wnid": "n03187595",
    "search_key": "rotary phone",
    "search_engine": "flickr",
    "uploader": "becca",
    "date_upload_our_db": "2018-09-11 20:49:39",
    "date_taken": "2013-05-31 20:06:51",
    "date_upload_search_engine": "2007-06-16 18:21:42",
    "width": null,
    "height": null,
    "max_taken_date": "2014-07-11",
    "max_uploaded_date": "2014-07-11",
    "min_taken_date": "2012-07-11",
    "min_uploaded_date": "2012-07-11",
    "search_sort": "date-posted-asc",
    "max_images": 100
  },
  {
    "id_ours": "62a70630f7deafcd00012eb30dc972cf8c7ef5b3",
    "id_search_engine": "6885860381",
    "url": "https://farm8.staticflickr.com/7053/6885860381_11460684de_z.jpg",
    "url_type": "url_z",
    "wnid": "n03187595",
    "search_key": "rotary phone",
    "search_engine": "flickr",
    "uploader": "becca",
    "date_upload_our_db": "2018-09-11 20:49:39",
    "date_taken": "2014-05-16 11:05:38",
    "date_upload_search_engine": "2012-02-16 03:54:13",
    "width": null,
    "height": null,
    "max_taken_date": "2014-07-11",
    "max_uploaded_date": "2014-07-11",
    "min_taken_date": "2012-07-11",
    "min_uploaded_date": "2012-07-11",
    "search_sort": "date-posted-asc",
    "max_images": 100
  },
  {
    "id_ours": "6e5eb1e5046b590c1ee9757b2f562d8693658edb",
    "id_search_engine": "7592507208",
    "url": "https://farm8.staticflickr.com/7263/7592507208_c52b6b5f51_o.jpg",
    "url_type": "url_o",
    "wnid": "n03187595",
    "search_key": "rotary phone",
    "search_engine": "flickr",
    "uploader": "becca",
    "date_upload_our_db": "2018-09-11 20:49:39",
    "date_taken": "2012-07-17 16:02:18",
    "date_upload_search_engine": "2012-07-17 13:02:18",
    "width": null,
    "height": null,
    "max_taken_date": "2014-07-11",
    "max_uploaded_date": "2014-07-11",
    "min_taken_date": "2012-07-11",
    "min_uploaded_date": "2012-07-11",
    "search_sort": "date-posted-asc",
    "max_images": 100
  },
  {
    "id_ours": "a598ba53c7340dc7fbe900c4cf76104699e18bd6",
    "id_search_engine": "7606265964",
    "url": "https://farm8.staticflickr.com/7130/7606265964_a16b4b01b0_o.jpg",
    "url_type": "url_o",
    "wnid": "n03187595",
    "search_key": "rotary phone",
    "search_engine": "flickr",
    "uploader": "becca",
    "date_upload_our_db": "2018-09-11 20:49:39",
    "date_taken": "2012-07-19 18:15:45",
    "date_upload_search_engine": "2012-07-19 15:57:22",
    "width": null,
    "height": null,
    "max_taken_date": "2014-07-11",
    "max_uploaded_date": "2014-07-11",
    "min_taken_date": "2012-07-11",
    "min_uploaded_date": "2012-07-11",
    "search_sort": "date-posted-asc",
    "max_images": 100
  },
  {
    "id_ours": "4b636a5a2fb776face37e23c5b2fdcdcbdb45c04",
    "id_search_engine": "7606265192",
    "url": "https://farm8.staticflickr.com/7126/7606265192_a306145cda_o.jpg",
    "url_type": "url_o",
    "wnid": "n03187595",
    "search_key": "rotary phone",
    "search_engine": "flickr",
    "uploader": "becca",
    "date_upload_our_db": "2018-09-11 20:49:39",
    "date_taken": "2012-07-19 18:14:43",
    "date_upload_search_engine": "2012-07-19 15:57:23",
    "width": null,
    "height": null,
    "max_taken_date": "2014-07-11",
    "max_uploaded_date": "2014-07-11",
    "min_taken_date": "2012-07-11",
    "min_uploaded_date": "2012-07-11",
    "search_sort": "date-posted-asc",
    "max_images": 100
  },
  {
    "id_ours": "9783e9ca66cb543668e59fe082a6e42ce6598599",
    "id_search_engine": "7606262960",
    "url": "https://farm9.staticflickr.com/8162/7606262960_3dcafa54e7_o.jpg",
    "url_type": "url_o",
    "wnid": "n03187595",
    "search_key": "rotary phone",
    "search_engine": "flickr",
    "uploader": "becca",
    "date_upload_our_db": "2018-09-11 20:49:39",
    "date_taken": "2012-07-19 18:16:15",
    "date_upload_search_engine": "2012-07-19 15:57:27",
    "width": null,
    "height": null,
    "max_taken_date": "2014-07-11",
    "max_uploaded_date": "2014-07-11",
    "min_taken_date": "2012-07-11",
    "min_uploaded_date": "2012-07-11",
    "search_sort": "date-posted-asc",
    "max_images": 100
  },
  {
    "id_ours": "61d6944a62b10d7df3739e7fa0157994624f3024",
    "id_search_engine": "7611320742",
    "url": "https://farm8.staticflickr.com/7116/7611320742_645a302101_o.jpg",
    "url_type": "url_o",
    "wnid": "n03187595",
    "search_key": "rotary phone",
    "search_engine": "flickr",
    "uploader": "becca",
    "date_upload_our_db": "2018-09-11 20:49:39",
    "date_taken": "2012-07-20 14:07:37",
    "date_upload_search_engine": "2012-07-20 13:09:37",
    "width": "1500",
    "height": "1048",
    "max_taken_date": "2014-07-11",
    "max_uploaded_date": "2014-07-11",
    "min_taken_date": "2012-07-11",
    "min_uploaded_date": "2012-07-11",
    "search_sort": "date-posted-asc",
    "max_images": 100
  },
  {
    "id_ours": "01141e34b23e6daad0c4269892616234dc98e954",
    "id_search_engine": "7615507790",
    "url": "https://farm8.staticflickr.com/7257/7615507790_1c8bfed54a_o.jpg",
    "url_type": "url_o",
    "wnid": "n03187595",
    "search_key": "rotary phone",
    "search_engine": "flickr",
    "uploader": "becca",
    "date_upload_our_db": "2018-09-11 20:49:39",
    "date_taken": "2012-07-21 10:43:35",
    "date_upload_search_engine": "2012-07-21 07:43:35",
    "width": null,
    "height": null,
    "max_taken_date": "2014-07-11",
    "max_uploaded_date": "2014-07-11",
    "min_taken_date": "2012-07-11",
    "min_uploaded_date": "2012-07-11",
    "search_sort": "date-posted-asc",
    "max_images": 100
  },
  {
    "id_ours": "7ccd1a041c89467554b6e2b1508bf1c3b3f03db2",
    "id_search_engine": "7638210416",
    "url": "https://farm9.staticflickr.com/8431/7638210416_5a2dcd8238_o.jpg",
    "url_type": "url_o",
    "wnid": "n03187595",
    "search_key": "rotary phone",
    "search_engine": "flickr",
    "uploader": "becca",
    "date_upload_our_db": "2018-09-11 20:49:39",
    "date_taken": "2012-07-24 13:34:46",
    "date_upload_search_engine": "2012-07-24 10:34:46",
    "width": null,
    "height": null,
    "max_taken_date": "2014-07-11",
    "max_uploaded_date": "2014-07-11",
    "min_taken_date": "2012-07-11",
    "min_uploaded_date": "2012-07-11",
    "search_sort": "date-posted-asc",
    "max_images": 100
  },
  {
    "id_ours": "d4b3679c00bff7ac0f2edddf1620bc02e53e9661",
    "id_search_engine": "7662379690",
    "url": "https://farm9.staticflickr.com/8433/7662379690_f0b2447233_k.jpg",
    "url_type": "url_k",
    "wnid": "n03187595",
    "search_key": "rotary phone",
    "search_engine": "flickr",
    "uploader": "becca",
    "date_upload_our_db": "2018-09-11 20:49:39",
    "date_taken": "2012-07-28 09:45:42",
    "date_upload_search_engine": "2012-07-28 08:27:09",
    "width": null,
    "height": null,
    "max_taken_date": "2014-07-11",
    "max_uploaded_date": "2014-07-11",
    "min_taken_date": "2012-07-11",
    "min_uploaded_date": "2012-07-11",
    "search_sort": "date-posted-asc",
    "max_images": 100
  },
  {
    "id_ours": "be93f1fe3fc70d8ea38895349a10f95e1c89664e",
    "id_search_engine": "7665919118",
    "url": "https://farm8.staticflickr.com/7251/7665919118_bba1f096e5_o.jpg",
    "url_type": "url_o",
    "wnid": "n03187595",
    "search_key": "rotary phone",
    "search_engine": "flickr",
    "uploader": "becca",
    "date_upload_our_db": "2018-09-11 20:49:39",
    "date_taken": "2012-07-28 21:04:19",
    "date_upload_search_engine": "2012-07-28 19:52:16",
    "width": "1296",
    "height": "968",
    "max_taken_date": "2014-07-11",
    "max_uploaded_date": "2014-07-11",
    "min_taken_date": "2012-07-11",
    "min_uploaded_date": "2012-07-11",
    "search_sort": "date-posted-asc",
    "max_images": 100
  },
  {
    "id_ours": "3ac840ebc087fb63224c3c873fbd5005bf20a054",
    "id_search_engine": "7666443074",
    "url": "https://farm8.staticflickr.com/7129/7666443074_b7a402b44e_o.jpg",
    "url_type": "url_o",
    "wnid": "n03187595",
    "search_key": "rotary phone",
    "search_engine": "flickr",
    "uploader": "becca",
    "date_upload_our_db": "2018-09-11 20:49:39",
    "date_taken": "2012-07-28 23:55:49",
    "date_upload_search_engine": "2012-07-28 21:58:26",
    "width": "1296",
    "height": "968",
    "max_taken_date": "2014-07-11",
    "max_uploaded_date": "2014-07-11",
    "min_taken_date": "2012-07-11",
    "min_uploaded_date": "2012-07-11",
    "search_sort": "date-posted-asc",
    "max_images": 100
  },
  {
    "id_ours": "a3a08562e1ea4f079f6ad9c844cebc8d7ef85de2",
    "id_search_engine": "7678654776",
    "url": "https://farm8.staticflickr.com/7114/7678654776_30fd6ef9c9_k.jpg",
    "url_type": "url_k",
    "wnid": "n03187595",
    "search_key": "rotary phone",
    "search_engine": "flickr",
    "uploader": "becca",
    "date_upload_our_db": "2018-09-11 20:49:39",
    "date_taken": "2012-07-30 12:00:21",
    "date_upload_search_engine": "2012-07-30 12:15:22",
    "width": null,
    "height": null,
    "max_taken_date": "2014-07-11",
    "max_uploaded_date": "2014-07-11",
    "min_taken_date": "2012-07-11",
    "min_uploaded_date": "2012-07-11",
    "search_sort": "date-posted-asc",
    "max_images": 100
  },
  {
    "id_ours": "ac03cc4652028d6ff66da20ecd3454473bcab63a",
    "id_search_engine": "7685778578",
    "url": "https://farm8.staticflickr.com/7124/7685778578_a0a14b948c_o.jpg",
    "url_type": "url_o",
    "wnid": "n03187595",
    "search_key": "rotary phone",
    "search_engine": "flickr",
    "uploader": "becca",
    "date_upload_our_db": "2018-09-11 20:49:39",
    "date_taken": "2012-07-31 16:06:51",
    "date_upload_search_engine": "2012-07-31 11:29:36",
    "width": "2750",
    "height": "3131",
    "max_taken_date": "2014-07-11",
    "max_uploaded_date": "2014-07-11",
    "min_taken_date": "2012-07-11",
    "min_uploaded_date": "2012-07-11",
    "search_sort": "date-posted-asc",
    "max_images": 100
  },
  {
    "id_ours": "68738e412c2600ca7fcb76e8f08000786c4ac0d8",
    "id_search_engine": "7685772682",
    "url": "https://farm8.staticflickr.com/7259/7685772682_98b6e07d9d_o.jpg",
    "url_type": "url_o",
    "wnid": "n03187595",
    "search_key": "rotary phone",
    "search_engine": "flickr",
    "uploader": "becca",
    "date_upload_our_db": "2018-09-11 20:49:39",
    "date_taken": "2012-07-31 16:06:13",
    "date_upload_search_engine": "2012-07-31 11:28:43",
    "width": "2865",
    "height": "3655",
    "max_taken_date": "2014-07-11",
    "max_uploaded_date": "2014-07-11",
    "min_taken_date": "2012-07-11",
    "min_uploaded_date": "2012-07-11",
    "search_sort": "date-posted-asc",
    "max_images": 100
  },
  {
    "id_ours": "4e45a36287a821fe44c186ccdd6f4004795679b8",
    "id_search_engine": "7686752434",
    "url": "https://farm8.staticflickr.com/7270/7686752434_a09fb4ca7b_o.jpg",
    "url_type": "url_o",
    "wnid": "n03187595",
    "search_key": "rotary phone",
    "search_engine": "flickr",
    "uploader": "becca",
    "date_upload_our_db": "2018-09-11 20:49:39",
    "date_taken": "2012-07-17 17:38:18",
    "date_upload_search_engine": "2012-07-31 14:00:47",
    "width": null,
    "height": null,
    "max_taken_date": "2014-07-11",
    "max_uploaded_date": "2014-07-11",
    "min_taken_date": "2012-07-11",
    "min_uploaded_date": "2012-07-11",
    "search_sort": "date-posted-asc",
    "max_images": 100
  },
  {
    "id_ours": "6f98dae0aa533d58edbf6c628b5d069432e3f889",
    "id_search_engine": "7706143020",
    "url": "https://farm9.staticflickr.com/8006/7706143020_7b7ed66c58_o.jpg",
    "url_type": "url_o",
    "wnid": "n03187595",
    "search_key": "rotary phone",
    "search_engine": "flickr",
    "uploader": "becca",
    "date_upload_our_db": "2018-09-11 20:49:39",
    "date_taken": "2012-08-04 09:30:03",
    "date_upload_search_engine": "2012-08-04 06:41:57",
    "width": "523",
    "height": "1014",
    "max_taken_date": "2014-07-11",
    "max_uploaded_date": "2014-07-11",
    "min_taken_date": "2012-07-11",
    "min_uploaded_date": "2012-07-11",
    "search_sort": "date-posted-asc",
    "max_images": 100
  },
  {
    "id_ours": "952a3b8416e9de761ae2808ff0d71b778ab9501e",
    "id_search_engine": "7712668254",
    "url": "https://farm8.staticflickr.com/7132/7712668254_0dce53e975_o.jpg",
    "url_type": "url_o",
    "wnid": "n03187595",
    "search_key": "rotary phone",
    "search_engine": "flickr",
    "uploader": "becca",
    "date_upload_our_db": "2018-09-11 20:49:39",
    "date_taken": "2012-08-04 16:35:37",
    "date_upload_search_engine": "2012-08-04 14:16:00",
    "width": "2026",
    "height": "1340",
    "max_taken_date": "2014-07-11",
    "max_uploaded_date": "2014-07-11",
    "min_taken_date": "2012-07-11",
    "min_uploaded_date": "2012-07-11",
    "search_sort": "date-posted-asc",
    "max_images": 100
  },
  {
    "id_ours": "64a30eff22ae7a5df68b40674aec63c236be0c28",
    "id_search_engine": "7751182592",
    "url": "https://farm9.staticflickr.com/8294/7751182592_8c1739ae1d_z.jpg",
    "url_type": "url_z",
    "wnid": "n03187595",
    "search_key": "rotary phone",
    "search_engine": "flickr",
    "uploader": "becca",
    "date_upload_our_db": "2018-09-11 20:49:39",
    "date_taken": "2012-08-09 23:09:05",
    "date_upload_search_engine": "2012-08-09 23:09:05",
    "width": null,
    "height": null,
    "max_taken_date": "2014-07-11",
    "max_uploaded_date": "2014-07-11",
    "min_taken_date": "2012-07-11",
    "min_uploaded_date": "2012-07-11",
    "search_sort": "date-posted-asc",
    "max_images": 100
  },
  {
    "id_ours": "cc8692e81bd93d38817b0e8bca11676b138ac0b1",
    "id_search_engine": "7758323700",
    "url": "https://farm9.staticflickr.com/8289/7758323700_79a9e6fa6d_o.jpg",
    "url_type": "url_o",
    "wnid": "n03187595",
    "search_key": "rotary phone",
    "search_engine": "flickr",
    "uploader": "becca",
    "date_upload_our_db": "2018-09-11 20:49:39",
    "date_taken": "2012-08-11 07:55:36",
    "date_upload_search_engine": "2012-08-11 05:01:19",
    "width": "3225",
    "height": "1360",
    "max_taken_date": "2014-07-11",
    "max_uploaded_date": "2014-07-11",
    "min_taken_date": "2012-07-11",
    "min_uploaded_date": "2012-07-11",
    "search_sort": "date-posted-asc",
    "max_images": 100
  },
  {
    "id_ours": "4763f931fb4e8fa31dd20b355a00cc1abaa2b42d",
    "id_search_engine": "7787720040",
    "url": "https://farm9.staticflickr.com/8298/7787720040_f3a3ce3fa4_o.jpg",
    "url_type": "url_o",
    "wnid": "n03187595",
    "search_key": "rotary phone",
    "search_engine": "flickr",
    "uploader": "becca",
    "date_upload_our_db": "2018-09-11 20:49:39",
    "date_taken": "2012-08-14 16:49:23",
    "date_upload_search_engine": "2012-08-15 04:49:42",
    "width": "1913",
    "height": "3413",
    "max_taken_date": "2014-07-11",
    "max_uploaded_date": "2014-07-11",
    "min_taken_date": "2012-07-11",
    "min_uploaded_date": "2012-07-11",
    "search_sort": "date-posted-asc",
    "max_images": 100
  },
  {
    "id_ours": "a138d77a1c9319d67c5f700d32d67380476fb93b",
    "id_search_engine": "7787718894",
    "url": "https://farm9.staticflickr.com/8301/7787718894_634e636f14_o.jpg",
    "url_type": "url_o",
    "wnid": "n03187595",
    "search_key": "rotary phone",
    "search_engine": "flickr",
    "uploader": "becca",
    "date_upload_our_db": "2018-09-11 20:49:39",
    "date_taken": "2012-08-14 16:48:57",
    "date_upload_search_engine": "2012-08-15 04:49:24",
    "width": "2000",
    "height": "3568",
    "max_taken_date": "2014-07-11",
    "max_uploaded_date": "2014-07-11",
    "min_taken_date": "2012-07-11",
    "min_uploaded_date": "2012-07-11",
    "search_sort": "date-posted-asc",
    "max_images": 100
  },
  {
    "id_ours": "732cd19565ecc4fe8c4dd2efeb35040fd28e0077",
    "id_search_engine": "7796099388",
    "url": "https://farm9.staticflickr.com/8284/7796099388_1d80f9d5c1_o.jpg",
    "url_type": "url_o",
    "wnid": "n03187595",
    "search_key": "rotary phone",
    "search_engine": "flickr",
    "uploader": "becca",
    "date_upload_our_db": "2018-09-11 20:49:39",
    "date_taken": "2012-08-16 11:09:27",
    "date_upload_search_engine": "2012-08-16 09:31:04",
    "width": null,
    "height": null,
    "max_taken_date": "2014-07-11",
    "max_uploaded_date": "2014-07-11",
    "min_taken_date": "2012-07-11",
    "min_uploaded_date": "2012-07-11",
    "search_sort": "date-posted-asc",
    "max_images": 100
  },
  {
    "id_ours": "c95efc4fbedbba5c8a41397e2ba75be8e236e994",
    "id_search_engine": "7804297388",
    "url": "https://farm9.staticflickr.com/8447/7804297388_22c519608e_c.jpg",
    "url_type": "url_c",
    "wnid": "n03187595",
    "search_key": "rotary phone",
    "search_engine": "flickr",
    "uploader": "becca",
    "date_upload_our_db": "2018-09-11 20:49:39",
    "date_taken": "2012-08-17 16:22:33",
    "date_upload_search_engine": "2012-08-17 14:33:59",
    "width": null,
    "height": null,
    "max_taken_date": "2014-07-11",
    "max_uploaded_date": "2014-07-11",
    "min_taken_date": "2012-07-11",
    "min_uploaded_date": "2012-07-11",
    "search_sort": "date-posted-asc",
    "max_images": 100
  },
  {
    "id_ours": "27e8e33c0e2f4d53dc52476adec9f7a4eb8fa080",
    "id_search_engine": "7806019582",
    "url": "https://farm8.staticflickr.com/7120/7806019582_fab2407600_o.jpg",
    "url_type": "url_o",
    "wnid": "n03187595",
    "search_key": "rotary phone",
    "search_engine": "flickr",
    "uploader": "becca",
    "date_upload_our_db": "2018-09-11 20:49:39",
    "date_taken": "2012-08-17 03:47:20",
    "date_upload_search_engine": "2012-08-17 21:35:40",
    "width": null,
    "height": null,
    "max_taken_date": "2014-07-11",
    "max_uploaded_date": "2014-07-11",
    "min_taken_date": "2012-07-11",
    "min_uploaded_date": "2012-07-11",
    "search_sort": "date-posted-asc",
    "max_images": 100
  },
  {
    "id_ours": "b092e78c7a90349613df7d047d24e64b24a6974b",
    "id_search_engine": "7819156332",
    "url": "https://farm9.staticflickr.com/8300/7819156332_a6e112c6c0_o.jpg",
    "url_type": "url_o",
    "wnid": "n03187595",
    "search_key": "rotary phone",
    "search_engine": "flickr",
    "uploader": "becca",
    "date_upload_our_db": "2018-09-11 20:49:39",
    "date_taken": "2012-08-19 15:51:51",
    "date_upload_search_engine": "2012-08-19 16:32:39",
    "width": null,
    "height": null,
    "max_taken_date": "2014-07-11",
    "max_uploaded_date": "2014-07-11",
    "min_taken_date": "2012-07-11",
    "min_uploaded_date": "2012-07-11",
    "search_sort": "date-posted-asc",
    "max_images": 100
  },
  {
    "id_ours": "04a12d12cd4386117e47f624e141bd4d2c5068b5",
    "id_search_engine": "7833763464",
    "url": "https://farm9.staticflickr.com/8442/7833763464_fec3d6fde1_k.jpg",
    "url_type": "url_k",
    "wnid": "n03187595",
    "search_key": "rotary phone",
    "search_engine": "flickr",
    "uploader": "becca",
    "date_upload_our_db": "2018-09-11 20:49:39",
    "date_taken": "2012-08-19 17:28:05",
    "date_upload_search_engine": "2012-08-21 14:08:35",
    "width": null,
    "height": null,
    "max_taken_date": "2014-07-11",
    "max_uploaded_date": "2014-07-11",
    "min_taken_date": "2012-07-11",
    "min_uploaded_date": "2012-07-11",
    "search_sort": "date-posted-asc",
    "max_images": 100
  },
  {
    "id_ours": "5f234d4c9b705ef14d6df9b62d6fe94a0ba6f870",
    "id_search_engine": "7833800882",
    "url": "https://farm9.staticflickr.com/8285/7833800882_2b8dc87c64_k.jpg",
    "url_type": "url_k",
    "wnid": "n03187595",
    "search_key": "rotary phone",
    "search_engine": "flickr",
    "uploader": "becca",
    "date_upload_our_db": "2018-09-11 20:49:39",
    "date_taken": "2012-08-14 19:09:15",
    "date_upload_search_engine": "2012-08-21 14:14:51",
    "width": null,
    "height": null,
    "max_taken_date": "2014-07-11",
    "max_uploaded_date": "2014-07-11",
    "min_taken_date": "2012-07-11",
    "min_uploaded_date": "2012-07-11",
    "search_sort": "date-posted-asc",
    "max_images": 100
  },
  {
    "id_ours": "f9835c4deac6b5d60971ef56e4b5c88de0affd3d",
    "id_search_engine": "7854543754",
    "url": "https://farm9.staticflickr.com/8289/7854543754_6dff8bd9d1_c.jpg",
    "url_type": "url_c",
    "wnid": "n03187595",
    "search_key": "rotary phone",
    "search_engine": "flickr",
    "uploader": "becca",
    "date_upload_our_db": "2018-09-11 20:49:39",
    "date_taken": "2012-08-24 19:33:21",
    "date_upload_search_engine": "2012-08-24 19:34:45",
    "width": null,
    "height": null,
    "max_taken_date": "2014-07-11",
    "max_uploaded_date": "2014-07-11",
    "min_taken_date": "2012-07-11",
    "min_uploaded_date": "2012-07-11",
    "search_sort": "date-posted-asc",
    "max_images": 100
  },
  {
    "id_ours": "71f9354483b396c6686e051f729c05223d977230",
    "id_search_engine": "7857619910",
    "url": "https://farm8.staticflickr.com/7264/7857619910_a68b632b9c_c.jpg",
    "url_type": "url_c",
    "wnid": "n03187595",
    "search_key": "rotary phone",
    "search_engine": "flickr",
    "uploader": "becca",
    "date_upload_our_db": "2018-09-11 20:49:39",
    "date_taken": "2012-08-22 16:41:41",
    "date_upload_search_engine": "2012-08-25 08:57:23",
    "width": null,
    "height": null,
    "max_taken_date": "2014-07-11",
    "max_uploaded_date": "2014-07-11",
    "min_taken_date": "2012-07-11",
    "min_uploaded_date": "2012-07-11",
    "search_sort": "date-posted-asc",
    "max_images": 100
  },
  {
    "id_ours": "e72ed4b4a5a838d0aad707dfe0db3d07318f32c4",
    "id_search_engine": "7874683426",
    "url": "https://farm9.staticflickr.com/8294/7874683426_60e7a33126_o.jpg",
    "url_type": "url_o",
    "wnid": "n03187595",
    "search_key": "rotary phone",
    "search_engine": "flickr",
    "uploader": "becca",
    "date_upload_our_db": "2018-09-11 20:49:39",
    "date_taken": "2012-08-18 11:17:19",
    "date_upload_search_engine": "2012-08-27 12:06:40",
    "width": "4320",
    "height": "2432",
    "max_taken_date": "2014-07-11",
    "max_uploaded_date": "2014-07-11",
    "min_taken_date": "2012-07-11",
    "min_uploaded_date": "2012-07-11",
    "search_sort": "date-posted-asc",
    "max_images": 100
  },
  {
    "id_ours": "ae479215570f228eb8d17e76ee33d2db9f252add",
    "id_search_engine": "7882697706",
    "url": "https://farm9.staticflickr.com/8444/7882697706_affafa6860_o.jpg",
    "url_type": "url_o",
    "wnid": "n03187595",
    "search_key": "rotary phone",
    "search_engine": "flickr",
    "uploader": "becca",
    "date_upload_our_db": "2018-09-11 20:49:39",
    "date_taken": "2012-08-28 13:28:42",
    "date_upload_search_engine": "2012-08-28 13:29:35",
    "width": null,
    "height": null,
    "max_taken_date": "2014-07-11",
    "max_uploaded_date": "2014-07-11",
    "min_taken_date": "2012-07-11",
    "min_uploaded_date": "2012-07-11",
    "search_sort": "date-posted-asc",
    "max_images": 100
  },
  {
    "id_ours": "2e2655957ad17a41a2096098fd344e4e0ac033ad",
    "id_search_engine": "7901505366",
    "url": "https://farm9.staticflickr.com/8180/7901505366_d0768e5829_k.jpg",
    "url_type": "url_k",
    "wnid": "n03187595",
    "search_key": "rotary phone",
    "search_engine": "flickr",
    "uploader": "becca",
    "date_upload_our_db": "2018-09-11 20:49:39",
    "date_taken": "2012-08-31 00:59:09",
    "date_upload_search_engine": "2012-08-31 11:02:49",
    "width": null,
    "height": null,
    "max_taken_date": "2014-07-11",
    "max_uploaded_date": "2014-07-11",
    "min_taken_date": "2012-07-11",
    "min_uploaded_date": "2012-07-11",
    "search_sort": "date-posted-asc",
    "max_images": 100
  },
  {
    "id_ours": "61dba390225ab78aed041b6d2495acc698e49d4b",
    "id_search_engine": "7915646042",
    "url": "https://farm9.staticflickr.com/8444/7915646042_52f5cf4d38_o.jpg",
    "url_type": "url_o",
    "wnid": "n03187595",
    "search_key": "rotary phone",
    "search_engine": "flickr",
    "uploader": "becca",
    "date_upload_our_db": "2018-09-11 20:49:39",
    "date_taken": "2012-09-02 10:15:02",
    "date_upload_search_engine": "2012-09-02 11:54:18",
    "width": "2560",
    "height": "1920",
    "max_taken_date": "2014-07-11",
    "max_uploaded_date": "2014-07-11",
    "min_taken_date": "2012-07-11",
    "min_uploaded_date": "2012-07-11",
    "search_sort": "date-posted-asc",
    "max_images": 100
  },
  {
    "id_ours": "b6c71c2b3a1e54f5faf85e4b1f516cdbc3ad9e69",
    "id_search_engine": "7932831268",
    "url": "https://farm9.staticflickr.com/8457/7932831268_d2b0beb9a0_c.jpg",
    "url_type": "url_c",
    "wnid": "n03187595",
    "search_key": "rotary phone",
    "search_engine": "flickr",
    "uploader": "becca",
    "date_upload_our_db": "2018-09-11 20:49:39",
    "date_taken": "2012-08-19 15:36:23",
    "date_upload_search_engine": "2012-09-04 14:59:01",
    "width": null,
    "height": null,
    "max_taken_date": "2014-07-11",
    "max_uploaded_date": "2014-07-11",
    "min_taken_date": "2012-07-11",
    "min_uploaded_date": "2012-07-11",
    "search_sort": "date-posted-asc",
    "max_images": 100
  },
  {
    "id_ours": "e2eb005c2f4e71014cb938f6e70bf864ac0a6db4",
    "id_search_engine": "7932830558",
    "url": "https://farm9.staticflickr.com/8437/7932830558_7b2ce911bd_c.jpg",
    "url_type": "url_c",
    "wnid": "n03187595",
    "search_key": "rotary phone",
    "search_engine": "flickr",
    "uploader": "becca",
    "date_upload_our_db": "2018-09-11 20:49:39",
    "date_taken": "2012-08-19 11:57:42",
    "date_upload_search_engine": "2012-09-04 14:58:55",
    "width": null,
    "height": null,
    "max_taken_date": "2014-07-11",
    "max_uploaded_date": "2014-07-11",
    "min_taken_date": "2012-07-11",
    "min_uploaded_date": "2012-07-11",
    "search_sort": "date-posted-asc",
    "max_images": 100
  },
  {
    "id_ours": "41c41fe0350ba515a1bc249f590a929820d3f945",
    "id_search_engine": "7932834244",
    "url": "https://farm9.staticflickr.com/8180/7932834244_8ccb9ccafe_c.jpg",
    "url_type": "url_c",
    "wnid": "n03187595",
    "search_key": "rotary phone",
    "search_engine": "flickr",
    "uploader": "becca",
    "date_upload_our_db": "2018-09-11 20:49:39",
    "date_taken": "2012-08-19 15:29:39",
    "date_upload_search_engine": "2012-09-04 14:59:31",
    "width": null,
    "height": null,
    "max_taken_date": "2014-07-11",
    "max_uploaded_date": "2014-07-11",
    "min_taken_date": "2012-07-11",
    "min_uploaded_date": "2012-07-11",
    "search_sort": "date-posted-asc",
    "max_images": 100
  },
  {
    "id_ours": "f635ce8ae134d0742e22eedf0807137bd0851978",
    "id_search_engine": "7932832710",
    "url": "https://farm9.staticflickr.com/8320/7932832710_be5c36fdf2_c.jpg",
    "url_type": "url_c",
    "wnid": "n03187595",
    "search_key": "rotary phone",
    "search_engine": "flickr",
    "uploader": "becca",
    "date_upload_our_db": "2018-09-11 20:49:39",
    "date_taken": "2012-08-19 15:40:25",
    "date_upload_search_engine": "2012-09-04 14:59:15",
    "width": null,
    "height": null,
    "max_taken_date": "2014-07-11",
    "max_uploaded_date": "2014-07-11",
    "min_taken_date": "2012-07-11",
    "min_uploaded_date": "2012-07-11",
    "search_sort": "date-posted-asc",
    "max_images": 100
  },
  {
    "id_ours": "23851a182b2c297a8144ff624670b54e354f8b4f",
    "id_search_engine": "7942686826",
    "url": "https://farm9.staticflickr.com/8319/7942686826_6ba07d5411_o.jpg",
    "url_type": "url_o",
    "wnid": "n03187595",
    "search_key": "rotary phone",
    "search_engine": "flickr",
    "uploader": "becca",
    "date_upload_our_db": "2018-09-11 20:49:39",
    "date_taken": "2012-07-28 09:34:36",
    "date_upload_search_engine": "2012-09-06 03:36:35",
    "width": null,
    "height": null,
    "max_taken_date": "2014-07-11",
    "max_uploaded_date": "2014-07-11",
    "min_taken_date": "2012-07-11",
    "min_uploaded_date": "2012-07-11",
    "search_sort": "date-posted-asc",
    "max_images": 100
  },
  {
    "id_ours": "1d2ae7ed7616b0fedcc33186e218fb2202e78a6e",
    "id_search_engine": "7958981812",
    "url": "https://farm9.staticflickr.com/8035/7958981812_0856b46001_o.jpg",
    "url_type": "url_o",
    "wnid": "n03187595",
    "search_key": "rotary phone",
    "search_engine": "flickr",
    "uploader": "becca",
    "date_upload_our_db": "2018-09-11 20:49:39",
    "date_taken": "2012-09-02 10:28:07",
    "date_upload_search_engine": "2012-09-08 19:01:47",
    "width": null,
    "height": null,
    "max_taken_date": "2014-07-11",
    "max_uploaded_date": "2014-07-11",
    "min_taken_date": "2012-07-11",
    "min_uploaded_date": "2012-07-11",
    "search_sort": "date-posted-asc",
    "max_images": 100
  },
  {
    "id_ours": "2210353833ec6d43a0016509ad0db6b0bfbdf374",
    "id_search_engine": "7958989988",
    "url": "https://farm9.staticflickr.com/8302/7958989988_0ce88b4e4d_o.jpg",
    "url_type": "url_o",
    "wnid": "n03187595",
    "search_key": "rotary phone",
    "search_engine": "flickr",
    "uploader": "becca",
    "date_upload_our_db": "2018-09-11 20:49:39",
    "date_taken": "2012-09-02 10:28:12",
    "date_upload_search_engine": "2012-09-08 19:01:46",
    "width": null,
    "height": null,
    "max_taken_date": "2014-07-11",
    "max_uploaded_date": "2014-07-11",
    "min_taken_date": "2012-07-11",
    "min_uploaded_date": "2012-07-11",
    "search_sort": "date-posted-asc",
    "max_images": 100
  },
  {
    "id_ours": "6b9f9a218805995e663a44a7f8f40815ccdaeeac",
    "id_search_engine": "7971895352",
    "url": "https://farm9.staticflickr.com/8039/7971895352_c1572b9844_o.jpg",
    "url_type": "url_o",
    "wnid": "n03187595",
    "search_key": "rotary phone",
    "search_engine": "flickr",
    "uploader": "becca",
    "date_upload_our_db": "2018-09-11 20:49:39",
    "date_taken": "2012-09-10 09:20:49",
    "date_upload_search_engine": "2012-09-10 09:20:49",
    "width": null,
    "height": null,
    "max_taken_date": "2014-07-11",
    "max_uploaded_date": "2014-07-11",
    "min_taken_date": "2012-07-11",
    "min_uploaded_date": "2012-07-11",
    "search_sort": "date-posted-asc",
    "max_images": 100
  },
  {
    "id_ours": "822f1893ea19296b9f026d1f1cf57d97d1dbbae5",
    "id_search_engine": "7974716462",
    "url": "https://farm9.staticflickr.com/8449/7974716462_d342de91a5_k.jpg",
    "url_type": "url_k",
    "wnid": "n03187595",
    "search_key": "rotary phone",
    "search_engine": "flickr",
    "uploader": "becca",
    "date_upload_our_db": "2018-09-11 20:49:39",
    "date_taken": "2012-08-02 01:30:07",
    "date_upload_search_engine": "2012-09-10 18:33:42",
    "width": null,
    "height": null,
    "max_taken_date": "2014-07-11",
    "max_uploaded_date": "2014-07-11",
    "min_taken_date": "2012-07-11",
    "min_uploaded_date": "2012-07-11",
    "search_sort": "date-posted-asc",
    "max_images": 100
  },
  {
    "id_ours": "5a0837f507d203d3deff1c67bef0289edf8960de",
    "id_search_engine": "7998311032",
    "url": "https://farm9.staticflickr.com/8178/7998311032_a80801138b_k.jpg",
    "url_type": "url_k",
    "wnid": "n03187595",
    "search_key": "rotary phone",
    "search_engine": "flickr",
    "uploader": "becca",
    "date_upload_our_db": "2018-09-11 20:49:39",
    "date_taken": "2012-09-16 11:45:02",
    "date_upload_search_engine": "2012-09-17 19:20:03",
    "width": null,
    "height": null,
    "max_taken_date": "2014-07-11",
    "max_uploaded_date": "2014-07-11",
    "min_taken_date": "2012-07-11",
    "min_uploaded_date": "2012-07-11",
    "search_sort": "date-posted-asc",
    "max_images": 100
  },
  {
    "id_ours": "8b2454f75a28b3f12fe8e6aa1e0c45cd40c4b8af",
    "id_search_engine": "7998758332",
    "url": "https://farm9.staticflickr.com/8308/7998758332_bf0a30c8fc_c.jpg",
    "url_type": "url_c",
    "wnid": "n03187595",
    "search_key": "rotary phone",
    "search_engine": "flickr",
    "uploader": "becca",
    "date_upload_our_db": "2018-09-11 20:49:39",
    "date_taken": "2012-07-11 21:20:58",
    "date_upload_search_engine": "2012-09-17 22:45:26",
    "width": null,
    "height": null,
    "max_taken_date": "2014-07-11",
    "max_uploaded_date": "2014-07-11",
    "min_taken_date": "2012-07-11",
    "min_uploaded_date": "2012-07-11",
    "search_sort": "date-posted-asc",
    "max_images": 100
  },
  {
    "id_ours": "0cb0ac942caffc54ffd85e424bea380145684431",
    "id_search_engine": "8009774311",
    "url": "https://farm9.staticflickr.com/8179/8009774311_865cb6395b_o.jpg",
    "url_type": "url_o",
    "wnid": "n03187595",
    "search_key": "rotary phone",
    "search_engine": "flickr",
    "uploader": "becca",
    "date_upload_our_db": "2018-09-11 20:49:39",
    "date_taken": "2012-09-21 16:44:20",
    "date_upload_search_engine": "2012-09-21 11:21:58",
    "width": null,
    "height": null,
    "max_taken_date": "2014-07-11",
    "max_uploaded_date": "2014-07-11",
    "min_taken_date": "2012-07-11",
    "min_uploaded_date": "2012-07-11",
    "search_sort": "date-posted-asc",
    "max_images": 100
  },
  {
    "id_ours": "4a4fc823e9d0089f35f445cab1fc0a1d50a22eaf",
    "id_search_engine": "8010369025",
    "url": "https://farm9.staticflickr.com/8438/8010369025_70b3dafaba_o.jpg",
    "url_type": "url_o",
    "wnid": "n03187595",
    "search_key": "rotary phone",
    "search_engine": "flickr",
    "uploader": "becca",
    "date_upload_our_db": "2018-09-11 20:49:39",
    "date_taken": "2012-09-21 17:12:01",
    "date_upload_search_engine": "2012-09-21 15:13:52",
    "width": null,
    "height": null,
    "max_taken_date": "2014-07-11",
    "max_uploaded_date": "2014-07-11",
    "min_taken_date": "2012-07-11",
    "min_uploaded_date": "2012-07-11",
    "search_sort": "date-posted-asc",
    "max_images": 100
  },
  {
    "id_ours": "8b0993cf52948570940f377f3cbcc398892c9062",
    "id_search_engine": "8017646047",
    "url": "https://farm9.staticflickr.com/8440/8017646047_b9c64d6dbd_o.jpg",
    "url_type": "url_o",
    "wnid": "n03187595",
    "search_key": "rotary phone",
    "search_engine": "flickr",
    "uploader": "becca",
    "date_upload_our_db": "2018-09-11 20:49:39",
    "date_taken": "2012-09-23 16:59:38",
    "date_upload_search_engine": "2012-09-23 17:13:23",
    "width": null,
    "height": null,
    "max_taken_date": "2014-07-11",
    "max_uploaded_date": "2014-07-11",
    "min_taken_date": "2012-07-11",
    "min_uploaded_date": "2012-07-11",
    "search_sort": "date-posted-asc",
    "max_images": 100
  },
  {
    "id_ours": "a8ec401bb1e08ae05d9a35046ba847cb95786455",
    "id_search_engine": "8017633491",
    "url": "https://farm9.staticflickr.com/8308/8017633491_33ebf464db_o.jpg",
    "url_type": "url_o",
    "wnid": "n03187595",
    "search_key": "rotary phone",
    "search_engine": "flickr",
    "uploader": "becca",
    "date_upload_our_db": "2018-09-11 20:49:39",
    "date_taken": "2012-09-23 16:55:44",
    "date_upload_search_engine": "2012-09-23 17:13:23",
    "width": null,
    "height": null,
    "max_taken_date": "2014-07-11",
    "max_uploaded_date": "2014-07-11",
    "min_taken_date": "2012-07-11",
    "min_uploaded_date": "2012-07-11",
    "search_sort": "date-posted-asc",
    "max_images": 100
  },
  {
    "id_ours": "04b0b1fdc887b22424fa48c05c4285f030f74d14",
    "id_search_engine": "8017652836",
    "url": "https://farm9.staticflickr.com/8320/8017652836_f3233eee42_o.jpg",
    "url_type": "url_o",
    "wnid": "n03187595",
    "search_key": "rotary phone",
    "search_engine": "flickr",
    "uploader": "becca",
    "date_upload_our_db": "2018-09-11 20:49:39",
    "date_taken": "2012-09-23 17:01:02",
    "date_upload_search_engine": "2012-09-23 17:13:24",
    "width": null,
    "height": null,
    "max_taken_date": "2014-07-11",
    "max_uploaded_date": "2014-07-11",
    "min_taken_date": "2012-07-11",
    "min_uploaded_date": "2012-07-11",
    "search_sort": "date-posted-asc",
    "max_images": 100
  },
  {
    "id_ours": "d13477986626a2bf88e41171a5a1a62b8ac36ab7",
    "id_search_engine": "8017661684",
    "url": "https://farm9.staticflickr.com/8322/8017661684_c47c40fe4f_o.jpg",
    "url_type": "url_o",
    "wnid": "n03187595",
    "search_key": "rotary phone",
    "search_engine": "flickr",
    "uploader": "becca",
    "date_upload_our_db": "2018-09-11 20:49:39",
    "date_taken": "2012-09-23 17:03:55",
    "date_upload_search_engine": "2012-09-23 17:13:24",
    "width": null,
    "height": null,
    "max_taken_date": "2014-07-11",
    "max_uploaded_date": "2014-07-11",
    "min_taken_date": "2012-07-11",
    "min_uploaded_date": "2012-07-11",
    "search_sort": "date-posted-asc",
    "max_images": 100
  },
  {
    "id_ours": "7d2312b6780742bd1842ae067c3a907d230a4120",
    "id_search_engine": "8018092349",
    "url": "https://farm9.staticflickr.com/8298/8018092349_4af969f261_o.jpg",
    "url_type": "url_o",
    "wnid": "n03187595",
    "search_key": "rotary phone",
    "search_engine": "flickr",
    "uploader": "becca",
    "date_upload_our_db": "2018-09-11 20:49:39",
    "date_taken": "2012-08-19 12:15:20",
    "date_upload_search_engine": "2012-09-23 19:27:31",
    "width": "4928",
    "height": "3264",
    "max_taken_date": "2014-07-11",
    "max_uploaded_date": "2014-07-11",
    "min_taken_date": "2012-07-11",
    "min_uploaded_date": "2012-07-11",
    "search_sort": "date-posted-asc",
    "max_images": 100
  },
  {
    "id_ours": "e405966b5ce7542217f9110aecdf18dd9bc229ab",
    "id_search_engine": "8028162780",
    "url": "https://farm9.staticflickr.com/8179/8028162780_37274b3aff_o.jpg",
    "url_type": "url_o",
    "wnid": "n03187595",
    "search_key": "rotary phone",
    "search_engine": "flickr",
    "uploader": "becca",
    "date_upload_our_db": "2018-09-11 20:49:39",
    "date_taken": "2012-09-26 04:19:18",
    "date_upload_search_engine": "2012-09-26 16:53:05",
    "width": null,
    "height": null,
    "max_taken_date": "2014-07-11",
    "max_uploaded_date": "2014-07-11",
    "min_taken_date": "2012-07-11",
    "min_uploaded_date": "2012-07-11",
    "search_sort": "date-posted-asc",
    "max_images": 100
  },
  {
    "id_ours": "bdf3179b2d668bc6689f2f24e0c8e8316ac46ecf",
    "id_search_engine": "8028482626",
    "url": "https://farm9.staticflickr.com/8315/8028482626_5f1f3f2ba4_o.jpg",
    "url_type": "url_o",
    "wnid": "n03187595",
    "search_key": "rotary phone",
    "search_engine": "flickr",
    "uploader": "becca",
    "date_upload_our_db": "2018-09-11 20:49:39",
    "date_taken": "2012-09-26 20:45:29",
    "date_upload_search_engine": "2012-09-26 19:22:40",
    "width": null,
    "height": null,
    "max_taken_date": "2014-07-11",
    "max_uploaded_date": "2014-07-11",
    "min_taken_date": "2012-07-11",
    "min_uploaded_date": "2012-07-11",
    "search_sort": "date-posted-asc",
    "max_images": 100
  },
  {
    "id_ours": "f00ebe943604565b8c7e9b6444e42e902b2fb20f",
    "id_search_engine": "8028917942",
    "url": "https://farm9.staticflickr.com/8030/8028917942_c4d1b826c2_o.jpg",
    "url_type": "url_o",
    "wnid": "n03187595",
    "search_key": "rotary phone",
    "search_engine": "flickr",
    "uploader": "becca",
    "date_upload_our_db": "2018-09-11 20:49:39",
    "date_taken": "2012-09-24 17:30:42",
    "date_upload_search_engine": "2012-09-26 23:25:34",
    "width": "1600",
    "height": "1201",
    "max_taken_date": "2014-07-11",
    "max_uploaded_date": "2014-07-11",
    "min_taken_date": "2012-07-11",
    "min_uploaded_date": "2012-07-11",
    "search_sort": "date-posted-asc",
    "max_images": 100
  },
  {
    "id_ours": "64163b9649f9d552cb1ffd458c07064a976107c0",
    "id_search_engine": "8035087612",
    "url": "https://farm9.staticflickr.com/8454/8035087612_9dbdcf3acb_o.jpg",
    "url_type": "url_o",
    "wnid": "n03187595",
    "search_key": "rotary phone",
    "search_engine": "flickr",
    "uploader": "becca",
    "date_upload_our_db": "2018-09-11 20:49:39",
    "date_taken": "2012-09-03 11:09:40",
    "date_upload_search_engine": "2012-09-29 01:24:11",
    "width": "3996",
    "height": "2543",
    "max_taken_date": "2014-07-11",
    "max_uploaded_date": "2014-07-11",
    "min_taken_date": "2012-07-11",
    "min_uploaded_date": "2012-07-11",
    "search_sort": "date-posted-asc",
    "max_images": 100
  },
  {
    "id_ours": "aa441f4e5c3aa54eb6109c940364f74eb90376e7",
    "id_search_engine": "8037636328",
    "url": "https://farm9.staticflickr.com/8454/8037636328_33a1736834_o.jpg",
    "url_type": "url_o",
    "wnid": "n03187595",
    "search_key": "rotary phone",
    "search_engine": "flickr",
    "uploader": "becca",
    "date_upload_our_db": "2018-09-11 20:49:39",
    "date_taken": "2012-09-29 21:24:29",
    "date_upload_search_engine": "2012-09-29 18:24:29",
    "width": "2133",
    "height": "2511",
    "max_taken_date": "2014-07-11",
    "max_uploaded_date": "2014-07-11",
    "min_taken_date": "2012-07-11",
    "min_uploaded_date": "2012-07-11",
    "search_sort": "date-posted-asc",
    "max_images": 100
  },
  {
    "id_ours": "31179906e40d4285a928d11910d0d9e9f1884c76",
    "id_search_engine": "8042178113",
    "url": "https://farm9.staticflickr.com/8175/8042178113_fdaa8ea4ef_o.jpg",
    "url_type": "url_o",
    "wnid": "n03187595",
    "search_key": "rotary phone",
    "search_engine": "flickr",
    "uploader": "becca",
    "date_upload_our_db": "2018-09-11 20:49:39",
    "date_taken": "2012-09-30 22:18:31",
    "date_upload_search_engine": "2012-09-30 20:54:24",
    "width": "4608",
    "height": "3456",
    "max_taken_date": "2014-07-11",
    "max_uploaded_date": "2014-07-11",
    "min_taken_date": "2012-07-11",
    "min_uploaded_date": "2012-07-11",
    "search_sort": "date-posted-asc",
    "max_images": 100
  },
  {
    "id_ours": "236f0521b7bc8ef33e876f89bd499d33fbb90f14",
    "id_search_engine": "8043099804",
    "url": "https://farm9.staticflickr.com/8315/8043099804_2a5706232e_o.jpg",
    "url_type": "url_o",
    "wnid": "n03187595",
    "search_key": "rotary phone",
    "search_engine": "flickr",
    "uploader": "becca",
    "date_upload_our_db": "2018-09-11 20:49:39",
    "date_taken": "2012-09-30 17:57:18",
    "date_upload_search_engine": "2012-10-01 04:33:11",
    "width": "4032",
    "height": "3024",
    "max_taken_date": "2014-07-11",
    "max_uploaded_date": "2014-07-11",
    "min_taken_date": "2012-07-11",
    "min_uploaded_date": "2012-07-11",
    "search_sort": "date-posted-asc",
    "max_images": 100
  },
  {
    "id_ours": "4b44be9020eba9b2d46c4dc5a25394162cb12a42",
    "id_search_engine": "8050091229",
    "url": "https://farm9.staticflickr.com/8314/8050091229_2554e5be5f_o.png",
    "url_type": "url_o",
    "wnid": "n03187595",
    "search_key": "rotary phone",
    "search_engine": "flickr",
    "uploader": "becca",
    "date_upload_our_db": "2018-09-11 20:49:39",
    "date_taken": "2012-10-03 07:33:29",
    "date_upload_search_engine": "2012-10-03 04:34:04",
    "width": "2448",
    "height": "3264",
    "max_taken_date": "2014-07-11",
    "max_uploaded_date": "2014-07-11",
    "min_taken_date": "2012-07-11",
    "min_uploaded_date": "2012-07-11",
    "search_sort": "date-posted-asc",
    "max_images": 100
  },
  {
    "id_ours": "8b0ff6dd820f8f42b584568cd7db19f1678d8175",
    "id_search_engine": "8071201251",
    "url": "https://farm9.staticflickr.com/8311/8071201251_4dc79f9805_o.jpg",
    "url_type": "url_o",
    "wnid": "n03187595",
    "search_key": "rotary phone",
    "search_engine": "flickr",
    "uploader": "becca",
    "date_upload_our_db": "2018-09-11 20:49:39",
    "date_taken": "2012-10-09 12:11:57",
    "date_upload_search_engine": "2012-10-09 09:30:43",
    "width": "4256",
    "height": "2832",
    "max_taken_date": "2014-07-11",
    "max_uploaded_date": "2014-07-11",
    "min_taken_date": "2012-07-11",
    "min_uploaded_date": "2012-07-11",
    "search_sort": "date-posted-asc",
    "max_images": 100
  },
  {
    "id_ours": "23f306e30928f687963d61ff75c455aba42dd876",
    "id_search_engine": "8072153003",
    "url": "https://farm9.staticflickr.com/8170/8072153003_249c322e71_o.jpg",
    "url_type": "url_o",
    "wnid": "n03187595",
    "search_key": "rotary phone",
    "search_engine": "flickr",
    "uploader": "becca",
    "date_upload_our_db": "2018-09-11 20:49:39",
    "date_taken": "2012-08-18 11:19:42",
    "date_upload_search_engine": "2012-10-09 14:44:08",
    "width": "4320",
    "height": "2432",
    "max_taken_date": "2014-07-11",
    "max_uploaded_date": "2014-07-11",
    "min_taken_date": "2012-07-11",
    "min_uploaded_date": "2012-07-11",
    "search_sort": "date-posted-asc",
    "max_images": 100
  },
  {
    "id_ours": "f89254ff8beac331b913ffb8feb3495ced3a3250",
    "id_search_engine": "8075467410",
    "url": "https://farm9.staticflickr.com/8476/8075467410_258d9dafaa_o.jpg",
    "url_type": "url_o",
    "wnid": "n03187595",
    "search_key": "rotary phone",
    "search_engine": "flickr",
    "uploader": "becca",
    "date_upload_our_db": "2018-09-11 20:49:39",
    "date_taken": "2012-08-31 14:22:29",
    "date_upload_search_engine": "2012-10-10 17:04:39",
    "width": null,
    "height": null,
    "max_taken_date": "2014-07-11",
    "max_uploaded_date": "2014-07-11",
    "min_taken_date": "2012-07-11",
    "min_uploaded_date": "2012-07-11",
    "search_sort": "date-posted-asc",
    "max_images": 100
  },
  {
    "id_ours": "f5a604d6204acd8786804498f79b551e52e87f02",
    "id_search_engine": "8077097098",
    "url": "https://farm9.staticflickr.com/8189/8077097098_822ebcb531_o.jpg",
    "url_type": "url_o",
    "wnid": "n03187595",
    "search_key": "rotary phone",
    "search_engine": "flickr",
    "uploader": "becca",
    "date_upload_our_db": "2018-09-11 20:49:39",
    "date_taken": "2012-10-08 12:31:11",
    "date_upload_search_engine": "2012-10-11 07:48:58",
    "width": null,
    "height": null,
    "max_taken_date": "2014-07-11",
    "max_uploaded_date": "2014-07-11",
    "min_taken_date": "2012-07-11",
    "min_uploaded_date": "2012-07-11",
    "search_sort": "date-posted-asc",
    "max_images": 100
  },
  {
    "id_ours": "cf6f30387d96b01204ddfebd3c0f31e45a30701c",
    "id_search_engine": "8090568377",
    "url": "https://farm9.staticflickr.com/8469/8090568377_fa7944973a_o.jpg",
    "url_type": "url_o",
    "wnid": "n03187595",
    "search_key": "rotary phone",
    "search_engine": "flickr",
    "uploader": "becca",
    "date_upload_our_db": "2018-09-11 20:49:39",
    "date_taken": "2012-10-09 10:46:36",
    "date_upload_search_engine": "2012-10-15 08:52:02",
    "width": "634",
    "height": "470",
    "max_taken_date": "2014-07-11",
    "max_uploaded_date": "2014-07-11",
    "min_taken_date": "2012-07-11",
    "min_uploaded_date": "2012-07-11",
    "search_sort": "date-posted-asc",
    "max_images": 100
  },
  {
    "id_ours": "b5e53fdcd7b1218da9c19345bd0249866139e6e8",
    "id_search_engine": "8090572668",
    "url": "https://farm9.staticflickr.com/8334/8090572668_fb3422fffb_o.jpg",
    "url_type": "url_o",
    "wnid": "n03187595",
    "search_key": "rotary phone",
    "search_engine": "flickr",
    "uploader": "becca",
    "date_upload_our_db": "2018-09-11 20:49:39",
    "date_taken": "2012-10-09 10:45:53",
    "date_upload_search_engine": "2012-10-15 08:52:02",
    "width": "439",
    "height": "648",
    "max_taken_date": "2014-07-11",
    "max_uploaded_date": "2014-07-11",
    "min_taken_date": "2012-07-11",
    "min_uploaded_date": "2012-07-11",
    "search_sort": "date-posted-asc",
    "max_images": 100
  },
  {
    "id_ours": "8acd141310dd1d91818ddd828d982e5dc4fccdc2",
    "id_search_engine": "8091847570",
    "url": "https://farm9.staticflickr.com/8472/8091847570_41f625ae67_o.jpg",
    "url_type": "url_o",
    "wnid": "n03187595",
    "search_key": "rotary phone",
    "search_engine": "flickr",
    "uploader": "becca",
    "date_upload_our_db": "2018-09-11 20:49:39",
    "date_taken": "2012-10-15 16:58:49",
    "date_upload_search_engine": "2012-10-15 15:38:27",
    "width": null,
    "height": null,
    "max_taken_date": "2014-07-11",
    "max_uploaded_date": "2014-07-11",
    "min_taken_date": "2012-07-11",
    "min_uploaded_date": "2012-07-11",
    "search_sort": "date-posted-asc",
    "max_images": 100
  },
  {
    "id_ours": "38c416f4535cfa712c681839a31ffcb0a0382415",
    "id_search_engine": "8106459738",
    "url": "https://farm9.staticflickr.com/8185/8106459738_7e9ca8fb9f_c.jpg",
    "url_type": "url_c",
    "wnid": "n03187595",
    "search_key": "rotary phone",
    "search_engine": "flickr",
    "uploader": "becca",
    "date_upload_our_db": "2018-09-11 20:49:39",
    "date_taken": "2012-10-18 09:21:09",
    "date_upload_search_engine": "2012-10-20 13:54:23",
    "width": null,
    "height": null,
    "max_taken_date": "2014-07-11",
    "max_uploaded_date": "2014-07-11",
    "min_taken_date": "2012-07-11",
    "min_uploaded_date": "2012-07-11",
    "search_sort": "date-posted-asc",
    "max_images": 100
  },
  {
    "id_ours": "859165995c5562c760ae06076bd21c95fb52b2b7",
    "id_search_engine": "8106460032",
    "url": "https://farm9.staticflickr.com/8051/8106460032_bd740ac429_c.jpg",
    "url_type": "url_c",
    "wnid": "n03187595",
    "search_key": "rotary phone",
    "search_engine": "flickr",
    "uploader": "becca",
    "date_upload_our_db": "2018-09-11 20:49:39",
    "date_taken": "2012-10-18 09:19:41",
    "date_upload_search_engine": "2012-10-20 13:54:22",
    "width": null,
    "height": null,
    "max_taken_date": "2014-07-11",
    "max_uploaded_date": "2014-07-11",
    "min_taken_date": "2012-07-11",
    "min_uploaded_date": "2012-07-11",
    "search_sort": "date-posted-asc",
    "max_images": 100
  },
  {
    "id_ours": "061e50ea99b44b7927aa80175cb528e75b270d6a",
    "id_search_engine": "8107300675",
    "url": "https://farm9.staticflickr.com/8332/8107300675_67058fccb2_o.jpg",
    "url_type": "url_o",
    "wnid": "n03187595",
    "search_key": "rotary phone",
    "search_engine": "flickr",
    "uploader": "becca",
    "date_upload_our_db": "2018-09-11 20:49:39",
    "date_taken": "2012-10-20 19:41:16",
    "date_upload_search_engine": "2012-10-20 19:41:16",
    "width": null,
    "height": null,
    "max_taken_date": "2014-07-11",
    "max_uploaded_date": "2014-07-11",
    "min_taken_date": "2012-07-11",
    "min_uploaded_date": "2012-07-11",
    "search_sort": "date-posted-asc",
    "max_images": 100
  },
  {
    "id_ours": "209369475dd30042bb17a0294dc256e526993501",
    "id_search_engine": "8120391609",
    "url": "https://farm9.staticflickr.com/8474/8120391609_090a871526_h.jpg",
    "url_type": "url_h",
    "wnid": "n03187595",
    "search_key": "rotary phone",
    "search_engine": "flickr",
    "uploader": "becca",
    "date_upload_our_db": "2018-09-11 20:49:39",
    "date_taken": "2012-10-13 18:33:21",
    "date_upload_search_engine": "2012-10-24 15:31:36",
    "width": null,
    "height": null,
    "max_taken_date": "2014-07-11",
    "max_uploaded_date": "2014-07-11",
    "min_taken_date": "2012-07-11",
    "min_uploaded_date": "2012-07-11",
    "search_sort": "date-posted-asc",
    "max_images": 100
  },
  {
    "id_ours": "2250f3d44117ac5949e51c78637698e320787f05",
    "id_search_engine": "8122916787",
    "url": "https://farm9.staticflickr.com/8465/8122916787_99982f1e7d_h.jpg",
    "url_type": "url_h",
    "wnid": "n03187595",
    "search_key": "rotary phone",
    "search_engine": "flickr",
    "uploader": "becca",
    "date_upload_our_db": "2018-09-11 20:49:39",
    "date_taken": "2012-10-25 17:27:00",
    "date_upload_search_engine": "2012-10-25 12:47:49",
    "width": null,
    "height": null,
    "max_taken_date": "2014-07-11",
    "max_uploaded_date": "2014-07-11",
    "min_taken_date": "2012-07-11",
    "min_uploaded_date": "2012-07-11",
    "search_sort": "date-posted-asc",
    "max_images": 100
  },
  {
    "id_ours": "6392a4484951b673375f21878e63911ce9ac2f51",
    "id_search_engine": "8126462370",
    "url": "https://farm9.staticflickr.com/8335/8126462370_01bed17f18_o.jpg",
    "url_type": "url_o",
    "wnid": "n03187595",
    "search_key": "rotary phone",
    "search_engine": "flickr",
    "uploader": "becca",
    "date_upload_our_db": "2018-09-11 20:49:39",
    "date_taken": "2012-10-17 12:29:59",
    "date_upload_search_engine": "2012-10-26 18:30:09",
    "width": "3264",
    "height": "2448",
    "max_taken_date": "2014-07-11",
    "max_uploaded_date": "2014-07-11",
    "min_taken_date": "2012-07-11",
    "min_uploaded_date": "2012-07-11",
    "search_sort": "date-posted-asc",
    "max_images": 100
  },
  {
    "id_ours": "2b6adc4f52c663231643612baac8ce779866d7f4",
    "id_search_engine": "8127742373",
    "url": "https://farm9.staticflickr.com/8331/8127742373_2038b4d95d_k.jpg",
    "url_type": "url_k",
    "wnid": "n03187595",
    "search_key": "rotary phone",
    "search_engine": "flickr",
    "uploader": "becca",
    "date_upload_our_db": "2018-09-11 20:49:39",
    "date_taken": "2012-10-26 22:14:39",
    "date_upload_search_engine": "2012-10-27 07:44:52",
    "width": null,
    "height": null,
    "max_taken_date": "2014-07-11",
    "max_uploaded_date": "2014-07-11",
    "min_taken_date": "2012-07-11",
    "min_uploaded_date": "2012-07-11",
    "search_sort": "date-posted-asc",
    "max_images": 100
  },
  {
    "id_ours": "547ada79f81e9423ef7bbc274568ff26652fe96b",
    "id_search_engine": "8131766475",
    "url": "https://farm9.staticflickr.com/8044/8131766475_6d1a3e7aa0_k.jpg",
    "url_type": "url_k",
    "wnid": "n03187595",
    "search_key": "rotary phone",
    "search_engine": "flickr",
    "uploader": "becca",
    "date_upload_our_db": "2018-09-11 20:49:39",
    "date_taken": "2012-10-28 12:31:59",
    "date_upload_search_engine": "2012-10-28 10:56:24",
    "width": null,
    "height": null,
    "max_taken_date": "2014-07-11",
    "max_uploaded_date": "2014-07-11",
    "min_taken_date": "2012-07-11",
    "min_uploaded_date": "2012-07-11",
    "search_sort": "date-posted-asc",
    "max_images": 100
  },
  {
    "id_ours": "cb1a7d0decad27958df6132e63d2b4f6a159cb14",
    "id_search_engine": "8136046318",
    "url": "https://farm9.staticflickr.com/8186/8136046318_492c00d3bf_k.jpg",
    "url_type": "url_k",
    "wnid": "n03187595",
    "search_key": "rotary phone",
    "search_engine": "flickr",
    "uploader": "becca",
    "date_upload_our_db": "2018-09-11 20:49:39",
    "date_taken": "2012-10-29 12:11:22",
    "date_upload_search_engine": "2012-10-29 12:41:39",
    "width": null,
    "height": null,
    "max_taken_date": "2014-07-11",
    "max_uploaded_date": "2014-07-11",
    "min_taken_date": "2012-07-11",
    "min_uploaded_date": "2012-07-11",
    "search_sort": "date-posted-asc",
    "max_images": 100
  },
  {
    "id_ours": "e0134171f74150a2500d107f5176fc93b6f51f05",
    "id_search_engine": "8137619741",
    "url": "https://farm9.staticflickr.com/8469/8137619741_198a282611_k.jpg",
    "url_type": "url_k",
    "wnid": "n03187595",
    "search_key": "rotary phone",
    "search_engine": "flickr",
    "uploader": "becca",
    "date_upload_our_db": "2018-09-11 20:49:39",
    "date_taken": "2012-10-29 23:45:03",
    "date_upload_search_engine": "2012-10-29 23:36:55",
    "width": null,
    "height": null,
    "max_taken_date": "2014-07-11",
    "max_uploaded_date": "2014-07-11",
    "min_taken_date": "2012-07-11",
    "min_uploaded_date": "2012-07-11",
    "search_sort": "date-posted-asc",
    "max_images": 100
  },
  {
    "id_ours": "8daa21f37f0950625bc30726cb9c842457d13d6b",
    "id_search_engine": "8180213658",
    "url": "https://farm9.staticflickr.com/8201/8180213658_b03034078c_o.jpg",
    "url_type": "url_o",
    "wnid": "n03187595",
    "search_key": "rotary phone",
    "search_engine": "flickr",
    "uploader": "becca",
    "date_upload_our_db": "2018-09-11 20:49:39",
    "date_taken": "2012-11-11 13:34:28",
    "date_upload_search_engine": "2012-11-12 14:05:56",
    "width": "3521",
    "height": "2641",
    "max_taken_date": "2014-07-11",
    "max_uploaded_date": "2014-07-11",
    "min_taken_date": "2012-07-11",
    "min_uploaded_date": "2012-07-11",
    "search_sort": "date-posted-asc",
    "max_images": 100
  },
  {
    "id_ours": "13f551c9f5573e6f537838c3f5f992e62ad0cf93",
    "id_search_engine": "8180174917",
    "url": "https://farm9.staticflickr.com/8337/8180174917_6426aaf84f_o.jpg",
    "url_type": "url_o",
    "wnid": "n03187595",
    "search_key": "rotary phone",
    "search_engine": "flickr",
    "uploader": "becca",
    "date_upload_our_db": "2018-09-11 20:49:39",
    "date_taken": "2012-11-11 13:29:09",
    "date_upload_search_engine": "2012-11-12 14:04:18",
    "width": "4000",
    "height": "3000",
    "max_taken_date": "2014-07-11",
    "max_uploaded_date": "2014-07-11",
    "min_taken_date": "2012-07-11",
    "min_uploaded_date": "2012-07-11",
    "search_sort": "date-posted-asc",
    "max_images": 100
  },
  {
    "id_ours": "8c34059fa22dd8167c2cc5ea4ccc378800c2e3d7",
    "id_search_engine": "8180211872",
    "url": "https://farm9.staticflickr.com/8059/8180211872_cedfbbcd9f_o.jpg",
    "url_type": "url_o",
    "wnid": "n03187595",
    "search_key": "rotary phone",
    "search_engine": "flickr",
    "uploader": "becca",
    "date_upload_our_db": "2018-09-11 20:49:39",
    "date_taken": "2012-11-11 13:33:48",
    "date_upload_search_engine": "2012-11-12 14:05:20",
    "width": "4000",
    "height": "3000",
    "max_taken_date": "2014-07-11",
    "max_uploaded_date": "2014-07-11",
    "min_taken_date": "2012-07-11",
    "min_uploaded_date": "2012-07-11",
    "search_sort": "date-posted-asc",
    "max_images": 100
  },
  {
    "id_ours": "2cf2f691bbd6e25b423093c93703fbf56930e264",
    "id_search_engine": "8189011275",
    "url": "https://farm9.staticflickr.com/8480/8189011275_465083045f_h.jpg",
    "url_type": "url_h",
    "wnid": "n03187595",
    "search_key": "rotary phone",
    "search_engine": "flickr",
    "uploader": "becca",
    "date_upload_our_db": "2018-09-11 20:49:39",
    "date_taken": "2012-10-20 14:21:56",
    "date_upload_search_engine": "2012-11-15 19:49:20",
    "width": null,
    "height": null,
    "max_taken_date": "2014-07-11",
    "max_uploaded_date": "2014-07-11",
    "min_taken_date": "2012-07-11",
    "min_uploaded_date": "2012-07-11",
    "search_sort": "date-posted-asc",
    "max_images": 100
  },
  {
    "id_ours": "09628c57e5416de04d13a999fda77e7c53d67da1",
    "id_search_engine": "8193865406",
    "url": "https://farm9.staticflickr.com/8201/8193865406_1f2abd2f54_o.jpg",
    "url_type": "url_o",
    "wnid": "n03187595",
    "search_key": "rotary phone",
    "search_engine": "flickr",
    "uploader": "becca",
    "date_upload_our_db": "2018-09-11 20:49:39",
    "date_taken": "2012-11-17 16:40:22",
    "date_upload_search_engine": "2012-11-17 08:45:20",
    "width": null,
    "height": null,
    "max_taken_date": "2014-07-11",
    "max_uploaded_date": "2014-07-11",
    "min_taken_date": "2012-07-11",
    "min_uploaded_date": "2012-07-11",
    "search_sort": "date-posted-asc",
    "max_images": 100
  },
  {
    "id_ours": "7abcb3ca42f843a37c459540e67fd4e7d8667c22",
    "id_search_engine": "8214009398",
    "url": "https://farm9.staticflickr.com/8200/8214009398_825382d636_o.jpg",
    "url_type": "url_o",
    "wnid": "n03187595",
    "search_key": "rotary phone",
    "search_engine": "flickr",
    "uploader": "becca",
    "date_upload_our_db": "2018-09-11 20:49:39",
    "date_taken": "2012-11-24 05:36:21",
    "date_upload_search_engine": "2012-11-24 05:37:38",
    "width": null,
    "height": null,
    "max_taken_date": "2014-07-11",
    "max_uploaded_date": "2014-07-11",
    "min_taken_date": "2012-07-11",
    "min_uploaded_date": "2012-07-11",
    "search_sort": "date-posted-asc",
    "max_images": 100
  },
  {
    "id_ours": "3b07c2978a1a1e787f59ebac2d6d43cd0b6df888",
    "id_search_engine": "8231805394",
    "url": "https://farm9.staticflickr.com/8067/8231805394_6539da606f_c.jpg",
    "url_type": "url_c",
    "wnid": "n03187595",
    "search_key": "rotary phone",
    "search_engine": "flickr",
    "uploader": "becca",
    "date_upload_our_db": "2018-09-11 20:49:39",
    "date_taken": "2012-11-29 21:47:49",
    "date_upload_search_engine": "2012-11-29 20:10:06",
    "width": null,
    "height": null,
    "max_taken_date": "2014-07-11",
    "max_uploaded_date": "2014-07-11",
    "min_taken_date": "2012-07-11",
    "min_uploaded_date": "2012-07-11",
    "search_sort": "date-posted-asc",
    "max_images": 100
  },
  {
    "id_ours": "e1d52ca582aa3af294a58bbb103a2aed4d547a62",
    "id_search_engine": "8232579600",
    "url": "https://farm9.staticflickr.com/8204/8232579600_a0794cf83c_c.jpg",
    "url_type": "url_c",
    "wnid": "n03187595",
    "search_key": "rotary phone",
    "search_engine": "flickr",
    "uploader": "becca",
    "date_upload_our_db": "2018-09-11 20:49:39",
    "date_taken": "2012-11-30 08:34:15",
    "date_upload_search_engine": "2012-11-30 05:34:46",
    "width": null,
    "height": null,
    "max_taken_date": "2014-07-11",
    "max_uploaded_date": "2014-07-11",
    "min_taken_date": "2012-07-11",
    "min_uploaded_date": "2012-07-11",
    "search_sort": "date-posted-asc",
    "max_images": 100
  },
  {
    "id_ours": "3feb83793ee25ec2ed089ab18487c5219ccb70c1",
    "id_search_engine": "8231517211",
    "url": "https://farm9.staticflickr.com/8489/8231517211_0bd1fd19e3_c.jpg",
    "url_type": "url_c",
    "wnid": "n03187595",
    "search_key": "rotary phone",
    "search_engine": "flickr",
    "uploader": "becca",
    "date_upload_our_db": "2018-09-11 20:49:39",
    "date_taken": "2012-11-30 08:33:51",
    "date_upload_search_engine": "2012-11-30 05:34:47",
    "width": null,
    "height": null,
    "max_taken_date": "2014-07-11",
    "max_uploaded_date": "2014-07-11",
    "min_taken_date": "2012-07-11",
    "min_uploaded_date": "2012-07-11",
    "search_sort": "date-posted-asc",
    "max_images": 100
  },
  {
    "id_ours": "4dc3217fe460dfbe8131ed60ad85dc6ca78307de",
    "id_search_engine": "8246239017",
    "url": "https://farm9.staticflickr.com/8487/8246239017_e4c21ae633_o.jpg",
    "url_type": "url_o",
    "wnid": "n03187595",
    "search_key": "rotary phone",
    "search_engine": "flickr",
    "uploader": "becca",
    "date_upload_our_db": "2018-09-11 20:49:39",
    "date_taken": "2012-12-04 09:06:36",
    "date_upload_search_engine": "2012-12-05 04:36:54",
    "width": null,
    "height": null,
    "max_taken_date": "2014-07-11",
    "max_uploaded_date": "2014-07-11",
    "min_taken_date": "2012-07-11",
    "min_uploaded_date": "2012-07-11",
    "search_sort": "date-posted-asc",
    "max_images": 100
  },
  {
    "id_ours": "488a3d1feda39b3ca6d9c49e90c48b198740acb3",
    "id_search_engine": "8258082831",
    "url": "https://farm9.staticflickr.com/8338/8258082831_d209dbf3b1_k.jpg",
    "url_type": "url_k",
    "wnid": "n03187595",
    "search_key": "rotary phone",
    "search_engine": "flickr",
    "uploader": "becca",
    "date_upload_our_db": "2018-09-11 20:49:39",
    "date_taken": "2012-12-09 16:52:33",
    "date_upload_search_engine": "2012-12-09 12:53:06",
    "width": null,
    "height": null,
    "max_taken_date": "2014-07-11",
    "max_uploaded_date": "2014-07-11",
    "min_taken_date": "2012-07-11",
    "min_uploaded_date": "2012-07-11",
    "search_sort": "date-posted-asc",
    "max_images": 100
  },
  {
    "id_ours": "1db448ed937406e222a0dd82ec443eea58528bf7",
    "id_search_engine": "8267769136",
    "url": "https://farm9.staticflickr.com/8479/8267769136_a993d1aa60_z.jpg",
    "url_type": "url_z",
    "wnid": "n03187595",
    "search_key": "rotary phone",
    "search_engine": "flickr",
    "uploader": "becca",
    "date_upload_our_db": "2018-09-11 20:49:39",
    "date_taken": "2012-12-12 13:07:51",
    "date_upload_search_engine": "2012-12-12 10:07:51",
    "width": null,
    "height": null,
    "max_taken_date": "2014-07-11",
    "max_uploaded_date": "2014-07-11",
    "min_taken_date": "2012-07-11",
    "min_uploaded_date": "2012-07-11",
    "search_sort": "date-posted-asc",
    "max_images": 100
  },
  {
    "id_ours": "cb212e3106b2020f7c4647ab22afeeb8aef1ccd4",
    "id_search_engine": "8270331648",
    "url": "https://farm9.staticflickr.com/8214/8270331648_10a5278c6d_c.jpg",
    "url_type": "url_c",
    "wnid": "n03187595",
    "search_key": "rotary phone",
    "search_engine": "flickr",
    "uploader": "becca",
    "date_upload_our_db": "2018-09-11 20:49:39",
    "date_taken": "2012-12-12 08:53:16",
    "date_upload_search_engine": "2012-12-13 08:55:38",
    "width": null,
    "height": null,
    "max_taken_date": "2014-07-11",
    "max_uploaded_date": "2014-07-11",
    "min_taken_date": "2012-07-11",
    "min_uploaded_date": "2012-07-11",
    "search_sort": "date-posted-asc",
    "max_images": 100
  },
  {
    "id_ours": "da27935b14970e988e3ff0ae1a7b9fd2fbfab481",
    "id_search_engine": "8273659914",
    "url": "https://farm9.staticflickr.com/8203/8273659914_3d8bf8ee16_o.jpg",
    "url_type": "url_o",
    "wnid": "n03187595",
    "search_key": "rotary phone",
    "search_engine": "flickr",
    "uploader": "becca",
    "date_upload_our_db": "2018-09-11 20:49:39",
    "date_taken": "2012-12-14 14:51:21",
    "date_upload_search_engine": "2012-12-14 14:21:02",
    "width": "4000",
    "height": "3000",
    "max_taken_date": "2014-07-11",
    "max_uploaded_date": "2014-07-11",
    "min_taken_date": "2012-07-11",
    "min_uploaded_date": "2012-07-11",
    "search_sort": "date-posted-asc",
    "max_images": 100
  },
  {
    "id_ours": "424f48a966fa9a4462173dd6e8285dd4c4893183",
    "id_search_engine": "8274587486",
    "url": "https://farm9.staticflickr.com/8082/8274587486_4ecb29c894_o.jpg",
    "url_type": "url_o",
    "wnid": "n03187595",
    "search_key": "rotary phone",
    "search_engine": "flickr",
    "uploader": "becca",
    "date_upload_our_db": "2018-09-11 20:49:39",
    "date_taken": "2012-11-11 15:07:46",
    "date_upload_search_engine": "2012-12-15 00:59:42",
    "width": "4000",
    "height": "3000",
    "max_taken_date": "2014-07-11",
    "max_uploaded_date": "2014-07-11",
    "min_taken_date": "2012-07-11",
    "min_uploaded_date": "2012-07-11",
    "search_sort": "date-posted-asc",
    "max_images": 100
  },
  {
    "id_ours": "5a951e5af8fa3d17572b9712027f9987e83cbff5",
    "id_search_engine": "8274585778",
    "url": "https://farm9.staticflickr.com/8345/8274585778_ae4e9aea69_o.jpg",
    "url_type": "url_o",
    "wnid": "n03187595",
    "search_key": "rotary phone",
    "search_engine": "flickr",
    "uploader": "becca",
    "date_upload_our_db": "2018-09-11 20:49:39",
    "date_taken": "2012-11-11 12:03:47",
    "date_upload_search_engine": "2012-12-15 00:58:11",
    "width": "3315",
    "height": "3000",
    "max_taken_date": "2014-07-11",
    "max_uploaded_date": "2014-07-11",
    "min_taken_date": "2012-07-11",
    "min_uploaded_date": "2012-07-11",
    "search_sort": "date-posted-asc",
    "max_images": 100
  },
  {
    "id_ours": "4d0a93279622ee88e256f2d671ee4b85b2d9e099",
    "id_search_engine": "8273519981",
    "url": "https://farm9.staticflickr.com/8216/8273519981_7505f4c6c0_o.jpg",
    "url_type": "url_o",
    "wnid": "n03187595",
    "search_key": "rotary phone",
    "search_engine": "flickr",
    "uploader": "becca",
    "date_upload_our_db": "2018-09-11 20:49:39",
    "date_taken": "2012-11-11 10:52:52",
    "date_upload_search_engine": "2012-12-15 00:57:37",
    "width": "1990",
    "height": "1495",
    "max_taken_date": "2014-07-11",
    "max_uploaded_date": "2014-07-11",
    "min_taken_date": "2012-07-11",
    "min_uploaded_date": "2012-07-11",
    "search_sort": "date-posted-asc",
    "max_images": 100
  },
  {
    "id_ours": "26df53ca4181617926ae9bf3f8cee08e62a1c3dd",
    "id_search_engine": "8273524141",
    "url": "https://farm9.staticflickr.com/8504/8273524141_c8ebe9d31e_o.jpg",
    "url_type": "url_o",
    "wnid": "n03187595",
    "search_key": "rotary phone",
    "search_engine": "flickr",
    "uploader": "becca",
    "date_upload_our_db": "2018-09-11 20:49:39",
    "date_taken": "2012-11-11 15:09:53",
    "date_upload_search_engine": "2012-12-15 01:01:08",
    "width": "4000",
    "height": "3000",
    "max_taken_date": "2014-07-11",
    "max_uploaded_date": "2014-07-11",
    "min_taken_date": "2012-07-11",
    "min_uploaded_date": "2012-07-11",
    "search_sort": "date-posted-asc",
    "max_images": 100
  },
  {
    "id_ours": "9898ebe78bf4da621ad8cb9a522db83c838ca1c4",
    "id_search_engine": "8274590150",
    "url": "https://farm9.staticflickr.com/8083/8274590150_69cb1f9a27_o.jpg",
    "url_type": "url_o",
    "wnid": "n03187595",
    "search_key": "rotary phone",
    "search_engine": "flickr",
    "uploader": "becca",
    "date_upload_our_db": "2018-09-11 20:49:39",
    "date_taken": "2012-11-11 15:45:00",
    "date_upload_search_engine": "2012-12-15 01:02:01",
    "width": "4000",
    "height": "3000",
    "max_taken_date": "2014-07-11",
    "max_uploaded_date": "2014-07-11",
    "min_taken_date": "2012-07-11",
    "min_uploaded_date": "2012-07-11",
    "search_sort": "date-posted-asc",
    "max_images": 100
  },
  {
    "id_ours": "325aa8b07f2a26b714f987e97c9d00078a15e671",
    "id_search_engine": "8274592092",
    "url": "https://farm9.staticflickr.com/8492/8274592092_38a2859e3c_o.jpg",
    "url_type": "url_o",
    "wnid": "n03187595",
    "search_key": "rotary phone",
    "search_engine": "flickr",
    "uploader": "becca",
    "date_upload_our_db": "2018-09-11 20:49:39",
    "date_taken": "2012-11-11 18:32:36",
    "date_upload_search_engine": "2012-12-15 01:03:43",
    "width": "4000",
    "height": "3000",
    "max_taken_date": "2014-07-11",
    "max_uploaded_date": "2014-07-11",
    "min_taken_date": "2012-07-11",
    "min_uploaded_date": "2012-07-11",
    "search_sort": "date-posted-asc",
    "max_images": 100
  },
  {
    "id_ours": "7dd41bb5655147e95eedb55d921a9eeb7676e9bc",
    "id_search_engine": "8274588282",
    "url": "https://farm9.staticflickr.com/8062/8274588282_bb5019f6b6_o.jpg",
    "url_type": "url_o",
    "wnid": "n03187595",
    "search_key": "rotary phone",
    "search_engine": "flickr",
    "uploader": "becca",
    "date_upload_our_db": "2018-09-11 20:49:39",
    "date_taken": "2012-11-11 15:08:22",
    "date_upload_search_engine": "2012-12-15 01:00:25",
    "width": "4000",
    "height": "3000",
    "max_taken_date": "2014-07-11",
    "max_uploaded_date": "2014-07-11",
    "min_taken_date": "2012-07-11",
    "min_uploaded_date": "2012-07-11",
    "search_sort": "date-posted-asc",
    "max_images": 100
  },
  {
    "id_ours": "5855c0ace5233043b757f543c0990e244ce81685",
    "id_search_engine": "8282392162",
    "url": "https://farm9.staticflickr.com/8477/8282392162_5d6137c56c_o.jpg",
    "url_type": "url_o",
    "wnid": "n03187595",
    "search_key": "rotary phone",
    "search_engine": "flickr",
    "uploader": "becca",
    "date_upload_our_db": "2018-09-11 20:49:39",
    "date_taken": "2012-12-11 14:36:34",
    "date_upload_search_engine": "2012-12-17 12:52:06",
    "width": null,
    "height": null,
    "max_taken_date": "2014-07-11",
    "max_uploaded_date": "2014-07-11",
    "min_taken_date": "2012-07-11",
    "min_uploaded_date": "2012-07-11",
    "search_sort": "date-posted-asc",
    "max_images": 100
  },
  {
    "id_ours": "e9263f198fea21857ef5e140e0930c741516b474",
    "id_search_engine": "8282035343",
    "url": "https://farm9.staticflickr.com/8503/8282035343_6547cc96de_o.jpg",
    "url_type": "url_o",
    "wnid": "n03187595",
    "search_key": "rotary phone",
    "search_engine": "flickr",
    "uploader": "becca",
    "date_upload_our_db": "2018-09-11 20:49:39",
    "date_taken": "2012-12-11 14:36:00",
    "date_upload_search_engine": "2012-12-17 17:34:33",
    "width": null,
    "height": null,
    "max_taken_date": "2014-07-11",
    "max_uploaded_date": "2014-07-11",
    "min_taken_date": "2012-07-11",
    "min_uploaded_date": "2012-07-11",
    "search_sort": "date-posted-asc",
    "max_images": 100
  }
]