[
  {
    "id_ours": "78248a9328e0a0325bedeaaeea92458d0a6e0144",
    "id_search_engine": "7593583560",
    "url": "https://farm9.staticflickr.com/8163/7593583560_d4f0aa9051_o.jpg",
    "url_type": "url_o",
    "wnid": "n03954731",
    "search_key": "woodworking plane",
    "search_engine": "flickr",
    "uploader": "becca",
    "date_upload_our_db": "2018-11-30 08:00:33",
    "date_taken": "2012-07-17 17:31:57",
    "date_upload_search_engine": "2012-07-17 16:07:53",
    "width": "960",
    "height": "720",
    "max_taken_date": "2014-07-11",
    "max_uploaded_date": "2014-07-11",
    "min_taken_date": "2012-07-11",
    "min_uploaded_date": "2012-07-11",
    "search_sort": "date-posted-asc",
    "max_images": 200,
    "batch": "d97079811b7eeaffca23043afbdea0056967cba58c63f98654d01dbdc5e7a80b"
  },
  {
    "id_ours": "aef0eacb0e6dfeb5277624001285c329f814a8d8",
    "id_search_engine": "7647199228",
    "url": "https://farm9.staticflickr.com/8018/7647199228_481a3ee227_k.jpg",
    "url_type": "url_k",
    "wnid": "n03954731",
    "search_key": "woodworking plane",
    "search_engine": "flickr",
    "uploader": "becca",
    "date_upload_our_db": "2018-11-30 08:00:33",
    "date_taken": "2012-07-25 17:40:05",
    "date_upload_search_engine": "2012-07-25 17:59:01",
    "width": 2048,
    "height": 1536,
    "max_taken_date": "2014-07-11",
    "max_uploaded_date": "2014-07-11",
    "min_taken_date": "2012-07-11",
    "min_uploaded_date": "2012-07-11",
    "search_sort": "date-posted-asc",
    "max_images": 200,
    "batch": "d97079811b7eeaffca23043afbdea0056967cba58c63f98654d01dbdc5e7a80b"
  },
  {
    "id_ours": "cecc2241e8914a5f0f1eefdc150bb4f74a4dc2b3",
    "id_search_engine": "7986924935",
    "url": "https://farm9.staticflickr.com/8309/7986924935_4f00d09688_c.jpg",
    "url_type": "url_c",
    "wnid": "n03954731",
    "search_key": "woodworking plane",
    "search_engine": "flickr",
    "uploader": "becca",
    "date_upload_our_db": "2018-11-30 08:00:33",
    "date_taken": "2012-08-16 09:27:14",
    "date_upload_search_engine": "2012-09-14 17:01:55",
    "width": null,
    "height": null,
    "max_taken_date": "2014-07-11",
    "max_uploaded_date": "2014-07-11",
    "min_taken_date": "2012-07-11",
    "min_uploaded_date": "2012-07-11",
    "search_sort": "date-posted-asc",
    "max_images": 200,
    "batch": "d97079811b7eeaffca23043afbdea0056967cba58c63f98654d01dbdc5e7a80b"
  },
  {
    "id_ours": "bcb47cc49a8491d352063f3f6485ccbe5ef31728",
    "id_search_engine": "8000390538",
    "url": "https://farm9.staticflickr.com/8179/8000390538_5b97f0e817_o.jpg",
    "url_type": "url_o",
    "wnid": "n03954731",
    "search_key": "woodworking plane",
    "search_engine": "flickr",
    "uploader": "becca",
    "date_upload_our_db": "2018-11-30 08:00:33",
    "date_taken": "2012-09-18 09:37:53",
    "date_upload_search_engine": "2012-09-18 10:39:00",
    "width": "3264",
    "height": "2448",
    "max_taken_date": "2014-07-11",
    "max_uploaded_date": "2014-07-11",
    "min_taken_date": "2012-07-11",
    "min_uploaded_date": "2012-07-11",
    "search_sort": "date-posted-asc",
    "max_images": 200,
    "batch": "d97079811b7eeaffca23043afbdea0056967cba58c63f98654d01dbdc5e7a80b"
  },
  {
    "id_ours": "8d56626f531c3eb2fdb78d7b12c7a8e23db0abee",
    "id_search_engine": "8000390228",
    "url": "https://farm9.staticflickr.com/8310/8000390228_46713a2a04_o.jpg",
    "url_type": "url_o",
    "wnid": "n03954731",
    "search_key": "woodworking plane",
    "search_engine": "flickr",
    "uploader": "becca",
    "date_upload_our_db": "2018-11-30 08:00:33",
    "date_taken": "2012-09-18 09:51:17",
    "date_upload_search_engine": "2012-09-18 10:39:01",
    "width": "3264",
    "height": "2448",
    "max_taken_date": "2014-07-11",
    "max_uploaded_date": "2014-07-11",
    "min_taken_date": "2012-07-11",
    "min_uploaded_date": "2012-07-11",
    "search_sort": "date-posted-asc",
    "max_images": 200,
    "batch": "d97079811b7eeaffca23043afbdea0056967cba58c63f98654d01dbdc5e7a80b"
  },
  {
    "id_ours": "50b3f90702614af376bef443cab53d8ba448e982",
    "id_search_engine": "8106943709",
    "url": "https://farm9.staticflickr.com/8466/8106943709_d86e144596_o.jpg",
    "url_type": "url_o",
    "wnid": "n03954731",
    "search_key": "woodworking plane",
    "search_engine": "flickr",
    "uploader": "becca",
    "date_upload_our_db": "2018-11-30 08:00:33",
    "date_taken": "2012-10-20 20:30:41",
    "date_upload_search_engine": "2012-10-20 17:06:24",
    "width": "1280",
    "height": "1024",
    "max_taken_date": "2014-07-11",
    "max_uploaded_date": "2014-07-11",
    "min_taken_date": "2012-07-11",
    "min_uploaded_date": "2012-07-11",
    "search_sort": "date-posted-asc",
    "max_images": 200,
    "batch": "d97079811b7eeaffca23043afbdea0056967cba58c63f98654d01dbdc5e7a80b"
  },
  {
    "id_ours": "d0a989098ab52ad6997d603944ddb0b8189fd487",
    "id_search_engine": "8175233045",
    "url": "https://farm9.staticflickr.com/8350/8175233045_6debfc1a88_k.jpg",
    "url_type": "url_k",
    "wnid": "n03954731",
    "search_key": "woodworking plane",
    "search_engine": "flickr",
    "uploader": "becca",
    "date_upload_our_db": "2018-11-30 08:00:33",
    "date_taken": "2012-11-10 11:30:41",
    "date_upload_search_engine": "2012-11-11 06:48:56",
    "width": null,
    "height": null,
    "max_taken_date": "2014-07-11",
    "max_uploaded_date": "2014-07-11",
    "min_taken_date": "2012-07-11",
    "min_uploaded_date": "2012-07-11",
    "search_sort": "date-posted-asc",
    "max_images": 200,
    "batch": "d97079811b7eeaffca23043afbdea0056967cba58c63f98654d01dbdc5e7a80b"
  },
  {
    "id_ours": "cd158385ee6e62dafd4e589cf379cedaa08d0e20",
    "id_search_engine": "8175235435",
    "url": "https://farm9.staticflickr.com/8478/8175235435_34d8913e9f_k.jpg",
    "url_type": "url_k",
    "wnid": "n03954731",
    "search_key": "woodworking plane",
    "search_engine": "flickr",
    "uploader": "becca",
    "date_upload_our_db": "2018-11-30 08:00:33",
    "date_taken": "2012-11-10 11:29:34",
    "date_upload_search_engine": "2012-11-11 06:48:55",
    "width": null,
    "height": null,
    "max_taken_date": "2014-07-11",
    "max_uploaded_date": "2014-07-11",
    "min_taken_date": "2012-07-11",
    "min_uploaded_date": "2012-07-11",
    "search_sort": "date-posted-asc",
    "max_images": 200,
    "batch": "d97079811b7eeaffca23043afbdea0056967cba58c63f98654d01dbdc5e7a80b"
  },
  {
    "id_ours": "93b5b6e6a6e6783d6faa6bfbe7feb0337981f360",
    "id_search_engine": "8175223955",
    "url": "https://farm9.staticflickr.com/8201/8175223955_4c73f74cff_k.jpg",
    "url_type": "url_k",
    "wnid": "n03954731",
    "search_key": "woodworking plane",
    "search_engine": "flickr",
    "uploader": "becca",
    "date_upload_our_db": "2018-11-30 08:00:33",
    "date_taken": "2012-11-10 11:46:56",
    "date_upload_search_engine": "2012-11-11 06:48:59",
    "width": null,
    "height": null,
    "max_taken_date": "2014-07-11",
    "max_uploaded_date": "2014-07-11",
    "min_taken_date": "2012-07-11",
    "min_uploaded_date": "2012-07-11",
    "search_sort": "date-posted-asc",
    "max_images": 200,
    "batch": "d97079811b7eeaffca23043afbdea0056967cba58c63f98654d01dbdc5e7a80b"
  },
  {
    "id_ours": "e18bca051d49a800ff1cc499521cde765235d8ae",
    "id_search_engine": "8175261318",
    "url": "https://farm9.staticflickr.com/8489/8175261318_5970c7ce1e_k.jpg",
    "url_type": "url_k",
    "wnid": "n03954731",
    "search_key": "woodworking plane",
    "search_engine": "flickr",
    "uploader": "becca",
    "date_upload_our_db": "2018-11-30 08:00:33",
    "date_taken": "2012-11-10 11:31:16",
    "date_upload_search_engine": "2012-11-11 06:48:57",
    "width": null,
    "height": null,
    "max_taken_date": "2014-07-11",
    "max_uploaded_date": "2014-07-11",
    "min_taken_date": "2012-07-11",
    "min_uploaded_date": "2012-07-11",
    "search_sort": "date-posted-asc",
    "max_images": 200,
    "batch": "d97079811b7eeaffca23043afbdea0056967cba58c63f98654d01dbdc5e7a80b"
  },
  {
    "id_ours": "9055c6b21548320fa9d0d88abad8a629459624fa",
    "id_search_engine": "8175240087",
    "url": "https://farm9.staticflickr.com/8200/8175240087_5182bfc243_k.jpg",
    "url_type": "url_k",
    "wnid": "n03954731",
    "search_key": "woodworking plane",
    "search_engine": "flickr",
    "uploader": "becca",
    "date_upload_our_db": "2018-11-30 08:00:33",
    "date_taken": "2012-11-10 11:27:20",
    "date_upload_search_engine": "2012-11-11 06:48:54",
    "width": null,
    "height": null,
    "max_taken_date": "2014-07-11",
    "max_uploaded_date": "2014-07-11",
    "min_taken_date": "2012-07-11",
    "min_uploaded_date": "2012-07-11",
    "search_sort": "date-posted-asc",
    "max_images": 200,
    "batch": "d97079811b7eeaffca23043afbdea0056967cba58c63f98654d01dbdc5e7a80b"
  },
  {
    "id_ours": "f8867d279feba14bfcf78ce311170d2040ae0657",
    "id_search_engine": "8175270670",
    "url": "https://farm9.staticflickr.com/8207/8175270670_c36f17f5e1_k.jpg",
    "url_type": "url_k",
    "wnid": "n03954731",
    "search_key": "woodworking plane",
    "search_engine": "flickr",
    "uploader": "becca",
    "date_upload_our_db": "2018-11-30 08:00:33",
    "date_taken": "2012-11-10 11:27:41",
    "date_upload_search_engine": "2012-11-11 06:48:54",
    "width": null,
    "height": null,
    "max_taken_date": "2014-07-11",
    "max_uploaded_date": "2014-07-11",
    "min_taken_date": "2012-07-11",
    "min_uploaded_date": "2012-07-11",
    "search_sort": "date-posted-asc",
    "max_images": 200,
    "batch": "d97079811b7eeaffca23043afbdea0056967cba58c63f98654d01dbdc5e7a80b"
  },
  {
    "id_ours": "fc29c527b5da9f9a81d93608318c0696c4562f39",
    "id_search_engine": "8175221591",
    "url": "https://farm9.staticflickr.com/8346/8175221591_c9427f106c_k.jpg",
    "url_type": "url_k",
    "wnid": "n03954731",
    "search_key": "woodworking plane",
    "search_engine": "flickr",
    "uploader": "becca",
    "date_upload_our_db": "2018-11-30 08:00:33",
    "date_taken": "2012-11-10 11:47:22",
    "date_upload_search_engine": "2012-11-11 06:49:00",
    "width": null,
    "height": null,
    "max_taken_date": "2014-07-11",
    "max_uploaded_date": "2014-07-11",
    "min_taken_date": "2012-07-11",
    "min_uploaded_date": "2012-07-11",
    "search_sort": "date-posted-asc",
    "max_images": 200,
    "batch": "d97079811b7eeaffca23043afbdea0056967cba58c63f98654d01dbdc5e7a80b"
  },
  {
    "id_ours": "99650653285f6f1687046cf10399007f2b9bcbae",
    "id_search_engine": "8175211311",
    "url": "https://farm9.staticflickr.com/8480/8175211311_23a66bf301_k.jpg",
    "url_type": "url_k",
    "wnid": "n03954731",
    "search_key": "woodworking plane",
    "search_engine": "flickr",
    "uploader": "becca",
    "date_upload_our_db": "2018-11-30 08:00:33",
    "date_taken": "2012-11-10 11:49:38",
    "date_upload_search_engine": "2012-11-11 06:49:02",
    "width": null,
    "height": null,
    "max_taken_date": "2014-07-11",
    "max_uploaded_date": "2014-07-11",
    "min_taken_date": "2012-07-11",
    "min_uploaded_date": "2012-07-11",
    "search_sort": "date-posted-asc",
    "max_images": 200,
    "batch": "d97079811b7eeaffca23043afbdea0056967cba58c63f98654d01dbdc5e7a80b"
  },
  {
    "id_ours": "165b5374733b48674b4c10b2f4c33499daa03faa",
    "id_search_engine": "8194518770",
    "url": "https://farm9.staticflickr.com/8064/8194518770_0d301a84d0_o.jpg",
    "url_type": "url_o",
    "wnid": "n03954731",
    "search_key": "woodworking plane",
    "search_engine": "flickr",
    "uploader": "becca",
    "date_upload_our_db": "2018-11-30 08:00:33",
    "date_taken": "2012-11-17 16:32:05",
    "date_upload_search_engine": "2012-11-17 13:13:24",
    "width": "2832",
    "height": "1889",
    "max_taken_date": "2014-07-11",
    "max_uploaded_date": "2014-07-11",
    "min_taken_date": "2012-07-11",
    "min_uploaded_date": "2012-07-11",
    "search_sort": "date-posted-asc",
    "max_images": 200,
    "batch": "d97079811b7eeaffca23043afbdea0056967cba58c63f98654d01dbdc5e7a80b"
  },
  {
    "id_ours": "5231955533e6e56516cddc1b73a18ba274027e37",
    "id_search_engine": "8204513452",
    "url": "https://farm9.staticflickr.com/8344/8204513452_e3aa539309_k.jpg",
    "url_type": "url_k",
    "wnid": "n03954731",
    "search_key": "woodworking plane",
    "search_engine": "flickr",
    "uploader": "becca",
    "date_upload_our_db": "2018-11-30 08:00:33",
    "date_taken": "2012-11-20 14:29:08",
    "date_upload_search_engine": "2012-11-20 14:33:26",
    "width": null,
    "height": null,
    "max_taken_date": "2014-07-11",
    "max_uploaded_date": "2014-07-11",
    "min_taken_date": "2012-07-11",
    "min_uploaded_date": "2012-07-11",
    "search_sort": "date-posted-asc",
    "max_images": 200,
    "batch": "d97079811b7eeaffca23043afbdea0056967cba58c63f98654d01dbdc5e7a80b"
  },
  {
    "id_ours": "bc8e6ae3954caef15296ad34a1b0196291c3d05b",
    "id_search_engine": "8356050372",
    "url": "https://farm9.staticflickr.com/8225/8356050372_5673eb72cc_o.jpg",
    "url_type": "url_o",
    "wnid": "n03954731",
    "search_key": "woodworking plane",
    "search_engine": "flickr",
    "uploader": "becca",
    "date_upload_our_db": "2018-11-30 08:00:33",
    "date_taken": "2013-01-06 19:38:46",
    "date_upload_search_engine": "2013-01-06 16:02:32",
    "width": null,
    "height": null,
    "max_taken_date": "2014-07-11",
    "max_uploaded_date": "2014-07-11",
    "min_taken_date": "2012-07-11",
    "min_uploaded_date": "2012-07-11",
    "search_sort": "date-posted-asc",
    "max_images": 200,
    "batch": "d97079811b7eeaffca23043afbdea0056967cba58c63f98654d01dbdc5e7a80b"
  },
  {
    "id_ours": "320151bd8456d936c6947bd0fd401f342da4a3a9",
    "id_search_engine": "8378151879",
    "url": "https://farm9.staticflickr.com/8510/8378151879_d83d51cf0d_k.jpg",
    "url_type": "url_k",
    "wnid": "n03954731",
    "search_key": "woodworking plane",
    "search_engine": "flickr",
    "uploader": "becca",
    "date_upload_our_db": "2018-11-30 08:00:33",
    "date_taken": "2013-01-13 13:43:46",
    "date_upload_search_engine": "2013-01-13 18:49:21",
    "width": null,
    "height": null,
    "max_taken_date": "2014-07-11",
    "max_uploaded_date": "2014-07-11",
    "min_taken_date": "2012-07-11",
    "min_uploaded_date": "2012-07-11",
    "search_sort": "date-posted-asc",
    "max_images": 200,
    "batch": "d97079811b7eeaffca23043afbdea0056967cba58c63f98654d01dbdc5e7a80b"
  },
  {
    "id_ours": "d8aa3f67b90dacb0dc74e71a5dbd630bada545b9",
    "id_search_engine": "8400058721",
    "url": "https://farm9.staticflickr.com/8325/8400058721_58c7907595_o.jpg",
    "url_type": "url_o",
    "wnid": "n03954731",
    "search_key": "woodworking plane",
    "search_engine": "flickr",
    "uploader": "becca",
    "date_upload_our_db": "2018-11-30 08:00:33",
    "date_taken": "2013-01-21 01:19:59",
    "date_upload_search_engine": "2013-01-20 19:54:34",
    "width": null,
    "height": null,
    "max_taken_date": "2014-07-11",
    "max_uploaded_date": "2014-07-11",
    "min_taken_date": "2012-07-11",
    "min_uploaded_date": "2012-07-11",
    "search_sort": "date-posted-asc",
    "max_images": 200,
    "batch": "d97079811b7eeaffca23043afbdea0056967cba58c63f98654d01dbdc5e7a80b"
  },
  {
    "id_ours": "2db5abc2af46449ede6676150b6c1e236442967f",
    "id_search_engine": "8430027608",
    "url": "https://farm9.staticflickr.com/8499/8430027608_bc4b7e07e8_h.jpg",
    "url_type": "url_h",
    "wnid": "n03954731",
    "search_key": "woodworking plane",
    "search_engine": "flickr",
    "uploader": "becca",
    "date_upload_our_db": "2018-11-30 08:00:33",
    "date_taken": "2013-01-30 11:51:31",
    "date_upload_search_engine": "2013-01-30 05:26:53",
    "width": null,
    "height": null,
    "max_taken_date": "2014-07-11",
    "max_uploaded_date": "2014-07-11",
    "min_taken_date": "2012-07-11",
    "min_uploaded_date": "2012-07-11",
    "search_sort": "date-posted-asc",
    "max_images": 200,
    "batch": "d97079811b7eeaffca23043afbdea0056967cba58c63f98654d01dbdc5e7a80b"
  },
  {
    "id_ours": "c2cbe3b22e1f7181d1030e8a2c332f9c5709849b",
    "id_search_engine": "8443298500",
    "url": "https://farm9.staticflickr.com/8071/8443298500_bab09e0a2c_k.jpg",
    "url_type": "url_k",
    "wnid": "n03954731",
    "search_key": "woodworking plane",
    "search_engine": "flickr",
    "uploader": "becca",
    "date_upload_our_db": "2018-11-30 08:00:33",
    "date_taken": "2013-02-03 19:04:40",
    "date_upload_search_engine": "2013-02-03 16:18:30",
    "width": null,
    "height": null,
    "max_taken_date": "2014-07-11",
    "max_uploaded_date": "2014-07-11",
    "min_taken_date": "2012-07-11",
    "min_uploaded_date": "2012-07-11",
    "search_sort": "date-posted-asc",
    "max_images": 200,
    "batch": "d97079811b7eeaffca23043afbdea0056967cba58c63f98654d01dbdc5e7a80b"
  },
  {
    "id_ours": "814ed9e4e9fa7484ae50a5e5e425cc628bbc88f1",
    "id_search_engine": "8446665638",
    "url": "https://farm9.staticflickr.com/8495/8446665638_d564b4f5b4_k.jpg",
    "url_type": "url_k",
    "wnid": "n03954731",
    "search_key": "woodworking plane",
    "search_engine": "flickr",
    "uploader": "becca",
    "date_upload_our_db": "2018-11-30 08:00:33",
    "date_taken": "2013-02-04 19:51:48",
    "date_upload_search_engine": "2013-02-04 17:46:34",
    "width": null,
    "height": null,
    "max_taken_date": "2014-07-11",
    "max_uploaded_date": "2014-07-11",
    "min_taken_date": "2012-07-11",
    "min_uploaded_date": "2012-07-11",
    "search_sort": "date-posted-asc",
    "max_images": 200,
    "batch": "d97079811b7eeaffca23043afbdea0056967cba58c63f98654d01dbdc5e7a80b"
  },
  {
    "id_ours": "f74fe3ce8aa31c5b323824c808430d5062e0818b",
    "id_search_engine": "8459096381",
    "url": "https://farm9.staticflickr.com/8516/8459096381_148c8cc7ca_o.jpg",
    "url_type": "url_o",
    "wnid": "n03954731",
    "search_key": "woodworking plane",
    "search_engine": "flickr",
    "uploader": "becca",
    "date_upload_our_db": "2018-11-30 08:00:33",
    "date_taken": "2013-02-09 16:10:52",
    "date_upload_search_engine": "2013-02-09 16:10:52",
    "width": "3240",
    "height": "4320",
    "max_taken_date": "2014-07-11",
    "max_uploaded_date": "2014-07-11",
    "min_taken_date": "2012-07-11",
    "min_uploaded_date": "2012-07-11",
    "search_sort": "date-posted-asc",
    "max_images": 200,
    "batch": "d97079811b7eeaffca23043afbdea0056967cba58c63f98654d01dbdc5e7a80b"
  },
  {
    "id_ours": "14af3f19ce65fc4b068b3c454d5f2ee1feb4e1b3",
    "id_search_engine": "8460224828",
    "url": "https://farm9.staticflickr.com/8088/8460224828_7949866cf9_o.jpg",
    "url_type": "url_o",
    "wnid": "n03954731",
    "search_key": "woodworking plane",
    "search_engine": "flickr",
    "uploader": "becca",
    "date_upload_our_db": "2018-11-30 08:00:33",
    "date_taken": "2013-02-09 16:22:47",
    "date_upload_search_engine": "2013-02-09 16:22:47",
    "width": "3240",
    "height": "4320",
    "max_taken_date": "2014-07-11",
    "max_uploaded_date": "2014-07-11",
    "min_taken_date": "2012-07-11",
    "min_uploaded_date": "2012-07-11",
    "search_sort": "date-posted-asc",
    "max_images": 200,
    "batch": "d97079811b7eeaffca23043afbdea0056967cba58c63f98654d01dbdc5e7a80b"
  },
  {
    "id_ours": "eeef2c06804eacc343c027d4a28f81d822f52a03",
    "id_search_engine": "8466466279",
    "url": "https://farm9.staticflickr.com/8379/8466466279_a0df321148_o.jpg",
    "url_type": "url_o",
    "wnid": "n03954731",
    "search_key": "woodworking plane",
    "search_engine": "flickr",
    "uploader": "becca",
    "date_upload_our_db": "2018-11-30 08:00:33",
    "date_taken": "2013-02-10 15:27:36",
    "date_upload_search_engine": "2013-02-11 22:05:37",
    "width": null,
    "height": null,
    "max_taken_date": "2014-07-11",
    "max_uploaded_date": "2014-07-11",
    "min_taken_date": "2012-07-11",
    "min_uploaded_date": "2012-07-11",
    "search_sort": "date-posted-asc",
    "max_images": 200,
    "batch": "d97079811b7eeaffca23043afbdea0056967cba58c63f98654d01dbdc5e7a80b"
  },
  {
    "id_ours": "47b962f61cf0076d2faf92c6c6b7d3aeb9957a32",
    "id_search_engine": "8467223493",
    "url": "https://farm9.staticflickr.com/8521/8467223493_02ca529ff6_o.jpg",
    "url_type": "url_o",
    "wnid": "n03954731",
    "search_key": "woodworking plane",
    "search_engine": "flickr",
    "uploader": "becca",
    "date_upload_our_db": "2018-11-30 08:00:33",
    "date_taken": "2013-02-12 06:06:47",
    "date_upload_search_engine": "2013-02-12 06:06:47",
    "width": "3240",
    "height": "4320",
    "max_taken_date": "2014-07-11",
    "max_uploaded_date": "2014-07-11",
    "min_taken_date": "2012-07-11",
    "min_uploaded_date": "2012-07-11",
    "search_sort": "date-posted-asc",
    "max_images": 200,
    "batch": "d97079811b7eeaffca23043afbdea0056967cba58c63f98654d01dbdc5e7a80b"
  },
  {
    "id_ours": "8b09fe5e7f9a1ad53494b043c7e598cf04adcd8b",
    "id_search_engine": "8471631472",
    "url": "https://farm9.staticflickr.com/8369/8471631472_a1aac22c53_o.jpg",
    "url_type": "url_o",
    "wnid": "n03954731",
    "search_key": "woodworking plane",
    "search_engine": "flickr",
    "uploader": "becca",
    "date_upload_our_db": "2018-11-30 08:00:33",
    "date_taken": "2013-02-13 09:57:40",
    "date_upload_search_engine": "2013-02-13 09:57:40",
    "width": "576",
    "height": "768",
    "max_taken_date": "2014-07-11",
    "max_uploaded_date": "2014-07-11",
    "min_taken_date": "2012-07-11",
    "min_uploaded_date": "2012-07-11",
    "search_sort": "date-posted-asc",
    "max_images": 200,
    "batch": "d97079811b7eeaffca23043afbdea0056967cba58c63f98654d01dbdc5e7a80b"
  },
  {
    "id_ours": "e23e2198874aa7600fb5a1ec8e04c3c80550d77b",
    "id_search_engine": "8471637784",
    "url": "https://farm9.staticflickr.com/8092/8471637784_88431c9166_o.jpg",
    "url_type": "url_o",
    "wnid": "n03954731",
    "search_key": "woodworking plane",
    "search_engine": "flickr",
    "uploader": "becca",
    "date_upload_our_db": "2018-11-30 08:00:33",
    "date_taken": "2013-02-13 10:00:23",
    "date_upload_search_engine": "2013-02-13 10:00:23",
    "width": "1024",
    "height": "768",
    "max_taken_date": "2014-07-11",
    "max_uploaded_date": "2014-07-11",
    "min_taken_date": "2012-07-11",
    "min_uploaded_date": "2012-07-11",
    "search_sort": "date-posted-asc",
    "max_images": 200,
    "batch": "d97079811b7eeaffca23043afbdea0056967cba58c63f98654d01dbdc5e7a80b"
  },
  {
    "id_ours": "e7310ceb2b0f454204386affafe81fefa8df13aa",
    "id_search_engine": "8470542681",
    "url": "https://farm9.staticflickr.com/8242/8470542681_8be2ea6ea5_o.jpg",
    "url_type": "url_o",
    "wnid": "n03954731",
    "search_key": "woodworking plane",
    "search_engine": "flickr",
    "uploader": "becca",
    "date_upload_our_db": "2018-11-30 08:00:33",
    "date_taken": "2013-02-13 10:00:54",
    "date_upload_search_engine": "2013-02-13 10:00:54",
    "width": 576,
    "height": 768,
    "max_taken_date": "2014-07-11",
    "max_uploaded_date": "2014-07-11",
    "min_taken_date": "2012-07-11",
    "min_uploaded_date": "2012-07-11",
    "search_sort": "date-posted-asc",
    "max_images": 200,
    "batch": "d97079811b7eeaffca23043afbdea0056967cba58c63f98654d01dbdc5e7a80b"
  },
  {
    "id_ours": "d672d42c14aae935d47ac67ca27f5a06f5ef9522",
    "id_search_engine": "8470577681",
    "url": "https://farm9.staticflickr.com/8369/8470577681_277c256467_o.jpg",
    "url_type": "url_o",
    "wnid": "n03954731",
    "search_key": "woodworking plane",
    "search_engine": "flickr",
    "uploader": "becca",
    "date_upload_our_db": "2018-11-30 08:00:33",
    "date_taken": "2013-02-13 10:16:22",
    "date_upload_search_engine": "2013-02-13 10:16:22",
    "width": "1024",
    "height": "768",
    "max_taken_date": "2014-07-11",
    "max_uploaded_date": "2014-07-11",
    "min_taken_date": "2012-07-11",
    "min_uploaded_date": "2012-07-11",
    "search_sort": "date-posted-asc",
    "max_images": 200,
    "batch": "d97079811b7eeaffca23043afbdea0056967cba58c63f98654d01dbdc5e7a80b"
  },
  {
    "id_ours": "a78412c77be0394990c7d0692ea25d49f0a2f19f",
    "id_search_engine": "8470576669",
    "url": "https://farm9.staticflickr.com/8510/8470576669_4402bc7ea9_o.jpg",
    "url_type": "url_o",
    "wnid": "n03954731",
    "search_key": "woodworking plane",
    "search_engine": "flickr",
    "uploader": "becca",
    "date_upload_our_db": "2018-11-30 08:00:33",
    "date_taken": "2013-02-13 10:15:55",
    "date_upload_search_engine": "2013-02-13 10:15:55",
    "width": "1003",
    "height": "768",
    "max_taken_date": "2014-07-11",
    "max_uploaded_date": "2014-07-11",
    "min_taken_date": "2012-07-11",
    "min_uploaded_date": "2012-07-11",
    "search_sort": "date-posted-asc",
    "max_images": 200,
    "batch": "d97079811b7eeaffca23043afbdea0056967cba58c63f98654d01dbdc5e7a80b"
  },
  {
    "id_ours": "468c05086fd1b7921ab379955f9e6aa2f3ba7405",
    "id_search_engine": "8536069621",
    "url": "https://farm9.staticflickr.com/8381/8536069621_18c1512781_o.jpg",
    "url_type": "url_o",
    "wnid": "n03954731",
    "search_key": "woodworking plane",
    "search_engine": "flickr",
    "uploader": "becca",
    "date_upload_our_db": "2018-11-30 08:00:33",
    "date_taken": "2012-11-14 15:19:52",
    "date_upload_search_engine": "2013-03-07 07:20:49",
    "width": 3008,
    "height": 2000,
    "max_taken_date": "2014-07-11",
    "max_uploaded_date": "2014-07-11",
    "min_taken_date": "2012-07-11",
    "min_uploaded_date": "2012-07-11",
    "search_sort": "date-posted-asc",
    "max_images": 200,
    "batch": "d97079811b7eeaffca23043afbdea0056967cba58c63f98654d01dbdc5e7a80b"
  },
  {
    "id_ours": "32663e898481c82cc1575318c841b062c7e02b65",
    "id_search_engine": "8567824420",
    "url": "https://farm9.staticflickr.com/8378/8567824420_cbceaa411b_o.jpg",
    "url_type": "url_o",
    "wnid": "n03954731",
    "search_key": "woodworking plane",
    "search_engine": "flickr",
    "uploader": "becca",
    "date_upload_our_db": "2018-11-30 08:00:33",
    "date_taken": "2013-03-11 14:10:55",
    "date_upload_search_engine": "2013-03-17 20:45:16",
    "width": 3168,
    "height": 4752,
    "max_taken_date": "2014-07-11",
    "max_uploaded_date": "2014-07-11",
    "min_taken_date": "2012-07-11",
    "min_uploaded_date": "2012-07-11",
    "search_sort": "date-posted-asc",
    "max_images": 200,
    "batch": "d97079811b7eeaffca23043afbdea0056967cba58c63f98654d01dbdc5e7a80b"
  },
  {
    "id_ours": "99ba40adb8cd33a09f174bfd30dcc0fc78608450",
    "id_search_engine": "8580059873",
    "url": "https://farm9.staticflickr.com/8368/8580059873_9f054a0574_o.jpg",
    "url_type": "url_o",
    "wnid": "n03954731",
    "search_key": "woodworking plane",
    "search_engine": "flickr",
    "uploader": "becca",
    "date_upload_our_db": "2018-11-30 08:00:33",
    "date_taken": "2013-03-21 12:37:18",
    "date_upload_search_engine": "2013-03-22 12:53:05",
    "width": 3456,
    "height": 2304,
    "max_taken_date": "2014-07-11",
    "max_uploaded_date": "2014-07-11",
    "min_taken_date": "2012-07-11",
    "min_uploaded_date": "2012-07-11",
    "search_sort": "date-posted-asc",
    "max_images": 200,
    "batch": "d97079811b7eeaffca23043afbdea0056967cba58c63f98654d01dbdc5e7a80b"
  },
  {
    "id_ours": "73e4cc60351efcfaa9d788ca1e4be24d8ec4924d",
    "id_search_engine": "8608268939",
    "url": "https://farm9.staticflickr.com/8390/8608268939_82c3364fe5_o.jpg",
    "url_type": "url_o",
    "wnid": "n03954731",
    "search_key": "woodworking plane",
    "search_engine": "flickr",
    "uploader": "becca",
    "date_upload_our_db": "2018-11-30 08:00:33",
    "date_taken": "2013-03-31 16:24:38",
    "date_upload_search_engine": "2013-04-01 00:18:05",
    "width": 2592,
    "height": 1936,
    "max_taken_date": "2014-07-11",
    "max_uploaded_date": "2014-07-11",
    "min_taken_date": "2012-07-11",
    "min_uploaded_date": "2012-07-11",
    "search_sort": "date-posted-asc",
    "max_images": 200,
    "batch": "d97079811b7eeaffca23043afbdea0056967cba58c63f98654d01dbdc5e7a80b"
  },
  {
    "id_ours": "6233d10501bc7e0c9691ce2620ce40448963ad67",
    "id_search_engine": "8629589536",
    "url": "https://farm9.staticflickr.com/8383/8629589536_a17a381b9f_c.jpg",
    "url_type": "url_c",
    "wnid": "n03954731",
    "search_key": "woodworking plane",
    "search_engine": "flickr",
    "uploader": "becca",
    "date_upload_our_db": "2018-11-30 08:00:33",
    "date_taken": "2013-04-07 14:27:48",
    "date_upload_search_engine": "2013-04-07 14:27:45",
    "width": null,
    "height": null,
    "max_taken_date": "2014-07-11",
    "max_uploaded_date": "2014-07-11",
    "min_taken_date": "2012-07-11",
    "min_uploaded_date": "2012-07-11",
    "search_sort": "date-posted-asc",
    "max_images": 200,
    "batch": "d97079811b7eeaffca23043afbdea0056967cba58c63f98654d01dbdc5e7a80b"
  },
  {
    "id_ours": "4d2d89322d683cbebf25c358ec78e1f63a5c01a8",
    "id_search_engine": "8630300727",
    "url": "https://farm9.staticflickr.com/8398/8630300727_7397d89a95_c.jpg",
    "url_type": "url_c",
    "wnid": "n03954731",
    "search_key": "woodworking plane",
    "search_engine": "flickr",
    "uploader": "becca",
    "date_upload_our_db": "2018-11-30 08:00:33",
    "date_taken": "2013-04-06 14:37:07",
    "date_upload_search_engine": "2013-04-08 03:48:52",
    "width": 800,
    "height": 598,
    "max_taken_date": "2014-07-11",
    "max_uploaded_date": "2014-07-11",
    "min_taken_date": "2012-07-11",
    "min_uploaded_date": "2012-07-11",
    "search_sort": "date-posted-asc",
    "max_images": 200,
    "batch": "d97079811b7eeaffca23043afbdea0056967cba58c63f98654d01dbdc5e7a80b"
  },
  {
    "id_ours": "a73039ebcc9487fc135c8d78c27fae495ab0e93a",
    "id_search_engine": "8666848575",
    "url": "https://farm9.staticflickr.com/8524/8666848575_421afae2b1_o.jpg",
    "url_type": "url_o",
    "wnid": "n03954731",
    "search_key": "woodworking plane",
    "search_engine": "flickr",
    "uploader": "becca",
    "date_upload_our_db": "2018-11-30 08:00:33",
    "date_taken": "2013-04-20 19:40:35",
    "date_upload_search_engine": "2013-04-21 00:35:23",
    "width": 2304,
    "height": 3456,
    "max_taken_date": "2014-07-11",
    "max_uploaded_date": "2014-07-11",
    "min_taken_date": "2012-07-11",
    "min_uploaded_date": "2012-07-11",
    "search_sort": "date-posted-asc",
    "max_images": 200,
    "batch": "d97079811b7eeaffca23043afbdea0056967cba58c63f98654d01dbdc5e7a80b"
  },
  {
    "id_ours": "1fde15693eb0b39b0af895cda28bbf5d3f79a912",
    "id_search_engine": "8667952310",
    "url": "https://farm9.staticflickr.com/8528/8667952310_a3fccc1763_o.jpg",
    "url_type": "url_o",
    "wnid": "n03954731",
    "search_key": "woodworking plane",
    "search_engine": "flickr",
    "uploader": "becca",
    "date_upload_our_db": "2018-11-30 08:00:33",
    "date_taken": "2013-04-20 19:24:00",
    "date_upload_search_engine": "2013-04-21 00:35:18",
    "width": 2304,
    "height": 3456,
    "max_taken_date": "2014-07-11",
    "max_uploaded_date": "2014-07-11",
    "min_taken_date": "2012-07-11",
    "min_uploaded_date": "2012-07-11",
    "search_sort": "date-posted-asc",
    "max_images": 200,
    "batch": "d97079811b7eeaffca23043afbdea0056967cba58c63f98654d01dbdc5e7a80b"
  },
  {
    "id_ours": "27b909694b4866bcf9210545aeb175695fb5c20a",
    "id_search_engine": "8667950512",
    "url": "https://farm9.staticflickr.com/8530/8667950512_c43b68d2d3_o.jpg",
    "url_type": "url_o",
    "wnid": "n03954731",
    "search_key": "woodworking plane",
    "search_engine": "flickr",
    "uploader": "becca",
    "date_upload_our_db": "2018-11-30 08:00:33",
    "date_taken": "2013-04-20 19:39:52",
    "date_upload_search_engine": "2013-04-21 00:35:22",
    "width": 2196,
    "height": 3414,
    "max_taken_date": "2014-07-11",
    "max_uploaded_date": "2014-07-11",
    "min_taken_date": "2012-07-11",
    "min_uploaded_date": "2012-07-11",
    "search_sort": "date-posted-asc",
    "max_images": 200,
    "batch": "d97079811b7eeaffca23043afbdea0056967cba58c63f98654d01dbdc5e7a80b"
  },
  {
    "id_ours": "5fad323596f6390aea3bc76a8db78fcb4b0af3e6",
    "id_search_engine": "8666849103",
    "url": "https://farm9.staticflickr.com/8532/8666849103_1f7bd3c42c_o.jpg",
    "url_type": "url_o",
    "wnid": "n03954731",
    "search_key": "woodworking plane",
    "search_engine": "flickr",
    "uploader": "becca",
    "date_upload_our_db": "2018-11-30 08:00:33",
    "date_taken": "2013-04-20 19:34:45",
    "date_upload_search_engine": "2013-04-21 00:35:21",
    "width": 3456,
    "height": 2304,
    "max_taken_date": "2014-07-11",
    "max_uploaded_date": "2014-07-11",
    "min_taken_date": "2012-07-11",
    "min_uploaded_date": "2012-07-11",
    "search_sort": "date-posted-asc",
    "max_images": 200,
    "batch": "d97079811b7eeaffca23043afbdea0056967cba58c63f98654d01dbdc5e7a80b"
  },
  {
    "id_ours": "84ed32b54cfc644e507052fbdf7452e1abe1048f",
    "id_search_engine": "8667951714",
    "url": "https://farm9.staticflickr.com/8545/8667951714_d95bb38ab9_o.jpg",
    "url_type": "url_o",
    "wnid": "n03954731",
    "search_key": "woodworking plane",
    "search_engine": "flickr",
    "uploader": "becca",
    "date_upload_our_db": "2018-11-30 08:00:33",
    "date_taken": "2013-04-20 19:30:26",
    "date_upload_search_engine": "2013-04-21 00:35:19",
    "width": 3456,
    "height": 2304,
    "max_taken_date": "2014-07-11",
    "max_uploaded_date": "2014-07-11",
    "min_taken_date": "2012-07-11",
    "min_uploaded_date": "2012-07-11",
    "search_sort": "date-posted-asc",
    "max_images": 200,
    "batch": "d97079811b7eeaffca23043afbdea0056967cba58c63f98654d01dbdc5e7a80b"
  },
  {
    "id_ours": "74875995e0ec2e110fdc4c9fbdb03e411dbd4799",
    "id_search_engine": "8673643909",
    "url": "https://farm9.staticflickr.com/8116/8673643909_9cc31fc404_o.jpg",
    "url_type": "url_o",
    "wnid": "n03954731",
    "search_key": "woodworking plane",
    "search_engine": "flickr",
    "uploader": "becca",
    "date_upload_our_db": "2018-11-30 08:00:33",
    "date_taken": "2013-04-20 17:22:31",
    "date_upload_search_engine": "2013-04-22 23:08:03",
    "width": 3444,
    "height": 2052,
    "max_taken_date": "2014-07-11",
    "max_uploaded_date": "2014-07-11",
    "min_taken_date": "2012-07-11",
    "min_uploaded_date": "2012-07-11",
    "search_sort": "date-posted-asc",
    "max_images": 200,
    "batch": "d97079811b7eeaffca23043afbdea0056967cba58c63f98654d01dbdc5e7a80b"
  },
  {
    "id_ours": "5fd74ae445e4ea6836147874bf9975600f0c301e",
    "id_search_engine": "8674746780",
    "url": "https://farm9.staticflickr.com/8258/8674746780_9669ee03ec_o.jpg",
    "url_type": "url_o",
    "wnid": "n03954731",
    "search_key": "woodworking plane",
    "search_engine": "flickr",
    "uploader": "becca",
    "date_upload_our_db": "2018-11-30 08:00:33",
    "date_taken": "2013-04-20 18:15:27",
    "date_upload_search_engine": "2013-04-22 23:08:09",
    "width": 2160,
    "height": 3450,
    "max_taken_date": "2014-07-11",
    "max_uploaded_date": "2014-07-11",
    "min_taken_date": "2012-07-11",
    "min_uploaded_date": "2012-07-11",
    "search_sort": "date-posted-asc",
    "max_images": 200,
    "batch": "d97079811b7eeaffca23043afbdea0056967cba58c63f98654d01dbdc5e7a80b"
  },
  {
    "id_ours": "5199d00f91ba281f6948d19e5c43ce46029b3d9c",
    "id_search_engine": "8674747432",
    "url": "https://farm9.staticflickr.com/8253/8674747432_d512a87188_o.jpg",
    "url_type": "url_o",
    "wnid": "n03954731",
    "search_key": "woodworking plane",
    "search_engine": "flickr",
    "uploader": "becca",
    "date_upload_our_db": "2018-11-30 08:00:33",
    "date_taken": "2013-04-20 17:25:57",
    "date_upload_search_engine": "2013-04-22 23:08:05",
    "width": 3456,
    "height": 2304,
    "max_taken_date": "2014-07-11",
    "max_uploaded_date": "2014-07-11",
    "min_taken_date": "2012-07-11",
    "min_uploaded_date": "2012-07-11",
    "search_sort": "date-posted-asc",
    "max_images": 200,
    "batch": "d97079811b7eeaffca23043afbdea0056967cba58c63f98654d01dbdc5e7a80b"
  },
  {
    "id_ours": "fd97ddd44d9b6ffd40baab3b6bf39f3ea987fcc7",
    "id_search_engine": "8673683169",
    "url": "https://farm9.staticflickr.com/8266/8673683169_2103d73d19_o.jpg",
    "url_type": "url_o",
    "wnid": "n03954731",
    "search_key": "woodworking plane",
    "search_engine": "flickr",
    "uploader": "becca",
    "date_upload_our_db": "2018-11-30 08:00:33",
    "date_taken": "2013-04-20 19:26:16",
    "date_upload_search_engine": "2013-04-22 23:32:53",
    "width": 2880,
    "height": 2276,
    "max_taken_date": "2014-07-11",
    "max_uploaded_date": "2014-07-11",
    "min_taken_date": "2012-07-11",
    "min_uploaded_date": "2012-07-11",
    "search_sort": "date-posted-asc",
    "max_images": 200,
    "batch": "d97079811b7eeaffca23043afbdea0056967cba58c63f98654d01dbdc5e7a80b"
  },
  {
    "id_ours": "240a062f628a27014a51e837e9cf0522f0a120c6",
    "id_search_engine": "8674787638",
    "url": "https://farm9.staticflickr.com/8533/8674787638_e1f2b85011_o.jpg",
    "url_type": "url_o",
    "wnid": "n03954731",
    "search_key": "woodworking plane",
    "search_engine": "flickr",
    "uploader": "becca",
    "date_upload_our_db": "2018-11-30 08:00:33",
    "date_taken": "2013-04-20 19:24:00",
    "date_upload_search_engine": "2013-04-22 23:32:52",
    "width": 2304,
    "height": 3456,
    "max_taken_date": "2014-07-11",
    "max_uploaded_date": "2014-07-11",
    "min_taken_date": "2012-07-11",
    "min_uploaded_date": "2012-07-11",
    "search_sort": "date-posted-asc",
    "max_images": 200,
    "batch": "d97079811b7eeaffca23043afbdea0056967cba58c63f98654d01dbdc5e7a80b"
  },
  {
    "id_ours": "587247745c8a3ba269843ca4c6127272fe39f425",
    "id_search_engine": "9153800321",
    "url": "https://farm8.staticflickr.com/7281/9153800321_b4174f74c3_k.jpg",
    "url_type": "url_k",
    "wnid": "n03954731",
    "search_key": "woodworking plane",
    "search_engine": "flickr",
    "uploader": "becca",
    "date_upload_our_db": "2018-11-30 08:00:33",
    "date_taken": "2013-06-27 10:36:34",
    "date_upload_search_engine": "2013-06-27 17:09:27",
    "width": null,
    "height": null,
    "max_taken_date": "2014-07-11",
    "max_uploaded_date": "2014-07-11",
    "min_taken_date": "2012-07-11",
    "min_uploaded_date": "2012-07-11",
    "search_sort": "date-posted-asc",
    "max_images": 200,
    "batch": "d97079811b7eeaffca23043afbdea0056967cba58c63f98654d01dbdc5e7a80b"
  },
  {
    "id_ours": "6355eb2f8c8aa788f4eb52d17bb03e83cc4e1f9f",
    "id_search_engine": "9293723436",
    "url": "https://farm3.staticflickr.com/2806/9293723436_06e9dd4e64_o.jpg",
    "url_type": "url_o",
    "wnid": "n03954731",
    "search_key": "woodworking plane",
    "search_engine": "flickr",
    "uploader": "becca",
    "date_upload_our_db": "2018-11-30 08:00:33",
    "date_taken": "2013-07-15 15:23:11",
    "date_upload_search_engine": "2013-07-15 07:25:06",
    "width": null,
    "height": null,
    "max_taken_date": "2014-07-11",
    "max_uploaded_date": "2014-07-11",
    "min_taken_date": "2012-07-11",
    "min_uploaded_date": "2012-07-11",
    "search_sort": "date-posted-asc",
    "max_images": 200,
    "batch": "d97079811b7eeaffca23043afbdea0056967cba58c63f98654d01dbdc5e7a80b"
  },
  {
    "id_ours": "ae5b58bf2505ecefe22882097b40fc2529198841",
    "id_search_engine": "9293723716",
    "url": "https://farm3.staticflickr.com/2839/9293723716_3ed5160483_o.jpg",
    "url_type": "url_o",
    "wnid": "n03954731",
    "search_key": "woodworking plane",
    "search_engine": "flickr",
    "uploader": "becca",
    "date_upload_our_db": "2018-11-30 08:00:33",
    "date_taken": "2013-07-15 15:23:13",
    "date_upload_search_engine": "2013-07-15 07:25:04",
    "width": null,
    "height": null,
    "max_taken_date": "2014-07-11",
    "max_uploaded_date": "2014-07-11",
    "min_taken_date": "2012-07-11",
    "min_uploaded_date": "2012-07-11",
    "search_sort": "date-posted-asc",
    "max_images": 200,
    "batch": "d97079811b7eeaffca23043afbdea0056967cba58c63f98654d01dbdc5e7a80b"
  },
  {
    "id_ours": "9cf5064e0e4cacff77ef20e6bad33ea2658f1b25",
    "id_search_engine": "9383552165",
    "url": "https://farm8.staticflickr.com/7421/9383552165_2df98adea6_k.jpg",
    "url_type": "url_k",
    "wnid": "n03954731",
    "search_key": "woodworking plane",
    "search_engine": "flickr",
    "uploader": "becca",
    "date_upload_our_db": "2018-11-30 08:00:33",
    "date_taken": "2013-07-28 15:06:50",
    "date_upload_search_engine": "2013-07-28 09:34:01",
    "width": 2048,
    "height": 1306,
    "max_taken_date": "2014-07-11",
    "max_uploaded_date": "2014-07-11",
    "min_taken_date": "2012-07-11",
    "min_uploaded_date": "2012-07-11",
    "search_sort": "date-posted-asc",
    "max_images": 200,
    "batch": "d97079811b7eeaffca23043afbdea0056967cba58c63f98654d01dbdc5e7a80b"
  },
  {
    "id_ours": "185341588c8ee4aa34d6ec3930c7347687911dbe",
    "id_search_engine": "9391927458",
    "url": "https://farm3.staticflickr.com/2836/9391927458_6512c756fc_o.jpg",
    "url_type": "url_o",
    "wnid": "n03954731",
    "search_key": "woodworking plane",
    "search_engine": "flickr",
    "uploader": "becca",
    "date_upload_our_db": "2018-11-30 08:00:33",
    "date_taken": "2013-07-05 15:35:36",
    "date_upload_search_engine": "2013-07-29 00:32:55",
    "width": 4032,
    "height": 3024,
    "max_taken_date": "2014-07-11",
    "max_uploaded_date": "2014-07-11",
    "min_taken_date": "2012-07-11",
    "min_uploaded_date": "2012-07-11",
    "search_sort": "date-posted-asc",
    "max_images": 200,
    "batch": "d97079811b7eeaffca23043afbdea0056967cba58c63f98654d01dbdc5e7a80b"
  },
  {
    "id_ours": "6ae03966e5b8d207acb383b09c79525f06e78dde",
    "id_search_engine": "9481724522",
    "url": "https://farm8.staticflickr.com/7411/9481724522_7b856f0258_o.jpg",
    "url_type": "url_o",
    "wnid": "n03954731",
    "search_key": "woodworking plane",
    "search_engine": "flickr",
    "uploader": "becca",
    "date_upload_our_db": "2018-11-30 08:00:33",
    "date_taken": "2013-08-10 12:18:58",
    "date_upload_search_engine": "2013-08-10 12:23:42",
    "width": 1395,
    "height": 1971,
    "max_taken_date": "2014-07-11",
    "max_uploaded_date": "2014-07-11",
    "min_taken_date": "2012-07-11",
    "min_uploaded_date": "2012-07-11",
    "search_sort": "date-posted-asc",
    "max_images": 200,
    "batch": "d97079811b7eeaffca23043afbdea0056967cba58c63f98654d01dbdc5e7a80b"
  },
  {
    "id_ours": "dc188932b24588ce304c99d85343754927ae8459",
    "id_search_engine": "9511862613",
    "url": "https://farm4.staticflickr.com/3810/9511862613_c38bb65c2c_o.jpg",
    "url_type": "url_o",
    "wnid": "n03954731",
    "search_key": "woodworking plane",
    "search_engine": "flickr",
    "uploader": "becca",
    "date_upload_our_db": "2018-11-30 08:00:33",
    "date_taken": "2013-08-14 20:31:50",
    "date_upload_search_engine": "2013-08-14 19:39:39",
    "width": 3264,
    "height": 1840,
    "max_taken_date": "2014-07-11",
    "max_uploaded_date": "2014-07-11",
    "min_taken_date": "2012-07-11",
    "min_uploaded_date": "2012-07-11",
    "search_sort": "date-posted-asc",
    "max_images": 200,
    "batch": "d97079811b7eeaffca23043afbdea0056967cba58c63f98654d01dbdc5e7a80b"
  },
  {
    "id_ours": "523c923bb8bea172ab9b99d669ef4099c7b6e2c8",
    "id_search_engine": "9533384420",
    "url": "https://farm8.staticflickr.com/7434/9533384420_0584387923_k.jpg",
    "url_type": "url_k",
    "wnid": "n03954731",
    "search_key": "woodworking plane",
    "search_engine": "flickr",
    "uploader": "becca",
    "date_upload_our_db": "2018-11-30 08:00:33",
    "date_taken": "2013-08-17 14:17:58",
    "date_upload_search_engine": "2013-08-17 12:51:44",
    "width": null,
    "height": null,
    "max_taken_date": "2014-07-11",
    "max_uploaded_date": "2014-07-11",
    "min_taken_date": "2012-07-11",
    "min_uploaded_date": "2012-07-11",
    "search_sort": "date-posted-asc",
    "max_images": 200,
    "batch": "d97079811b7eeaffca23043afbdea0056967cba58c63f98654d01dbdc5e7a80b"
  },
  {
    "id_ours": "61e613b8d741306d9086c5cc8fc14786cca777fb",
    "id_search_engine": "9533381854",
    "url": "https://farm3.staticflickr.com/2855/9533381854_426c8387da_k.jpg",
    "url_type": "url_k",
    "wnid": "n03954731",
    "search_key": "woodworking plane",
    "search_engine": "flickr",
    "uploader": "becca",
    "date_upload_our_db": "2018-11-30 08:00:33",
    "date_taken": "2013-08-17 14:18:47",
    "date_upload_search_engine": "2013-08-17 12:51:45",
    "width": null,
    "height": null,
    "max_taken_date": "2014-07-11",
    "max_uploaded_date": "2014-07-11",
    "min_taken_date": "2012-07-11",
    "min_uploaded_date": "2012-07-11",
    "search_sort": "date-posted-asc",
    "max_images": 200,
    "batch": "d97079811b7eeaffca23043afbdea0056967cba58c63f98654d01dbdc5e7a80b"
  },
  {
    "id_ours": "458da8c63144c523e4e2b3e996367a00597c4841",
    "id_search_engine": "9530616041",
    "url": "https://farm6.staticflickr.com/5449/9530616041_90c87b173a_k.jpg",
    "url_type": "url_k",
    "wnid": "n03954731",
    "search_key": "woodworking plane",
    "search_engine": "flickr",
    "uploader": "becca",
    "date_upload_our_db": "2018-11-30 08:00:33",
    "date_taken": "2013-08-17 14:19:58",
    "date_upload_search_engine": "2013-08-17 12:51:46",
    "width": null,
    "height": null,
    "max_taken_date": "2014-07-11",
    "max_uploaded_date": "2014-07-11",
    "min_taken_date": "2012-07-11",
    "min_uploaded_date": "2012-07-11",
    "search_sort": "date-posted-asc",
    "max_images": 200,
    "batch": "d97079811b7eeaffca23043afbdea0056967cba58c63f98654d01dbdc5e7a80b"
  },
  {
    "id_ours": "26d108b83485c5e7f067c5f809af80589d5a336b",
    "id_search_engine": "9615326525",
    "url": "https://farm8.staticflickr.com/7369/9615326525_67aa8a0ede_k.jpg",
    "url_type": "url_k",
    "wnid": "n03954731",
    "search_key": "woodworking plane",
    "search_engine": "flickr",
    "uploader": "becca",
    "date_upload_our_db": "2018-11-30 08:00:33",
    "date_taken": "2013-08-27 14:44:26",
    "date_upload_search_engine": "2013-08-28 14:11:28",
    "width": null,
    "height": null,
    "max_taken_date": "2014-07-11",
    "max_uploaded_date": "2014-07-11",
    "min_taken_date": "2012-07-11",
    "min_uploaded_date": "2012-07-11",
    "search_sort": "date-posted-asc",
    "max_images": 200,
    "batch": "d97079811b7eeaffca23043afbdea0056967cba58c63f98654d01dbdc5e7a80b"
  },
  {
    "id_ours": "811aa53177e733fca35ada95adbbb7c78d70ec9c",
    "id_search_engine": "9615328375",
    "url": "https://farm8.staticflickr.com/7282/9615328375_ec34e8e8c1_k.jpg",
    "url_type": "url_k",
    "wnid": "n03954731",
    "search_key": "woodworking plane",
    "search_engine": "flickr",
    "uploader": "becca",
    "date_upload_our_db": "2018-11-30 08:00:33",
    "date_taken": "2013-08-27 14:37:55",
    "date_upload_search_engine": "2013-08-28 14:11:27",
    "width": null,
    "height": null,
    "max_taken_date": "2014-07-11",
    "max_uploaded_date": "2014-07-11",
    "min_taken_date": "2012-07-11",
    "min_uploaded_date": "2012-07-11",
    "search_sort": "date-posted-asc",
    "max_images": 200,
    "batch": "d97079811b7eeaffca23043afbdea0056967cba58c63f98654d01dbdc5e7a80b"
  },
  {
    "id_ours": "cc44ff13b1cd1f821dfd4dc2637719e2c6515b4b",
    "id_search_engine": "9615329797",
    "url": "https://farm4.staticflickr.com/3808/9615329797_88b28a3f45_k.jpg",
    "url_type": "url_k",
    "wnid": "n03954731",
    "search_key": "woodworking plane",
    "search_engine": "flickr",
    "uploader": "becca",
    "date_upload_our_db": "2018-11-30 08:00:33",
    "date_taken": "2013-08-26 15:56:30",
    "date_upload_search_engine": "2013-08-28 14:11:26",
    "width": null,
    "height": null,
    "max_taken_date": "2014-07-11",
    "max_uploaded_date": "2014-07-11",
    "min_taken_date": "2012-07-11",
    "min_uploaded_date": "2012-07-11",
    "search_sort": "date-posted-asc",
    "max_images": 200,
    "batch": "d97079811b7eeaffca23043afbdea0056967cba58c63f98654d01dbdc5e7a80b"
  },
  {
    "id_ours": "cab063052aaafe8e6fdee399e4349d4b26a54ec2",
    "id_search_engine": "9967920166",
    "url": "https://farm4.staticflickr.com/3708/9967920166_042f34bda2_o.jpg",
    "url_type": "url_o",
    "wnid": "n03954731",
    "search_key": "woodworking plane",
    "search_engine": "flickr",
    "uploader": "becca",
    "date_upload_our_db": "2018-11-30 08:00:33",
    "date_taken": "2013-09-23 14:17:44",
    "date_upload_search_engine": "2013-09-27 09:04:20",
    "width": 4896,
    "height": 2760,
    "max_taken_date": "2014-07-11",
    "max_uploaded_date": "2014-07-11",
    "min_taken_date": "2012-07-11",
    "min_uploaded_date": "2012-07-11",
    "search_sort": "date-posted-asc",
    "max_images": 200,
    "batch": "d97079811b7eeaffca23043afbdea0056967cba58c63f98654d01dbdc5e7a80b"
  },
  {
    "id_ours": "cd8c184a97c2f93aa891a41329ce16f32e6a0f8d",
    "id_search_engine": "10222894246",
    "url": "https://farm4.staticflickr.com/3678/10222894246_f61735eda5_o.jpg",
    "url_type": "url_o",
    "wnid": "n03954731",
    "search_key": "woodworking plane",
    "search_engine": "flickr",
    "uploader": "becca",
    "date_upload_our_db": "2018-11-30 08:00:33",
    "date_taken": "2013-04-13 15:21:41",
    "date_upload_search_engine": "2013-10-12 03:19:55",
    "width": 4288,
    "height": 2848,
    "max_taken_date": "2014-07-11",
    "max_uploaded_date": "2014-07-11",
    "min_taken_date": "2012-07-11",
    "min_uploaded_date": "2012-07-11",
    "search_sort": "date-posted-asc",
    "max_images": 200,
    "batch": "d97079811b7eeaffca23043afbdea0056967cba58c63f98654d01dbdc5e7a80b"
  },
  {
    "id_ours": "b7c28dc07d0770daf012a3f9c4fd5f62c612bb11",
    "id_search_engine": "10316786803",
    "url": "https://farm6.staticflickr.com/5486/10316786803_f6024908d8_h.jpg",
    "url_type": "url_h",
    "wnid": "n03954731",
    "search_key": "woodworking plane",
    "search_engine": "flickr",
    "uploader": "becca",
    "date_upload_our_db": "2018-11-30 08:00:33",
    "date_taken": "2013-10-16 19:16:34",
    "date_upload_search_engine": "2013-10-16 13:40:01",
    "width": 1362,
    "height": 1600,
    "max_taken_date": "2014-07-11",
    "max_uploaded_date": "2014-07-11",
    "min_taken_date": "2012-07-11",
    "min_uploaded_date": "2012-07-11",
    "search_sort": "date-posted-asc",
    "max_images": 200,
    "batch": "d97079811b7eeaffca23043afbdea0056967cba58c63f98654d01dbdc5e7a80b"
  },
  {
    "id_ours": "750ec7a1a3023a7e6f81a5fe20b0f26914785d8b",
    "id_search_engine": "10316789033",
    "url": "https://farm6.staticflickr.com/5472/10316789033_25e968d8c4_k.jpg",
    "url_type": "url_k",
    "wnid": "n03954731",
    "search_key": "woodworking plane",
    "search_engine": "flickr",
    "uploader": "becca",
    "date_upload_our_db": "2018-11-30 08:00:33",
    "date_taken": "2013-10-16 17:50:49",
    "date_upload_search_engine": "2013-10-16 13:40:00",
    "width": 1536,
    "height": 2048,
    "max_taken_date": "2014-07-11",
    "max_uploaded_date": "2014-07-11",
    "min_taken_date": "2012-07-11",
    "min_uploaded_date": "2012-07-11",
    "search_sort": "date-posted-asc",
    "max_images": 200,
    "batch": "d97079811b7eeaffca23043afbdea0056967cba58c63f98654d01dbdc5e7a80b"
  },
  {
    "id_ours": "93264b2f5ae42a1dd79f277f5e645549e4bf5d04",
    "id_search_engine": "10329937224",
    "url": "https://farm6.staticflickr.com/5472/10329937224_a0972b28f1_k.jpg",
    "url_type": "url_k",
    "wnid": "n03954731",
    "search_key": "woodworking plane",
    "search_engine": "flickr",
    "uploader": "becca",
    "date_upload_our_db": "2018-11-30 08:00:33",
    "date_taken": "2013-10-17 16:14:40",
    "date_upload_search_engine": "2013-10-17 08:44:10",
    "width": 2048,
    "height": 1053,
    "max_taken_date": "2014-07-11",
    "max_uploaded_date": "2014-07-11",
    "min_taken_date": "2012-07-11",
    "min_uploaded_date": "2012-07-11",
    "search_sort": "date-posted-asc",
    "max_images": 200,
    "batch": "d97079811b7eeaffca23043afbdea0056967cba58c63f98654d01dbdc5e7a80b"
  },
  {
    "id_ours": "b231ef50f82203f69f0beb07a516af8fd36b8777",
    "id_search_engine": "10347699094",
    "url": "https://farm4.staticflickr.com/3778/10347699094_2b9e072c77_k.jpg",
    "url_type": "url_k",
    "wnid": "n03954731",
    "search_key": "woodworking plane",
    "search_engine": "flickr",
    "uploader": "becca",
    "date_upload_our_db": "2018-11-30 08:00:33",
    "date_taken": "2013-10-18 17:29:38",
    "date_upload_search_engine": "2013-10-18 09:37:36",
    "width": null,
    "height": null,
    "max_taken_date": "2014-07-11",
    "max_uploaded_date": "2014-07-11",
    "min_taken_date": "2012-07-11",
    "min_uploaded_date": "2012-07-11",
    "search_sort": "date-posted-asc",
    "max_images": 200,
    "batch": "d97079811b7eeaffca23043afbdea0056967cba58c63f98654d01dbdc5e7a80b"
  },
  {
    "id_ours": "9340292ef11296a0bf52c52d6033b2ed83294a58",
    "id_search_engine": "10362171826",
    "url": "https://farm4.staticflickr.com/3738/10362171826_221b3afc84_o.jpg",
    "url_type": "url_o",
    "wnid": "n03954731",
    "search_key": "woodworking plane",
    "search_engine": "flickr",
    "uploader": "becca",
    "date_upload_our_db": "2018-11-30 08:00:33",
    "date_taken": "2013-10-19 07:21:31",
    "date_upload_search_engine": "2013-10-19 07:21:31",
    "width": 640,
    "height": 640,
    "max_taken_date": "2014-07-11",
    "max_uploaded_date": "2014-07-11",
    "min_taken_date": "2012-07-11",
    "min_uploaded_date": "2012-07-11",
    "search_sort": "date-posted-asc",
    "max_images": 200,
    "batch": "d97079811b7eeaffca23043afbdea0056967cba58c63f98654d01dbdc5e7a80b"
  },
  {
    "id_ours": "77569814bb95d71dc6300918a912ee022aede69b",
    "id_search_engine": "10405974276",
    "url": "https://farm4.staticflickr.com/3707/10405974276_786fdb372c_k.jpg",
    "url_type": "url_k",
    "wnid": "n03954731",
    "search_key": "woodworking plane",
    "search_engine": "flickr",
    "uploader": "becca",
    "date_upload_our_db": "2018-11-30 08:00:33",
    "date_taken": "2013-10-21 15:52:22",
    "date_upload_search_engine": "2013-10-21 09:48:41",
    "width": 1364,
    "height": 2048,
    "max_taken_date": "2014-07-11",
    "max_uploaded_date": "2014-07-11",
    "min_taken_date": "2012-07-11",
    "min_uploaded_date": "2012-07-11",
    "search_sort": "date-posted-asc",
    "max_images": 200,
    "batch": "d97079811b7eeaffca23043afbdea0056967cba58c63f98654d01dbdc5e7a80b"
  },
  {
    "id_ours": "e57b935f52e4351249a8b52d9b39f7d0d03c575f",
    "id_search_engine": "10465937054",
    "url": "https://farm8.staticflickr.com/7360/10465937054_8930a20572_k.jpg",
    "url_type": "url_k",
    "wnid": "n03954731",
    "search_key": "woodworking plane",
    "search_engine": "flickr",
    "uploader": "becca",
    "date_upload_our_db": "2018-11-30 08:00:33",
    "date_taken": "2013-10-24 23:31:31",
    "date_upload_search_engine": "2013-10-24 15:57:08",
    "width": 1637,
    "height": 2048,
    "max_taken_date": "2014-07-11",
    "max_uploaded_date": "2014-07-11",
    "min_taken_date": "2012-07-11",
    "min_uploaded_date": "2012-07-11",
    "search_sort": "date-posted-asc",
    "max_images": 200,
    "batch": "d97079811b7eeaffca23043afbdea0056967cba58c63f98654d01dbdc5e7a80b"
  },
  {
    "id_ours": "f85e45aefa9d538b32ad59e4cbd8cf72c771c304",
    "id_search_engine": "10573166773",
    "url": "https://farm4.staticflickr.com/3821/10573166773_74863a22ed_c.jpg",
    "url_type": "url_c",
    "wnid": "n03954731",
    "search_key": "woodworking plane",
    "search_engine": "flickr",
    "uploader": "becca",
    "date_upload_our_db": "2018-11-30 08:00:33",
    "date_taken": "2013-10-27 10:11:15",
    "date_upload_search_engine": "2013-10-30 05:21:59",
    "width": null,
    "height": null,
    "max_taken_date": "2014-07-11",
    "max_uploaded_date": "2014-07-11",
    "min_taken_date": "2012-07-11",
    "min_uploaded_date": "2012-07-11",
    "search_sort": "date-posted-asc",
    "max_images": 200,
    "batch": "d97079811b7eeaffca23043afbdea0056967cba58c63f98654d01dbdc5e7a80b"
  },
  {
    "id_ours": "5424474959145cfaa179b6d5e05911dd509b2fab",
    "id_search_engine": "10581232224",
    "url": "https://farm8.staticflickr.com/7337/10581232224_d7f32c5a61_o.jpg",
    "url_type": "url_o",
    "wnid": "n03954731",
    "search_key": "woodworking plane",
    "search_engine": "flickr",
    "uploader": "becca",
    "date_upload_our_db": "2018-11-30 08:00:33",
    "date_taken": "2013-10-30 22:52:06",
    "date_upload_search_engine": "2013-10-30 14:41:59",
    "width": "2048",
    "height": "1536",
    "max_taken_date": "2014-07-11",
    "max_uploaded_date": "2014-07-11",
    "min_taken_date": "2012-07-11",
    "min_uploaded_date": "2012-07-11",
    "search_sort": "date-posted-asc",
    "max_images": 200,
    "batch": "d97079811b7eeaffca23043afbdea0056967cba58c63f98654d01dbdc5e7a80b"
  },
  {
    "id_ours": "cbabbe159172e3303ac7f06e6f90bf830fea1b8f",
    "id_search_engine": "10581461113",
    "url": "https://farm4.staticflickr.com/3767/10581461113_dbc39258a8_o.jpg",
    "url_type": "url_o",
    "wnid": "n03954731",
    "search_key": "woodworking plane",
    "search_engine": "flickr",
    "uploader": "becca",
    "date_upload_our_db": "2018-11-30 08:00:33",
    "date_taken": "2013-10-30 18:50:22",
    "date_upload_search_engine": "2013-10-30 14:41:54",
    "width": "2048",
    "height": "1536",
    "max_taken_date": "2014-07-11",
    "max_uploaded_date": "2014-07-11",
    "min_taken_date": "2012-07-11",
    "min_uploaded_date": "2012-07-11",
    "search_sort": "date-posted-asc",
    "max_images": 200,
    "batch": "d97079811b7eeaffca23043afbdea0056967cba58c63f98654d01dbdc5e7a80b"
  },
  {
    "id_ours": "33b7f6521e33fafd3ca67d2e4907adf48adaf410",
    "id_search_engine": "10581207156",
    "url": "https://farm6.staticflickr.com/5472/10581207156_05d5f06688_o.jpg",
    "url_type": "url_o",
    "wnid": "n03954731",
    "search_key": "woodworking plane",
    "search_engine": "flickr",
    "uploader": "becca",
    "date_upload_our_db": "2018-11-30 08:00:33",
    "date_taken": "2013-10-30 22:53:25",
    "date_upload_search_engine": "2013-10-30 14:42:04",
    "width": "2048",
    "height": "1536",
    "max_taken_date": "2014-07-11",
    "max_uploaded_date": "2014-07-11",
    "min_taken_date": "2012-07-11",
    "min_uploaded_date": "2012-07-11",
    "search_sort": "date-posted-asc",
    "max_images": 200,
    "batch": "d97079811b7eeaffca23043afbdea0056967cba58c63f98654d01dbdc5e7a80b"
  },
  {
    "id_ours": "d95520005e2c601261ed21a32fdbedf51bc23d89",
    "id_search_engine": "10581225714",
    "url": "https://farm4.staticflickr.com/3739/10581225714_7110062ef4_o.jpg",
    "url_type": "url_o",
    "wnid": "n03954731",
    "search_key": "woodworking plane",
    "search_engine": "flickr",
    "uploader": "becca",
    "date_upload_our_db": "2018-11-30 08:00:33",
    "date_taken": "2013-10-30 22:53:11",
    "date_upload_search_engine": "2013-10-30 14:42:03",
    "width": "2048",
    "height": "1536",
    "max_taken_date": "2014-07-11",
    "max_uploaded_date": "2014-07-11",
    "min_taken_date": "2012-07-11",
    "min_uploaded_date": "2012-07-11",
    "search_sort": "date-posted-asc",
    "max_images": 200,
    "batch": "d97079811b7eeaffca23043afbdea0056967cba58c63f98654d01dbdc5e7a80b"
  },
  {
    "id_ours": "587dbc751cd34056b92abfe21fc4007be673d66b",
    "id_search_engine": "10581179885",
    "url": "https://farm6.staticflickr.com/5524/10581179885_fce0745507_o.jpg",
    "url_type": "url_o",
    "wnid": "n03954731",
    "search_key": "woodworking plane",
    "search_engine": "flickr",
    "uploader": "becca",
    "date_upload_our_db": "2018-11-30 08:00:33",
    "date_taken": "2013-10-30 22:50:39",
    "date_upload_search_engine": "2013-10-30 14:41:57",
    "width": 2048,
    "height": 1536,
    "max_taken_date": "2014-07-11",
    "max_uploaded_date": "2014-07-11",
    "min_taken_date": "2012-07-11",
    "min_uploaded_date": "2012-07-11",
    "search_sort": "date-posted-asc",
    "max_images": 200,
    "batch": "d97079811b7eeaffca23043afbdea0056967cba58c63f98654d01dbdc5e7a80b"
  },
  {
    "id_ours": "80d79b1c0ae6e109df6f8efc0ef3dcce128e056b",
    "id_search_engine": "10581221794",
    "url": "https://farm3.staticflickr.com/2812/10581221794_2ab5b089e3_o.jpg",
    "url_type": "url_o",
    "wnid": "n03954731",
    "search_key": "woodworking plane",
    "search_engine": "flickr",
    "uploader": "becca",
    "date_upload_our_db": "2018-11-30 08:00:33",
    "date_taken": "2013-10-30 22:54:37",
    "date_upload_search_engine": "2013-10-30 14:42:05",
    "width": "2048",
    "height": "1536",
    "max_taken_date": "2014-07-11",
    "max_uploaded_date": "2014-07-11",
    "min_taken_date": "2012-07-11",
    "min_uploaded_date": "2012-07-11",
    "search_sort": "date-posted-asc",
    "max_images": 200,
    "batch": "d97079811b7eeaffca23043afbdea0056967cba58c63f98654d01dbdc5e7a80b"
  },
  {
    "id_ours": "e4b62eb810e2da9e76d8f7eb92bf65367fdc339e",
    "id_search_engine": "10581376784",
    "url": "https://farm3.staticflickr.com/2836/10581376784_1fbe030be4_o.jpg",
    "url_type": "url_o",
    "wnid": "n03954731",
    "search_key": "woodworking plane",
    "search_engine": "flickr",
    "uploader": "becca",
    "date_upload_our_db": "2018-11-30 08:00:33",
    "date_taken": "2013-10-30 23:44:42",
    "date_upload_search_engine": "2013-10-30 14:50:55",
    "width": 2048,
    "height": 1536,
    "max_taken_date": "2014-07-11",
    "max_uploaded_date": "2014-07-11",
    "min_taken_date": "2012-07-11",
    "min_uploaded_date": "2012-07-11",
    "search_sort": "date-posted-asc",
    "max_images": 200,
    "batch": "d97079811b7eeaffca23043afbdea0056967cba58c63f98654d01dbdc5e7a80b"
  },
  {
    "id_ours": "a241442c27c9bb4e1ff9f258eafc1d8b8857fc1b",
    "id_search_engine": "10807212114",
    "url": "https://farm4.staticflickr.com/3708/10807212114_61fc0e77f4_o.jpg",
    "url_type": "url_o",
    "wnid": "n03954731",
    "search_key": "woodworking plane",
    "search_engine": "flickr",
    "uploader": "becca",
    "date_upload_our_db": "2018-11-30 08:00:33",
    "date_taken": "2013-09-21 17:16:54",
    "date_upload_search_engine": "2013-11-11 13:37:31",
    "width": "4896",
    "height": "3264",
    "max_taken_date": "2014-07-11",
    "max_uploaded_date": "2014-07-11",
    "min_taken_date": "2012-07-11",
    "min_uploaded_date": "2012-07-11",
    "search_sort": "date-posted-asc",
    "max_images": 200,
    "batch": "d97079811b7eeaffca23043afbdea0056967cba58c63f98654d01dbdc5e7a80b"
  },
  {
    "id_ours": "c966456b1c5a4516d3a9bc9614c6cba36bdf9d79",
    "id_search_engine": "10852226444",
    "url": "https://farm4.staticflickr.com/3736/10852226444_11cf19ec61_k.jpg",
    "url_type": "url_k",
    "wnid": "n03954731",
    "search_key": "woodworking plane",
    "search_engine": "flickr",
    "uploader": "becca",
    "date_upload_our_db": "2018-11-30 08:00:33",
    "date_taken": "2013-11-16 20:46:26",
    "date_upload_search_engine": "2013-11-14 03:07:18",
    "width": 1364,
    "height": 2048,
    "max_taken_date": "2014-07-11",
    "max_uploaded_date": "2014-07-11",
    "min_taken_date": "2012-07-11",
    "min_uploaded_date": "2012-07-11",
    "search_sort": "date-posted-asc",
    "max_images": 200,
    "batch": "d97079811b7eeaffca23043afbdea0056967cba58c63f98654d01dbdc5e7a80b"
  },
  {
    "id_ours": "c6538d13331d85c226b889e155291eabdf3490ba",
    "id_search_engine": "10921784565",
    "url": "https://farm6.staticflickr.com/5538/10921784565_e4cc72f757_o.jpg",
    "url_type": "url_o",
    "wnid": "n03954731",
    "search_key": "woodworking plane",
    "search_engine": "flickr",
    "uploader": "becca",
    "date_upload_our_db": "2018-11-30 08:00:33",
    "date_taken": "2013-11-18 10:22:16",
    "date_upload_search_engine": "2013-11-18 00:34:58",
    "width": "1024",
    "height": "768",
    "max_taken_date": "2014-07-11",
    "max_uploaded_date": "2014-07-11",
    "min_taken_date": "2012-07-11",
    "min_uploaded_date": "2012-07-11",
    "search_sort": "date-posted-asc",
    "max_images": 200,
    "batch": "d97079811b7eeaffca23043afbdea0056967cba58c63f98654d01dbdc5e7a80b"
  },
  {
    "id_ours": "480042b8b5b86e86b57ef71a51d2b3fbd2c8a00a",
    "id_search_engine": "10922029013",
    "url": "https://farm3.staticflickr.com/2875/10922029013_c197237165_o.jpg",
    "url_type": "url_o",
    "wnid": "n03954731",
    "search_key": "woodworking plane",
    "search_engine": "flickr",
    "uploader": "becca",
    "date_upload_our_db": "2018-11-30 08:00:33",
    "date_taken": "2013-11-17 10:21:44",
    "date_upload_search_engine": "2013-11-18 00:34:54",
    "width": "1536",
    "height": "2048",
    "max_taken_date": "2014-07-11",
    "max_uploaded_date": "2014-07-11",
    "min_taken_date": "2012-07-11",
    "min_uploaded_date": "2012-07-11",
    "search_sort": "date-posted-asc",
    "max_images": 200,
    "batch": "d97079811b7eeaffca23043afbdea0056967cba58c63f98654d01dbdc5e7a80b"
  },
  {
    "id_ours": "d5c44ef0e63505711514ea95cea60dbb2fdf3b61",
    "id_search_engine": "10931528946",
    "url": "https://farm8.staticflickr.com/7365/10931528946_a2b324db73_k.jpg",
    "url_type": "url_k",
    "wnid": "n03954731",
    "search_key": "woodworking plane",
    "search_engine": "flickr",
    "uploader": "becca",
    "date_upload_our_db": "2018-11-30 08:00:33",
    "date_taken": "2013-11-18 14:48:28",
    "date_upload_search_engine": "2013-11-18 12:14:14",
    "width": 1365,
    "height": 2048,
    "max_taken_date": "2014-07-11",
    "max_uploaded_date": "2014-07-11",
    "min_taken_date": "2012-07-11",
    "min_uploaded_date": "2012-07-11",
    "search_sort": "date-posted-asc",
    "max_images": 200,
    "batch": "d97079811b7eeaffca23043afbdea0056967cba58c63f98654d01dbdc5e7a80b"
  },
  {
    "id_ours": "e646d64e0c3ba7bc0cb1d8d896851bb14b54ac2b",
    "id_search_engine": "11124505494",
    "url": "https://farm8.staticflickr.com/7390/11124505494_b16db1979c_o.jpg",
    "url_type": "url_o",
    "wnid": "n03954731",
    "search_key": "woodworking plane",
    "search_engine": "flickr",
    "uploader": "becca",
    "date_upload_our_db": "2018-11-30 08:00:33",
    "date_taken": "2013-11-28 15:36:31",
    "date_upload_search_engine": "2013-11-29 16:24:52",
    "width": 3391,
    "height": 2609,
    "max_taken_date": "2014-07-11",
    "max_uploaded_date": "2014-07-11",
    "min_taken_date": "2012-07-11",
    "min_uploaded_date": "2012-07-11",
    "search_sort": "date-posted-asc",
    "max_images": 200,
    "batch": "d97079811b7eeaffca23043afbdea0056967cba58c63f98654d01dbdc5e7a80b"
  },
  {
    "id_ours": "0563d516b1ca6f05f58839c8388565b3dda1361d",
    "id_search_engine": "11325352995",
    "url": "https://farm3.staticflickr.com/2841/11325352995_7597382df7_o.jpg",
    "url_type": "url_o",
    "wnid": "n03954731",
    "search_key": "woodworking plane",
    "search_engine": "flickr",
    "uploader": "becca",
    "date_upload_our_db": "2018-11-30 08:00:33",
    "date_taken": "2013-12-11 11:10:35",
    "date_upload_search_engine": "2013-12-11 08:10:35",
    "width": 640,
    "height": 640,
    "max_taken_date": "2014-07-11",
    "max_uploaded_date": "2014-07-11",
    "min_taken_date": "2012-07-11",
    "min_uploaded_date": "2012-07-11",
    "search_sort": "date-posted-asc",
    "max_images": 200,
    "batch": "d97079811b7eeaffca23043afbdea0056967cba58c63f98654d01dbdc5e7a80b"
  },
  {
    "id_ours": "0680467f9739db33af25d7d778442bfcd93341b4",
    "id_search_engine": "11657768384",
    "url": "https://farm4.staticflickr.com/3750/11657768384_19feb083e3_o.jpg",
    "url_type": "url_o",
    "wnid": "n03954731",
    "search_key": "woodworking plane",
    "search_engine": "flickr",
    "uploader": "becca",
    "date_upload_our_db": "2018-11-30 08:00:33",
    "date_taken": "2013-12-30 19:50:49",
    "date_upload_search_engine": "2013-12-30 16:50:49",
    "width": null,
    "height": null,
    "max_taken_date": "2014-07-11",
    "max_uploaded_date": "2014-07-11",
    "min_taken_date": "2012-07-11",
    "min_uploaded_date": "2012-07-11",
    "search_sort": "date-posted-asc",
    "max_images": 200,
    "batch": "d97079811b7eeaffca23043afbdea0056967cba58c63f98654d01dbdc5e7a80b"
  },
  {
    "id_ours": "3d511b5c6380a9e3092778cebfde550277fefe05",
    "id_search_engine": "11751792806",
    "url": "https://farm4.staticflickr.com/3731/11751792806_078cf03068_o.jpg",
    "url_type": "url_o",
    "wnid": "n03954731",
    "search_key": "woodworking plane",
    "search_engine": "flickr",
    "uploader": "becca",
    "date_upload_our_db": "2018-11-30 08:00:33",
    "date_taken": "2014-01-03 21:59:05",
    "date_upload_search_engine": "2014-01-04 05:02:40",
    "width": 3264,
    "height": 3264,
    "max_taken_date": "2014-07-11",
    "max_uploaded_date": "2014-07-11",
    "min_taken_date": "2012-07-11",
    "min_uploaded_date": "2012-07-11",
    "search_sort": "date-posted-asc",
    "max_images": 200,
    "batch": "d97079811b7eeaffca23043afbdea0056967cba58c63f98654d01dbdc5e7a80b"
  },
  {
    "id_ours": "60f3c988cd2c33ef5121fe0971daeee7a17cbfba",
    "id_search_engine": "11801051505",
    "url": "https://farm4.staticflickr.com/3737/11801051505_6dcfa1d158_o.jpg",
    "url_type": "url_o",
    "wnid": "n03954731",
    "search_key": "woodworking plane",
    "search_engine": "flickr",
    "uploader": "becca",
    "date_upload_our_db": "2018-11-30 08:00:33",
    "date_taken": "2014-01-06 08:27:55",
    "date_upload_search_engine": "2014-01-06 08:27:55",
    "width": 640,
    "height": 640,
    "max_taken_date": "2014-07-11",
    "max_uploaded_date": "2014-07-11",
    "min_taken_date": "2012-07-11",
    "min_uploaded_date": "2012-07-11",
    "search_sort": "date-posted-asc",
    "max_images": 200,
    "batch": "d97079811b7eeaffca23043afbdea0056967cba58c63f98654d01dbdc5e7a80b"
  },
  {
    "id_ours": "de3e4d509871f974d7da5ecd08660eae398333e8",
    "id_search_engine": "11890112026",
    "url": "https://farm4.staticflickr.com/3676/11890112026_8b3f7da2dc_o.jpg",
    "url_type": "url_o",
    "wnid": "n03954731",
    "search_key": "woodworking plane",
    "search_engine": "flickr",
    "uploader": "becca",
    "date_upload_our_db": "2018-11-30 08:00:33",
    "date_taken": "2014-01-08 18:59:40",
    "date_upload_search_engine": "2014-01-11 08:29:04",
    "width": 3264,
    "height": 2448,
    "max_taken_date": "2014-07-11",
    "max_uploaded_date": "2014-07-11",
    "min_taken_date": "2012-07-11",
    "min_uploaded_date": "2012-07-11",
    "search_sort": "date-posted-asc",
    "max_images": 200,
    "batch": "d97079811b7eeaffca23043afbdea0056967cba58c63f98654d01dbdc5e7a80b"
  },
  {
    "id_ours": "e9ac2094949622289f29afe8fc5d31d19b9a101e",
    "id_search_engine": "12113637726",
    "url": "https://farm4.staticflickr.com/3777/12113637726_005cf4e209_o.jpg",
    "url_type": "url_o",
    "wnid": "n03954731",
    "search_key": "woodworking plane",
    "search_engine": "flickr",
    "uploader": "becca",
    "date_upload_our_db": "2018-11-30 08:00:33",
    "date_taken": "2014-01-23 23:42:29",
    "date_upload_search_engine": "2014-01-23 21:48:17",
    "width": null,
    "height": null,
    "max_taken_date": "2014-07-11",
    "max_uploaded_date": "2014-07-11",
    "min_taken_date": "2012-07-11",
    "min_uploaded_date": "2012-07-11",
    "search_sort": "date-posted-asc",
    "max_images": 200,
    "batch": "d97079811b7eeaffca23043afbdea0056967cba58c63f98654d01dbdc5e7a80b"
  },
  {
    "id_ours": "55ac1c35d9c91b2a7b7976f14aa61298b9cc5b33",
    "id_search_engine": "12113379174",
    "url": "https://farm4.staticflickr.com/3811/12113379174_c88d529dc3_o.jpg",
    "url_type": "url_o",
    "wnid": "n03954731",
    "search_key": "woodworking plane",
    "search_engine": "flickr",
    "uploader": "becca",
    "date_upload_our_db": "2018-11-30 08:00:33",
    "date_taken": "2013-11-24 21:39:44",
    "date_upload_search_engine": "2014-01-23 21:48:20",
    "width": null,
    "height": null,
    "max_taken_date": "2014-07-11",
    "max_uploaded_date": "2014-07-11",
    "min_taken_date": "2012-07-11",
    "min_uploaded_date": "2012-07-11",
    "search_sort": "date-posted-asc",
    "max_images": 200,
    "batch": "d97079811b7eeaffca23043afbdea0056967cba58c63f98654d01dbdc5e7a80b"
  },
  {
    "id_ours": "0c5195dab4841e8b7df8839c8ed0d3c03ec85af7",
    "id_search_engine": "12374544794",
    "url": "https://farm6.staticflickr.com/5528/12374544794_dbf37c2722_o.jpg",
    "url_type": "url_o",
    "wnid": "n03954731",
    "search_key": "woodworking plane",
    "search_engine": "flickr",
    "uploader": "becca",
    "date_upload_our_db": "2018-11-30 08:00:33",
    "date_taken": "2014-02-06 11:55:00",
    "date_upload_search_engine": "2014-02-07 17:54:12",
    "width": 4320,
    "height": 3240,
    "max_taken_date": "2014-07-11",
    "max_uploaded_date": "2014-07-11",
    "min_taken_date": "2012-07-11",
    "min_uploaded_date": "2012-07-11",
    "search_sort": "date-posted-asc",
    "max_images": 200,
    "batch": "d97079811b7eeaffca23043afbdea0056967cba58c63f98654d01dbdc5e7a80b"
  },
  {
    "id_ours": "5db2378149785da2b19f225cc6e1c26ad93b2464",
    "id_search_engine": "12374315774",
    "url": "https://farm3.staticflickr.com/2832/12374315774_8fdcf765b0_o.jpg",
    "url_type": "url_o",
    "wnid": "n03954731",
    "search_key": "woodworking plane",
    "search_engine": "flickr",
    "uploader": "becca",
    "date_upload_our_db": "2018-11-30 08:00:33",
    "date_taken": "2014-02-06 11:54:37",
    "date_upload_search_engine": "2014-02-07 17:54:11",
    "width": 4320,
    "height": 3240,
    "max_taken_date": "2014-07-11",
    "max_uploaded_date": "2014-07-11",
    "min_taken_date": "2012-07-11",
    "min_uploaded_date": "2012-07-11",
    "search_sort": "date-posted-asc",
    "max_images": 200,
    "batch": "d97079811b7eeaffca23043afbdea0056967cba58c63f98654d01dbdc5e7a80b"
  },
  {
    "id_ours": "9bb4333b57173818e4c7c2bc25f34442505a9d5a",
    "id_search_engine": "12374556964",
    "url": "https://farm4.staticflickr.com/3702/12374556964_0fe8dca311_o.jpg",
    "url_type": "url_o",
    "wnid": "n03954731",
    "search_key": "woodworking plane",
    "search_engine": "flickr",
    "uploader": "becca",
    "date_upload_our_db": "2018-11-30 08:00:33",
    "date_taken": "2014-02-06 11:54:18",
    "date_upload_search_engine": "2014-02-07 17:54:09",
    "width": 4320,
    "height": 3240,
    "max_taken_date": "2014-07-11",
    "max_uploaded_date": "2014-07-11",
    "min_taken_date": "2012-07-11",
    "min_uploaded_date": "2012-07-11",
    "search_sort": "date-posted-asc",
    "max_images": 200,
    "batch": "d97079811b7eeaffca23043afbdea0056967cba58c63f98654d01dbdc5e7a80b"
  },
  {
    "id_ours": "c4eb01601cc7c397f17fe922282ed8efc66ba053",
    "id_search_engine": "12374251523",
    "url": "https://farm8.staticflickr.com/7318/12374251523_d1f22c4817_o.jpg",
    "url_type": "url_o",
    "wnid": "n03954731",
    "search_key": "woodworking plane",
    "search_engine": "flickr",
    "uploader": "becca",
    "date_upload_our_db": "2018-11-30 08:00:33",
    "date_taken": "2014-02-06 11:54:49",
    "date_upload_search_engine": "2014-02-07 17:54:12",
    "width": 4320,
    "height": 3240,
    "max_taken_date": "2014-07-11",
    "max_uploaded_date": "2014-07-11",
    "min_taken_date": "2012-07-11",
    "min_uploaded_date": "2012-07-11",
    "search_sort": "date-posted-asc",
    "max_images": 200,
    "batch": "d97079811b7eeaffca23043afbdea0056967cba58c63f98654d01dbdc5e7a80b"
  },
  {
    "id_ours": "ba90f413c650982ae51d497afd8d19540a09b6d6",
    "id_search_engine": "12374554124",
    "url": "https://farm4.staticflickr.com/3802/12374554124_3103c29af8_o.jpg",
    "url_type": "url_o",
    "wnid": "n03954731",
    "search_key": "woodworking plane",
    "search_engine": "flickr",
    "uploader": "becca",
    "date_upload_our_db": "2018-11-30 08:00:33",
    "date_taken": "2014-02-06 11:54:23",
    "date_upload_search_engine": "2014-02-07 17:54:10",
    "width": 4320,
    "height": 3240,
    "max_taken_date": "2014-07-11",
    "max_uploaded_date": "2014-07-11",
    "min_taken_date": "2012-07-11",
    "min_uploaded_date": "2012-07-11",
    "search_sort": "date-posted-asc",
    "max_images": 200,
    "batch": "d97079811b7eeaffca23043afbdea0056967cba58c63f98654d01dbdc5e7a80b"
  },
  {
    "id_ours": "42de3bdcebcae13fa177c111e3f6cc64dd8b1429",
    "id_search_engine": "12642480184",
    "url": "https://farm6.staticflickr.com/5473/12642480184_5dccce755c_c.jpg",
    "url_type": "url_c",
    "wnid": "n03954731",
    "search_key": "woodworking plane",
    "search_engine": "flickr",
    "uploader": "becca",
    "date_upload_our_db": "2018-11-30 08:00:33",
    "date_taken": "2014-02-19 16:02:41",
    "date_upload_search_engine": "2014-02-19 13:04:30",
    "width": 800,
    "height": 533,
    "max_taken_date": "2014-07-11",
    "max_uploaded_date": "2014-07-11",
    "min_taken_date": "2012-07-11",
    "min_uploaded_date": "2012-07-11",
    "search_sort": "date-posted-asc",
    "max_images": 200,
    "batch": "d97079811b7eeaffca23043afbdea0056967cba58c63f98654d01dbdc5e7a80b"
  },
  {
    "id_ours": "f54d4587033546ba8b738890f2247edfa5221492",
    "id_search_engine": "12945793145",
    "url": "https://farm4.staticflickr.com/3793/12945793145_e8cdb5bece_o.jpg",
    "url_type": "url_o",
    "wnid": "n03954731",
    "search_key": "woodworking plane",
    "search_engine": "flickr",
    "uploader": "becca",
    "date_upload_our_db": "2018-11-30 08:00:33",
    "date_taken": "2014-03-04 12:32:41",
    "date_upload_search_engine": "2014-03-05 01:58:13",
    "width": 3264,
    "height": 2448,
    "max_taken_date": "2014-07-11",
    "max_uploaded_date": "2014-07-11",
    "min_taken_date": "2012-07-11",
    "min_uploaded_date": "2012-07-11",
    "search_sort": "date-posted-asc",
    "max_images": 200,
    "batch": "d97079811b7eeaffca23043afbdea0056967cba58c63f98654d01dbdc5e7a80b"
  },
  {
    "id_ours": "e0b4f1e70a3dead6de86fff5e7cd146236f097e9",
    "id_search_engine": "12959801114",
    "url": "https://farm3.staticflickr.com/2679/12959801114_afb892144c_o.jpg",
    "url_type": "url_o",
    "wnid": "n03954731",
    "search_key": "woodworking plane",
    "search_engine": "flickr",
    "uploader": "becca",
    "date_upload_our_db": "2018-11-30 08:00:33",
    "date_taken": "2014-03-04 10:30:08",
    "date_upload_search_engine": "2014-03-05 16:47:08",
    "width": 5472,
    "height": 3072,
    "max_taken_date": "2014-07-11",
    "max_uploaded_date": "2014-07-11",
    "min_taken_date": "2012-07-11",
    "min_uploaded_date": "2012-07-11",
    "search_sort": "date-posted-asc",
    "max_images": 200,
    "batch": "d97079811b7eeaffca23043afbdea0056967cba58c63f98654d01dbdc5e7a80b"
  },
  {
    "id_ours": "24bf16968b45294879cfc3c28bb572d806fa30d2",
    "id_search_engine": "12959780704",
    "url": "https://farm3.staticflickr.com/2247/12959780704_02774bb599_o.jpg",
    "url_type": "url_o",
    "wnid": "n03954731",
    "search_key": "woodworking plane",
    "search_engine": "flickr",
    "uploader": "becca",
    "date_upload_our_db": "2018-11-30 08:00:33",
    "date_taken": "2014-03-04 10:32:29",
    "date_upload_search_engine": "2014-03-05 16:47:11",
    "width": 5200,
    "height": 2924,
    "max_taken_date": "2014-07-11",
    "max_uploaded_date": "2014-07-11",
    "min_taken_date": "2012-07-11",
    "min_uploaded_date": "2012-07-11",
    "search_sort": "date-posted-asc",
    "max_images": 200,
    "batch": "d97079811b7eeaffca23043afbdea0056967cba58c63f98654d01dbdc5e7a80b"
  },
  {
    "id_ours": "a61c66f373b18a2059a6657525c8103e6d17bd72",
    "id_search_engine": "12959795904",
    "url": "https://farm3.staticflickr.com/2056/12959795904_ff5625f71e_o.jpg",
    "url_type": "url_o",
    "wnid": "n03954731",
    "search_key": "woodworking plane",
    "search_engine": "flickr",
    "uploader": "becca",
    "date_upload_our_db": "2018-11-30 08:00:33",
    "date_taken": "2014-03-04 10:28:39",
    "date_upload_search_engine": "2014-03-05 16:47:09",
    "width": 5155,
    "height": 2894,
    "max_taken_date": "2014-07-11",
    "max_uploaded_date": "2014-07-11",
    "min_taken_date": "2012-07-11",
    "min_uploaded_date": "2012-07-11",
    "search_sort": "date-posted-asc",
    "max_images": 200,
    "batch": "d97079811b7eeaffca23043afbdea0056967cba58c63f98654d01dbdc5e7a80b"
  },
  {
    "id_ours": "3c3a1ee3ff9c51214e3857e3e5f8bce8ccb64ad0",
    "id_search_engine": "13265040155",
    "url": "https://farm8.staticflickr.com/7097/13265040155_baeea9e6d4_o.jpg",
    "url_type": "url_o",
    "wnid": "n03954731",
    "search_key": "woodworking plane",
    "search_engine": "flickr",
    "uploader": "becca",
    "date_upload_our_db": "2018-11-30 08:00:33",
    "date_taken": "2014-03-18 14:51:46",
    "date_upload_search_engine": "2014-03-19 06:23:48",
    "width": 3264,
    "height": 2448,
    "max_taken_date": "2014-07-11",
    "max_uploaded_date": "2014-07-11",
    "min_taken_date": "2012-07-11",
    "min_uploaded_date": "2012-07-11",
    "search_sort": "date-posted-asc",
    "max_images": 200,
    "batch": "d97079811b7eeaffca23043afbdea0056967cba58c63f98654d01dbdc5e7a80b"
  },
  {
    "id_ours": "f6542ebacfcd1e185ec284de3414cc005ef0764b",
    "id_search_engine": "13264890225",
    "url": "https://farm4.staticflickr.com/3773/13264890225_d9f6773164_o.jpg",
    "url_type": "url_o",
    "wnid": "n03954731",
    "search_key": "woodworking plane",
    "search_engine": "flickr",
    "uploader": "becca",
    "date_upload_our_db": "2018-11-30 08:00:33",
    "date_taken": "2014-03-18 15:04:21",
    "date_upload_search_engine": "2014-03-19 06:24:00",
    "width": 3264,
    "height": 2448,
    "max_taken_date": "2014-07-11",
    "max_uploaded_date": "2014-07-11",
    "min_taken_date": "2012-07-11",
    "min_uploaded_date": "2012-07-11",
    "search_sort": "date-posted-asc",
    "max_images": 200,
    "batch": "d97079811b7eeaffca23043afbdea0056967cba58c63f98654d01dbdc5e7a80b"
  },
  {
    "id_ours": "1a1b09cb82d753669247bcf34951ed3ff0add24d",
    "id_search_engine": "13393213145",
    "url": "https://farm8.staticflickr.com/7314/13393213145_120200f78f_o.jpg",
    "url_type": "url_o",
    "wnid": "n03954731",
    "search_key": "woodworking plane",
    "search_engine": "flickr",
    "uploader": "becca",
    "date_upload_our_db": "2018-11-30 08:00:33",
    "date_taken": "2014-03-24 19:57:57",
    "date_upload_search_engine": "2014-03-24 18:00:42",
    "width": 1500,
    "height": 1000,
    "max_taken_date": "2014-07-11",
    "max_uploaded_date": "2014-07-11",
    "min_taken_date": "2012-07-11",
    "min_uploaded_date": "2012-07-11",
    "search_sort": "date-posted-asc",
    "max_images": 200,
    "batch": "d97079811b7eeaffca23043afbdea0056967cba58c63f98654d01dbdc5e7a80b"
  },
  {
    "id_ours": "6f8b072506dc04886336d5838eb084f8af9b3885",
    "id_search_engine": "13393344443",
    "url": "https://farm4.staticflickr.com/3832/13393344443_dc45289b03_o.jpg",
    "url_type": "url_o",
    "wnid": "n03954731",
    "search_key": "woodworking plane",
    "search_engine": "flickr",
    "uploader": "becca",
    "date_upload_our_db": "2018-11-30 08:00:33",
    "date_taken": "2014-03-24 19:54:54",
    "date_upload_search_engine": "2014-03-24 18:00:46",
    "width": 1000,
    "height": 1500,
    "max_taken_date": "2014-07-11",
    "max_uploaded_date": "2014-07-11",
    "min_taken_date": "2012-07-11",
    "min_uploaded_date": "2012-07-11",
    "search_sort": "date-posted-asc",
    "max_images": 200,
    "batch": "d97079811b7eeaffca23043afbdea0056967cba58c63f98654d01dbdc5e7a80b"
  },
  {
    "id_ours": "42484deb41bc0145292e45eb8b57b02b91c0b6d3",
    "id_search_engine": "13393211595",
    "url": "https://farm4.staticflickr.com/3673/13393211595_b9871373d1_o.jpg",
    "url_type": "url_o",
    "wnid": "n03954731",
    "search_key": "woodworking plane",
    "search_engine": "flickr",
    "uploader": "becca",
    "date_upload_our_db": "2018-11-30 08:00:33",
    "date_taken": "2014-03-24 20:03:08",
    "date_upload_search_engine": "2014-03-24 18:00:44",
    "width": 1500,
    "height": 1000,
    "max_taken_date": "2014-07-11",
    "max_uploaded_date": "2014-07-11",
    "min_taken_date": "2012-07-11",
    "min_uploaded_date": "2012-07-11",
    "search_sort": "date-posted-asc",
    "max_images": 200,
    "batch": "d97079811b7eeaffca23043afbdea0056967cba58c63f98654d01dbdc5e7a80b"
  },
  {
    "id_ours": "7889804f575a87a758feebe2411e87737ef2b951",
    "id_search_engine": "13666645055",
    "url": "https://farm8.staticflickr.com/7278/13666645055_70fc4f156f_k.jpg",
    "url_type": "url_k",
    "wnid": "n03954731",
    "search_key": "woodworking plane",
    "search_engine": "flickr",
    "uploader": "becca",
    "date_upload_our_db": "2018-11-30 08:00:33",
    "date_taken": "2014-03-28 11:30:11",
    "date_upload_search_engine": "2014-04-06 06:30:44",
    "width": 2048,
    "height": 1365,
    "max_taken_date": "2014-07-11",
    "max_uploaded_date": "2014-07-11",
    "min_taken_date": "2012-07-11",
    "min_uploaded_date": "2012-07-11",
    "search_sort": "date-posted-asc",
    "max_images": 200,
    "batch": "d97079811b7eeaffca23043afbdea0056967cba58c63f98654d01dbdc5e7a80b"
  },
  {
    "id_ours": "a2abe14be7bc1cad8acacc33ceb99bccccd38e38",
    "id_search_engine": "13666831165",
    "url": "https://farm4.staticflickr.com/3719/13666831165_c29388131c_k.jpg",
    "url_type": "url_k",
    "wnid": "n03954731",
    "search_key": "woodworking plane",
    "search_engine": "flickr",
    "uploader": "becca",
    "date_upload_our_db": "2018-11-30 08:00:33",
    "date_taken": "2014-03-28 11:29:27",
    "date_upload_search_engine": "2014-04-06 06:39:13",
    "width": null,
    "height": null,
    "max_taken_date": "2014-07-11",
    "max_uploaded_date": "2014-07-11",
    "min_taken_date": "2012-07-11",
    "min_uploaded_date": "2012-07-11",
    "search_sort": "date-posted-asc",
    "max_images": 200,
    "batch": "d97079811b7eeaffca23043afbdea0056967cba58c63f98654d01dbdc5e7a80b"
  },
  {
    "id_ours": "abbc8903aa4fe78117c00b03a2cc66621078eb5b",
    "id_search_engine": "13666824403",
    "url": "https://farm8.staticflickr.com/7442/13666824403_1c9f6c69bd_k.jpg",
    "url_type": "url_k",
    "wnid": "n03954731",
    "search_key": "woodworking plane",
    "search_engine": "flickr",
    "uploader": "becca",
    "date_upload_our_db": "2018-11-30 08:00:33",
    "date_taken": "2014-03-28 14:36:54",
    "date_upload_search_engine": "2014-04-06 06:37:15",
    "width": 2048,
    "height": 1479,
    "max_taken_date": "2014-07-11",
    "max_uploaded_date": "2014-07-11",
    "min_taken_date": "2012-07-11",
    "min_uploaded_date": "2012-07-11",
    "search_sort": "date-posted-asc",
    "max_images": 200,
    "batch": "d97079811b7eeaffca23043afbdea0056967cba58c63f98654d01dbdc5e7a80b"
  },
  {
    "id_ours": "917b22c1c262c6b804c77a2ba482ee9b0b18374e",
    "id_search_engine": "13969772704",
    "url": "https://farm8.staticflickr.com/7202/13969772704_fa8f77d61f_o.jpg",
    "url_type": "url_o",
    "wnid": "n03954731",
    "search_key": "woodworking plane",
    "search_engine": "flickr",
    "uploader": "becca",
    "date_upload_our_db": "2018-11-30 08:00:33",
    "date_taken": "2014-04-21 13:38:48",
    "date_upload_search_engine": "2014-04-22 06:41:27",
    "width": 3264,
    "height": 2448,
    "max_taken_date": "2014-07-11",
    "max_uploaded_date": "2014-07-11",
    "min_taken_date": "2012-07-11",
    "min_uploaded_date": "2012-07-11",
    "search_sort": "date-posted-asc",
    "max_images": 200,
    "batch": "d97079811b7eeaffca23043afbdea0056967cba58c63f98654d01dbdc5e7a80b"
  },
  {
    "id_ours": "dc27666cf2aeee054923acc11854054b7d2bb9b1",
    "id_search_engine": "13989307403",
    "url": "https://farm6.staticflickr.com/5144/13989307403_2502793515_o.jpg",
    "url_type": "url_o",
    "wnid": "n03954731",
    "search_key": "woodworking plane",
    "search_engine": "flickr",
    "uploader": "becca",
    "date_upload_our_db": "2018-11-30 08:00:33",
    "date_taken": "2014-04-21 13:40:48",
    "date_upload_search_engine": "2014-04-22 06:41:28",
    "width": "3264",
    "height": "2448",
    "max_taken_date": "2014-07-11",
    "max_uploaded_date": "2014-07-11",
    "min_taken_date": "2012-07-11",
    "min_uploaded_date": "2012-07-11",
    "search_sort": "date-posted-asc",
    "max_images": 200,
    "batch": "d97079811b7eeaffca23043afbdea0056967cba58c63f98654d01dbdc5e7a80b"
  },
  {
    "id_ours": "c0b955dec22d00b8491d36d9ef03cb6a071c8bad",
    "id_search_engine": "14099221524",
    "url": "https://farm3.staticflickr.com/2940/14099221524_d036570b0a_o.jpg",
    "url_type": "url_o",
    "wnid": "n03954731",
    "search_key": "woodworking plane",
    "search_engine": "flickr",
    "uploader": "becca",
    "date_upload_our_db": "2018-11-30 08:00:33",
    "date_taken": "2014-05-03 16:29:39",
    "date_upload_search_engine": "2014-05-03 13:29:39",
    "width": null,
    "height": null,
    "max_taken_date": "2014-07-11",
    "max_uploaded_date": "2014-07-11",
    "min_taken_date": "2012-07-11",
    "min_uploaded_date": "2012-07-11",
    "search_sort": "date-posted-asc",
    "max_images": 200,
    "batch": "d97079811b7eeaffca23043afbdea0056967cba58c63f98654d01dbdc5e7a80b"
  },
  {
    "id_ours": "aef2e586b4ebd3fd196b900c5447cefe2a5cc2c1",
    "id_search_engine": "14114112006",
    "url": "https://farm8.staticflickr.com/7357/14114112006_e13555746d_z.jpg",
    "url_type": "url_z",
    "wnid": "n03954731",
    "search_key": "woodworking plane",
    "search_engine": "flickr",
    "uploader": "becca",
    "date_upload_our_db": "2018-11-30 08:00:33",
    "date_taken": "2014-05-08 05:46:19",
    "date_upload_search_engine": "2014-05-08 05:46:19",
    "width": 500,
    "height": 500,
    "max_taken_date": "2014-07-11",
    "max_uploaded_date": "2014-07-11",
    "min_taken_date": "2012-07-11",
    "min_uploaded_date": "2012-07-11",
    "search_sort": "date-posted-asc",
    "max_images": 200,
    "batch": "d97079811b7eeaffca23043afbdea0056967cba58c63f98654d01dbdc5e7a80b"
  },
  {
    "id_ours": "ee0744eb01d446de39bd3e9de302021f2a7acfbd",
    "id_search_engine": "13987657529",
    "url": "https://farm8.staticflickr.com/7358/13987657529_00c495b9b5_c.jpg",
    "url_type": "url_c",
    "wnid": "n03954731",
    "search_key": "woodworking plane",
    "search_engine": "flickr",
    "uploader": "becca",
    "date_upload_our_db": "2018-11-30 08:00:33",
    "date_taken": "2014-05-13 10:59:00",
    "date_upload_search_engine": "2014-05-12 20:31:44",
    "width": null,
    "height": null,
    "max_taken_date": "2014-07-11",
    "max_uploaded_date": "2014-07-11",
    "min_taken_date": "2012-07-11",
    "min_uploaded_date": "2012-07-11",
    "search_sort": "date-posted-asc",
    "max_images": 200,
    "batch": "d97079811b7eeaffca23043afbdea0056967cba58c63f98654d01dbdc5e7a80b"
  },
  {
    "id_ours": "e01cfae3cbb7dfbac81a83e6572cc8b75e5355aa",
    "id_search_engine": "14322376281",
    "url": "https://farm6.staticflickr.com/5550/14322376281_205b74d463_o.jpg",
    "url_type": "url_o",
    "wnid": "n03954731",
    "search_key": "woodworking plane",
    "search_engine": "flickr",
    "uploader": "becca",
    "date_upload_our_db": "2018-11-30 08:00:33",
    "date_taken": "2014-06-01 20:44:51",
    "date_upload_search_engine": "2014-06-01 19:42:49",
    "width": 2000,
    "height": 1333,
    "max_taken_date": "2014-07-11",
    "max_uploaded_date": "2014-07-11",
    "min_taken_date": "2012-07-11",
    "min_uploaded_date": "2012-07-11",
    "search_sort": "date-posted-asc",
    "max_images": 200,
    "batch": "d97079811b7eeaffca23043afbdea0056967cba58c63f98654d01dbdc5e7a80b"
  },
  {
    "id_ours": "819257f25fee0918c6862a21b13eaa12eb0afc93",
    "id_search_engine": "14139091810",
    "url": "https://farm3.staticflickr.com/2899/14139091810_e0ee1af0b0_o.jpg",
    "url_type": "url_o",
    "wnid": "n03954731",
    "search_key": "woodworking plane",
    "search_engine": "flickr",
    "uploader": "becca",
    "date_upload_our_db": "2018-11-30 08:00:33",
    "date_taken": "2014-06-01 20:44:30",
    "date_upload_search_engine": "2014-06-01 19:42:50",
    "width": 2000,
    "height": 1333,
    "max_taken_date": "2014-07-11",
    "max_uploaded_date": "2014-07-11",
    "min_taken_date": "2012-07-11",
    "min_uploaded_date": "2012-07-11",
    "search_sort": "date-posted-asc",
    "max_images": 200,
    "batch": "d97079811b7eeaffca23043afbdea0056967cba58c63f98654d01dbdc5e7a80b"
  },
  {
    "id_ours": "79369d10f473e7fd7620b4d02ee0c58aa0d3050f",
    "id_search_engine": "14197729979",
    "url": "https://farm6.staticflickr.com/5586/14197729979_e6d7e0c398_o.jpg",
    "url_type": "url_o",
    "wnid": "n03954731",
    "search_key": "woodworking plane",
    "search_engine": "flickr",
    "uploader": "becca",
    "date_upload_our_db": "2018-11-30 08:00:33",
    "date_taken": "2014-05-30 11:44:43",
    "date_upload_search_engine": "2014-06-09 11:07:52",
    "width": 4000,
    "height": 3000,
    "max_taken_date": "2014-07-11",
    "max_uploaded_date": "2014-07-11",
    "min_taken_date": "2012-07-11",
    "min_uploaded_date": "2012-07-11",
    "search_sort": "date-posted-asc",
    "max_images": 200,
    "batch": "d97079811b7eeaffca23043afbdea0056967cba58c63f98654d01dbdc5e7a80b"
  },
  {
    "id_ours": "f650eed12258c57d5a931b85b58572f5a0ef2e07",
    "id_search_engine": "16138004573",
    "url": "https://farm8.staticflickr.com/7594/16138004573_c89a5c5f96_o.jpg",
    "url_type": "url_o",
    "wnid": "n03954731",
    "search_key": "woodworking plane",
    "search_engine": "flickr",
    "uploader": "becca",
    "date_upload_our_db": "2018-11-30 08:00:33",
    "date_taken": "2013-10-13 17:29:37",
    "date_upload_search_engine": "2015-03-08 15:06:06",
    "width": 3264,
    "height": 2448,
    "max_taken_date": "2014-07-11",
    "max_uploaded_date": "2014-07-11",
    "min_taken_date": "2012-07-11",
    "min_uploaded_date": "2012-07-11",
    "search_sort": "date-posted-asc",
    "max_images": 200,
    "batch": "d97079811b7eeaffca23043afbdea0056967cba58c63f98654d01dbdc5e7a80b"
  },
  {
    "id_ours": "879eea875decca637866bc59f572989a0cb66e12",
    "id_search_engine": "21119684468",
    "url": "https://farm1.staticflickr.com/654/21119684468_64de0f167f_o.jpg",
    "url_type": "url_o",
    "wnid": "n03954731",
    "search_key": "woodworking plane",
    "search_engine": "flickr",
    "uploader": "becca",
    "date_upload_our_db": "2018-11-30 08:00:33",
    "date_taken": "2014-01-19 18:28:44",
    "date_upload_search_engine": "2015-09-10 16:32:39",
    "width": 800,
    "height": 532,
    "max_taken_date": "2014-07-11",
    "max_uploaded_date": "2014-07-11",
    "min_taken_date": "2012-07-11",
    "min_uploaded_date": "2012-07-11",
    "search_sort": "date-posted-asc",
    "max_images": 200,
    "batch": "d97079811b7eeaffca23043afbdea0056967cba58c63f98654d01dbdc5e7a80b"
  },
  {
    "id_ours": "469f3d9d5afa1d2b5c5eadba10af8c413b52175b",
    "id_search_engine": "22560301946",
    "url": "https://farm1.staticflickr.com/587/22560301946_0cdcc829d1_o.jpg",
    "url_type": "url_o",
    "wnid": "n03954731",
    "search_key": "woodworking plane",
    "search_engine": "flickr",
    "uploader": "becca",
    "date_upload_our_db": "2018-11-30 08:00:33",
    "date_taken": "2013-11-06 15:16:18",
    "date_upload_search_engine": "2015-10-29 16:11:33",
    "width": 1708,
    "height": 2648,
    "max_taken_date": "2014-07-11",
    "max_uploaded_date": "2014-07-11",
    "min_taken_date": "2012-07-11",
    "min_uploaded_date": "2012-07-11",
    "search_sort": "date-posted-asc",
    "max_images": 200,
    "batch": "d97079811b7eeaffca23043afbdea0056967cba58c63f98654d01dbdc5e7a80b"
  },
  {
    "id_ours": "7b8a0975a5637dbc65c4c635d5169ac5ee9672b5",
    "id_search_engine": "22586293395",
    "url": "https://farm1.staticflickr.com/762/22586293395_fae17c4434_o.jpg",
    "url_type": "url_o",
    "wnid": "n03954731",
    "search_key": "woodworking plane",
    "search_engine": "flickr",
    "uploader": "becca",
    "date_upload_our_db": "2018-11-30 08:00:33",
    "date_taken": "2013-11-06 15:17:34",
    "date_upload_search_engine": "2015-10-29 16:11:30",
    "width": 2082,
    "height": 1526,
    "max_taken_date": "2014-07-11",
    "max_uploaded_date": "2014-07-11",
    "min_taken_date": "2012-07-11",
    "min_uploaded_date": "2012-07-11",
    "search_sort": "date-posted-asc",
    "max_images": 200,
    "batch": "d97079811b7eeaffca23043afbdea0056967cba58c63f98654d01dbdc5e7a80b"
  },
  {
    "id_ours": "1eda7d048166c763e8ac9b90f63c3f933ce98381",
    "id_search_engine": "29468035893",
    "url": "https://farm6.staticflickr.com/5194/29468035893_dc5e80c006_k.jpg",
    "url_type": "url_k",
    "wnid": "n03954731",
    "search_key": "woodworking plane",
    "search_engine": "flickr",
    "uploader": "becca",
    "date_upload_our_db": "2018-11-30 08:00:33",
    "date_taken": "2013-10-20 18:59:50",
    "date_upload_search_engine": "2016-10-03 12:20:25",
    "width": 2048,
    "height": 1325,
    "max_taken_date": "2014-07-11",
    "max_uploaded_date": "2014-07-11",
    "min_taken_date": "2012-07-11",
    "min_uploaded_date": "2012-07-11",
    "search_sort": "date-posted-asc",
    "max_images": 200,
    "batch": "d97079811b7eeaffca23043afbdea0056967cba58c63f98654d01dbdc5e7a80b"
  },
  {
    "id_ours": "4ed669f8519f4770866f2e4fa88671ca9ec6c792",
    "id_search_engine": "38369983676",
    "url": "https://farm5.staticflickr.com/4522/38369983676_980e18dc88_o.jpg",
    "url_type": "url_o",
    "wnid": "n03954731",
    "search_key": "woodworking plane",
    "search_engine": "flickr",
    "uploader": "becca",
    "date_upload_our_db": "2018-11-30 08:00:33",
    "date_taken": "2012-09-17 09:51:14",
    "date_upload_search_engine": "2017-11-14 16:06:11",
    "width": 3400,
    "height": 3400,
    "max_taken_date": "2014-07-11",
    "max_uploaded_date": "2014-07-11",
    "min_taken_date": "2012-07-11",
    "min_uploaded_date": "2012-07-11",
    "search_sort": "date-posted-asc",
    "max_images": 200,
    "batch": "d97079811b7eeaffca23043afbdea0056967cba58c63f98654d01dbdc5e7a80b"
  },
  {
    "id_ours": "2bb9bf77ffa845b794d06e0460bf2beb38d9f350",
    "id_search_engine": "8470576979",
    "url": "https://farm9.staticflickr.com/8510/8470576979_6ed12ee5eb_o.jpg",
    "url_type": "url_o",
    "wnid": "n03954731",
    "search_key": "woodworking plane",
    "search_engine": "flickr",
    "uploader": "becca",
    "date_upload_our_db": "2018-11-30 08:00:33",
    "date_taken": "2013-02-13 10:16:05",
    "date_upload_search_engine": "2013-02-13 10:16:05",
    "width": "1024",
    "height": "768",
    "max_taken_date": "2014-07-11",
    "max_uploaded_date": "2014-07-11",
    "min_taken_date": "2012-07-11",
    "min_uploaded_date": "2012-07-11",
    "search_sort": "date-posted-asc",
    "max_images": 200,
    "batch": "d97079811b7eeaffca23043afbdea0056967cba58c63f98654d01dbdc5e7a80b"
  }
]